Workbook
Name _1: #REF!
Name _1: #REF!
Name _1: #REF!
Name _2: #REF!
Name _2: #REF!
Name _2: #REF!
Name _44: #REF!
Name _44: #REF!
Name _44: #REF!
Name a: #REF!
Name a: #REF!
Name a: #REF!
Name aa: #REF!
Name aa: #REF!
Name aa: #REF!
Name aaa: #REF!
Name aaa: #REF!
Name aaa: #REF!
Name aaaa: #REF!
Name APP: #REF!
Name b: #REF!
Name bb: #REF!
Name c_: #REF!
Name cc: #REF!
Name d: #REF!
Name dd: #REF!
Name e: #REF!
Name f: #REF!
Name ff: #REF!
Name fin: [2]CashFlow!#REF!
Name fin: [3]CashFlow!#REF!
Name fin: [4]CashFlow!#REF!
Name finn: [2]CashFlow!#REF!
Name finn: [3]CashFlow!#REF!
Name finn: [4]CashFlow!#REF!
Name g: Assumpt!$A$2:$W$84
Name h: #REF!
Name h: #REF!
Name h: #REF!
Name HD_VEH_POP_by_Phase_veh_power: #REF!
Name HD_VEH_POP_by_Phase_veh_power: #REF!
Name HD_VEH_POP_by_Phase_veh_power: #REF!
Name j: #REF!
Name j: #REF!
Name j: #REF!
Name m: #REF!
Name modelyear_inspected_by_year: #REF!
Name nn: #REF!
Name PTSum: [5]Summary!#REF!
Name PTSum: [5]Summary!#REF!
Name PTSum: [5]Summary!#REF!
Name rate: '[6]IT Hours'!$K$3:$L$6
Name Rate1: '[6]IT Hours'!$L$3:$M$6
Name rates: [7]Sheet1!$A$72:$D$78
Name rgData: #REF!
Name rgData: #REF!
Name rgData: #REF!
Name rgDataDate: #REF!
Name rgDataDate: #REF!
Name rgDataDate: #REF!

Sheet Assumpt
A1: New Jersey Enhanced Motor Vehicle Inspection/Maintenance Systems
A2: NJ Vehicle Inspection Program
A4: General Project Information:
A5: Proposal Number:
A6: Client: | C6: State of New Jersey
A7: Project Description: | C7: =A1 -> New Jersey Enhanced Motor Vehicle Inspection/Maintenance Systems
A8: Project Manager: | C8: Arden Clark
A9: Proposal Manager:
A10: Implementation Project Manager: | C10: Arden Clark
A11: Start Date: | C11: 44136
A12: Date Contract Starts - Paid Tests: | C12: 42491
A13: Completion Date: | C13: 46113
A14: Contract Duration: | C14: 6 Years | D14: =6*12-3 -> 69
A15: Extension Options | C15: 2, Two Year Extensions | D15: 48 Months
A16: Currency: | C16: US Dollars | D16: 117 Months total
A18: ****All Prices should NOT include tax
A22: SCOPE:
A23: VID Development
A24: PIF's and PFF's
A25: CIF's
A26: PIF Equipment
A28: xxxxxxxxxxxxxxxxxxxxxxxxxxxxxxxxxxxxxxxxxxxxxxxxxxxxxxxxxxxxxxxx | C28: xxxxxxxxxxxxxxxxxxxxxxxxxxxxxxxxxxxxxxxxxxxxxxxxx | D28: xxxxxxxxxxxxxxxxxxxxxxxxxxxxxxxxxxxxxxxxxxxxxxxxx | E28: xxxxxxxxxxxxxxxxxxxxxxxxxxxxxxxxxxxxxxxxxxxxxxxxx | F28: xxxxxxxxxxxxxxxxxxxxxxxxxxxxxxxxxxxxxxxxxxxxxxxxx | G28: xxxxxxxxxxxxxxxxxxxxxxxxxxxxxxxxxxxxxxxxxxxxxxxxx | H28: xxxxxxxxxxxxxxxxxxxxxxxxxxxxxxxxxxxxxxxxxxxxxxxxx | I28: xxxxxxxxxxxxxxxxxxxxxxxxxxxxxxxxxxxxxxxxxxxxxxxxx | J28: xxxxxxxxxxxxxxxxxxxxxxxxxxxxxxxxxxxxxxxxxxxxxxxxx | N28: xxxxxxxxxxxxxxxxxxxxxxxxxxxxxxxxxxxxxxxxxxxxxxxxx
C31: Original Contract Term | J31: Spare | K31: Spare | L31: Spare | M31: Spare
A32: Periods Assumed in Model: | C32: Start-up | D32: Year 1 | E32: Year 2 | F32: Year 3 | G32: Year 4 | H32: Year 5 | I32: Year 6 | J32: Year 7 | K32: Year 8 | L32: Year 9 | M32: Year 10 | N32: Grand Total
C33: 0 | D33: 9 | E33: 12 | F33: 12 | G33: 12 | H33: 12 | I33: 12 | J33: 12 | K33: 12 | L33: 12 | M33: 12 | N33: =SUM(D33:M33) -> 117
C34: Nov 2019 apr 2020 | D34: May 2020 Jan 2021 | E34: Feb 2021 Jan 2022 | F34: Feb 2022 Jan 2023 | G34: Feb 2024 Jan 2024 | H34: Feb 2024 Jan 2025 | I34: Feb 2025 Jan 2026 | J34: Feb 2026 Jan 2027 | K34: Feb 2027 Jan 2028 | L34: Feb 2028 Jan 2029 | M34: Feb 2029 Jan 2030 | N34: Years 1
N35: Thru 10
A38: Labor inflation | C38: 1 | D38: 1 | E38: 1.03 | F38: 1.03 | G38: 1.03 | H38: 1.03 | I38: 1 | J38: 1 | K38: 1 | L38: 1 | M38: 1
A39: Labor inflation cumulative | C39: 1 | D39: 1 | E39: =E38 -> 1.03 | F39: =E39*F38 -> 1.0609 | G39: =F39*G38 -> 1.092727 | H39: =G39*H38 -> 1.1255088 | I39: =H39*I38 -> 1.1255088 | J39: =I39*J38 -> 1.1255088 | K39: =J39*K38 -> 1.1255088 | L39: =K39*L38 -> 1.1255088 | M39: =L39*M38 -> 1.1255088
A40: ODC inflation | C40: 1 | D40: 1 | E40: 1 | F40: 1 | G40: 1 | H40: 1 | I40: 1 | J40: 1 | K40: 1 | L40: 1 | M40: 1
A41: ODC inflation cumulative | C41: 1 | D41: 1 | E41: 1 | F41: =E41*F40 -> 1 | G41: =F41*G40 -> 1 | H41: =G41*H40 -> 1 | I41: =H41*I40 -> 1 | J41: =I41*J40 -> 1 | K41: =J41*K40 -> 1 | L41: =K41*L40 -> 1 | M41: =L41*M40 -> 1
A42: Union Labor inflation | C42: 1 | D42: 1 | E42: 1.03 | F42: 1.01 | G42: 1.01 | H42: 1.01 | I42: 1.01 | J42: 1.01 | K42: 1.01 | L42: 1.01 | M42: 1.01
D45: Parsons | I45: Union
A46: Hours Worked per Year | D46: Days | E46: Hours | I46: Days | J46: Hours | K46: Per Month
A47: Total Work Hours | D47: =E47/8 -> 260 | E47: =52*40 -> 2080 | H47: Full Time | I47: =J47/8 -> 212 | J47: =8*5*42+16 -> 1696 | K47: =J47/12 -> 141.33333 | L47: ** Assumes 5 weeks vacation + 2 weeks sick + 13 holidays
A48: Paid Vacation - Statutory Holiday | D48: =E48/8 -> 8 | E48: =8*8 -> 64 | H48: Part Time | I48: =J48/8 -> 133.25 | J48: =5*5*42+16 -> 1066 | K48: =J48/12 -> 88.833333 | L48: ***4 weeks vacation+
A49: PTO - Vacation/Sick/Bereavement/Military | D49: 15 | E49: =15*8 -> 120 | H49: Warehouse | I49: =J49/8 -> 240 | J49: =8*5*48 -> 1920
A50: Total Work Less Fringe | D50: =D47-D48-D49 -> 237 | E50: =ROUND(E47-E48-E49,0) -> 1896 | I50: =SUM(I47:I49) -> 585.25 | J50: =SUM(J47:J49) -> 4682
J52: =AVERAGE(J47,J48,J49) -> 1560.6667
A54: xxxxxxxxxxxxxxxxxxxxxxxxxxxxxxxxxxxxxxxxxxxxxxxxx | C54: xxxxxxxxxxxxxxxxxxxxxxxxxxxxxxxxxxxxxxxxxxxxxxxxx | D54: xxxxxxxxxxxxxxxxxxxxxxxxxxxxxxxxxxxxxxxxxxxxxxxxx | E54: xxxxxxxxxxxxxxxxxxxxxxxxxxxxxxxxxxxxxxxxxxxxxxxxx | F54: xxxxxxxxxxxxxxxxxxxxxxxxxxxxxxxxxxxxxxxxxxxxxxxxx | G54: xxxxxxxxxxxxxxxxxxxxxxxxxxxxxxxxxxxxxxxxxxxxxxxxx | H54: xxxxxxxxxxxxxxxxxxxxxxxxxxxxxxxxxxxxxxxxxxxxxxxxx | I54: xxxxxxxxxxxxxxxxxxxxxxxxxxxxxxxxxxxxxxxxxxxxxxxxx | J54: xxxxxxxxxxxxxxxxxxxxxxxxxxxxxxxxxxxxxxxxxxxxxxxxx | N54: xxxxxxxxxxxxxxxxxxxxxxxxxxxxxxxxxxxxxxxxxxxxxxxxx | O54: xxxxxxxxxxxxxxxxxxxxxxxxxxxxxxxxxxxxxxxxxxxxxxxxx | P54: xxxxxxxxxxxxxxxxxxxxxxxxxxxxxxxxxxxxxxxxxxxxxxxxx | Q54: xxxxxxxxxxxxxxxxxxxxxxxxxxxxxxxxxxxxxxxxxxxxxxxxx | R54: xxxxxxxxxxxxxxxxxxxxxxxxxxxxxxxxxxxxxxxxxxxxxxxxx | S54: xxxxxxxxxxxxxxxxxxxxxxxxxxxxxxxxxxxxxxxxxxxxxxxxx | T54: xxxxxxxxxxxxxxxxxxxxxxxxxxxxxxxxxxxxxxxxxxxxxxxxx | U54: xxxxxxxxxxxxxxxxxxxxxxxxxxxxxxxxxxxxxxxxxxxxxxxxx | V54: xxxxxxxxxxxxxxxxxxxxxxxxxxxxxxxxxxxxxxxxxxxxxxxxx | W54: xxxxxxxxxxxxxxxxxxxxxxxxxxxxxxxxxxxxxxxxxxxxxxxxx | X54: xxxxxxxxxxxxxxxxxxxxxxxxxxxxxxxxxxxxxxxxxxxxxxxxx | Y54: xxxxxxxxxxxxxxxxxxxxxxxxxxxxxxxxxxxxxxxxxxxxxxxxx | Z54: xxxxxxxxxxxxxxxxxxxxxxxxxxxxxxxxxxxxxxxxxxxxxxxxx | AA54: xxxxxxxxxxxxxxxxxxxxxxxxxxxxxxxxxxxxxxxxxxxxxxxxx | AB54: xxxxxxxxxxxxxxxxxxxxxxxxxxxxxxxxxxxxxxxxxxxxxxxxx
A55: TEST VOLUME
A57: See Test Growth Analysis Worksheet
C58: =C32 -> Start-up | D58: =D32 -> Year 1 | E58: =E32 -> Year 2 | F58: =F32 -> Year 3 | G58: =G32 -> Year 4 | H58: =H32 -> Year 5 | I58: =I32 -> Year 6 | J58: =J32 -> Year 7 | ... M58: =M32 -> Year 10
A59: Number Of Inspections: | C59: =C34 -> Nov 2019 apr 2020 | D59: =D34 -> May 2020 Jan 2021 | E59: =E34 -> Feb 2021 Jan 2022 | F59: =F34 -> Feb 2022 Jan 2023 | G59: =G34 -> Feb 2024 Jan 2024 | H59: =H34 -> Feb 2024 Jan 2025 | I59: =I34 -> Feb 2025 Jan 2026 | J59: =J34 -> Feb 2026 Jan 2027 | ... M59: =M34 -> Feb 2029 Jan 2030
A60: Car count inflation | B60: 0
A61: CIF Tests | D61: 1425000 | E61: 1900000 | F61: =E61*(1+$B$60) -> 1900000 | G61: =F61*(1+$B$60) -> 1900000 | H61: =G61*(1+$B$60) -> 1900000 | I61: =H61*(1+$B$60) -> 1900000 | J61: =I61*(1+$B$60) -> 1900000 | K61: =J61*(1+$B$60) -> 1900000 | L61: =K61*(1+$B$60) -> 1900000 | M61: =L61*(1+$B$60) -> 1900000 | N61: =SUM(C61:M61) -> 18525000
A65: PIF Tests | D65: 205000 | E65: 255000 | F65: =E65*(1+$B$60) -> 255000 | G65: =F65*(1+$B$60) -> 255000 | H65: =G65*(1+$B$60) -> 255000 | I65: =H65*(1+$B$60) -> 255000 | J65: =I65*(1+$B$60) -> 255000 | K65: =J65*(1+$B$60) -> 255000 | L65: =K65*(1+$B$60) -> 255000 | M65: =L65*(1+$B$60) -> 255000 | N65: =SUM(C65:M65) -> 2500000
A69: Vehicle Inspections In the Period | C69: =SUM(C61:C61) -> 0 | D69: =SUM(D61:D65) -> 1630000 | E69: =SUM(E61:E65) -> 2155000 | F69: =SUM(F61:F65) -> 2155000 | G69: =SUM(G61:G65) -> 2155000 | H69: =SUM(H61:H65) -> 2155000 | I69: =SUM(I61:I65) -> 2155000 | J69: =SUM(J61:J65) -> 2155000 | K69: =SUM(K61:K65) -> 2155000 | ... M69: =SUM(M61:M65) -> 2155000 | N69: =SUM(C69:M69) -> 21025000
A71: Cumulative Inspections | C71: =C69 -> 0 | D71: =C71+D69 -> 1630000 | E71: =D71+E69 -> 3785000 | F71: =E71+F69 -> 5940000 | G71: =F71+G69 -> 8095000 | H71: =G71+H69 -> 10250000 | I71: =H71+I69 -> 12405000 | J71: =I71+J69 -> 14560000 | K71: =J71+K69 -> 16715000 | ... M71: =L71+M69 -> 21025000
A74: xxxxxxxxxxxxxxxxxxxxxxxxxxxxxxxxxxxxxxxxxxxxxxxxx | C74: xxxxxxxxxxxxxxxxxxxxxxxxxxxxxxxxxxxxxxxxxxxxxxxxx | D74: xxxxxxxxxxxxxxxxxxxxxxxxxxxxxxxxxxxxxxxxxxxxxxxxx | E74: xxxxxxxxxxxxxxxxxxxxxxxxxxxxxxxxxxxxxxxxxxxxxxxxx | F74: xxxxxxxxxxxxxxxxxxxxxxxxxxxxxxxxxxxxxxxxxxxxxxxxx | G74: xxxxxxxxxxxxxxxxxxxxxxxxxxxxxxxxxxxxxxxxxxxxxxxxx | H74: xxxxxxxxxxxxxxxxxxxxxxxxxxxxxxxxxxxxxxxxxxxxxxxxx | I74: xxxxxxxxxxxxxxxxxxxxxxxxxxxxxxxxxxxxxxxxxxxxxxxxx | J74: xxxxxxxxxxxxxxxxxxxxxxxxxxxxxxxxxxxxxxxxxxxxxxxxx | N74: xxxxxxxxxxxxxxxxxxxxxxxxxxxxxxxxxxxxxxxxxxxxxxxxx | S74: xxxxxxxxxxxxxxxxxxxxxxxxxxxxxxxxxxxxxxxxxxxxxxxxx | T74: xxxxxxxxxxxxxxxxxxxxxxxxxxxxxxxxxxxxxxxxxxxxxxxxx | U74: xxxxxxxxxxxxxxxxxxxxxxxxxxxxxxxxxxxxxxxxxxxxxxxxx | V74: xxxxxxxxxxxxxxxxxxxxxxxxxxxxxxxxxxxxxxxxxxxxxxxxx | W74: xxxxxxxxxxxxxxxxxxxxxxxxxxxxxxxxxxxxxxxxxxxxxxxxx | X74: xxxxxxxxxxxxxxxxxxxxxxxxxxxxxxxxxxxxxxxxxxxxxxxxx | Y74: xxxxxxxxxxxxxxxxxxxxxxxxxxxxxxxxxxxxxxxxxxxxxxxxx | Z74: xxxxxxxxxxxxxxxxxxxxxxxxxxxxxxxxxxxxxxxxxxxxxxxxx | AA74: xxxxxxxxxxxxxxxxxxxxxxxxxxxxxxxxxxxxxxxxxxxxxxxxx | AB74: xxxxxxxxxxxxxxxxxxxxxxxxxxxxxxxxxxxxxxxxxxxxxxxxx
A76: Stations
A77: Growth %age | C77: 0 | N77: Total
C78: .
A79: Private Inspections Facilities (PIF's) & PFF | C79: ***Current active PIF's and PFF's Current today | D79: 1250 | E79: =D79 -> 1250 | F79: =E81 -> 1250 | G79: =F81 -> 1250 | H79: =G81 -> 1250 | I79: =H81 -> 1250 | J79: =I81 -> 1250 | K79: =J81 -> 1250 | L79: =K81 -> 1250 | M79: =L81 -> 1250
E80: =E79*$C$77 -> 0 | F80: =F79*$C$77 -> 0 | G80: =G79*$C$77 -> 0 | H80: =H79*$C$77 -> 0 | I80: =I79*$C$77 -> 0 | J80: =J79*$C$77 -> 0 | K80: =K79*$C$77 -> 0 | L80: =L79*$C$77 -> 0 | M80: =M79*$C$77 -> 0
A81: Total Stations | C81: =SUM(C79:C80) -> 0 | D81: =SUM(D79:D80) -> 1250 | E81: =SUM(E79:E80) -> 1250 | F81: =SUM(F79:F80) -> 1250 | G81: =SUM(G79:G80) -> 1250 | H81: =SUM(H79:H80) -> 1250 | I81: =SUM(I79:I80) -> 1250 | J81: =SUM(J79:J80) -> 1250 | ... M81: =SUM(M79:M80) -> 1250
A84: Cashflow Assumptions
E88: =E65/1000 -> 255 | F88: =E88/12 -> 21.25 | G88: =F88*5 -> 106.25 | H88: =F88*40 -> 850

Sheet Pricing details
G1: Pricing and Labor Cost Sheet
O2: Fringe | AQ2: 200 | AR2: 96 | AU2: =AQ2*AR2 -> 19200 | AV2: 1
N3: ***Hourly rate in US $ | O3: CDN | AL3: =18585*18+57390 -> 391920 | AQ3: 1600 | AR3: 12 | AU3: =AQ3*AR3 -> 19200
O4: US | AL4: =3229/56890 -> 0.056758657
C5: 75196 | D5: 18 | E5: =C5*D5 -> 1353528 | O5: US-lite | Q5: Inflation
E6: =199551*18 -> 3591918 | O6: Acerage | Q6: Labor
Q7: ODC's
C9: MBE Type | D9: Company Nmae | E9: Cashflow Category | F9: Scope | G9: Section | H9: Price line and cost type | I9: Cost Type | J9: Description | K9: Price sheet line item | L9: x2 | M9: Cost Per Hour/Unit | N9: Fringe Rate | O9: Headcount/hours | P9: Month 1 | Q9: Month 2 | R9: Month 3 | S9: Month 4 | T9: Month 5 | U9: Month 6 | V9: Month 7 | W9: Month 8 | X9: Startup up totals | Y9: Year 1 | Z9: Year 2 | AA9: Year 3 | AB9: Year 4 | AC9: Year 5 | AD9: Year 6 | AE9: Year 7 | AF9: Year 8 | AG9: Year 9 | AH9: Year 10 | AI9: TOTAL UNITS | AJ9: total hours | AK9: x | AL9: startup | AM9: =CONCATENATE(Y9," Costs") -> Year 1 Costs | AN9: =CONCATENATE(Z9," Costs") -> Year 2 Costs | AO9: Year 3 costs | AP9: Year 4 costs | AQ9: Year 5 costs | AR9: Year 6 costs | AS9: Total costs Years 1 - 6 | AU9: Year 7 costs | AV9: Year 8 costs | AW9: Year 9 costs | AX9: Year 10 costs | AY9: Total costs Years 7-10 | AZ9: Total costs Years 0-10
A11: Canadian Labor
B12: Development Canada | H12: =CONCATENATE(K12,I12) -> 1Labor | I12: Labor | J12: =B12 -> Development Canada | K12: 1 | M12: =120000/2080*0.75 -> 43.269231 | O12: ='Application Development'!E163 -> 1683.825 | X12: =SUM(P12:W12) -> 0 | Y12: 1690 | AI12: =SUM(Y12:AH12) -> 1690 | AJ12: =AI12+X12 -> 1690 | AL12: =$M12*(1+$N12)*X12*Assumpt!C$39 -> 0 | AM12: =$M12*(1+$N12)*Y12*Assumpt!D$39 -> 73125 | AN12: =$M12*(1+P12)*Z12*Assumpt!E$39 -> 0 | AO12: =P12*(1+Q12)*AA12*Assumpt!F39 -> 0 | AP12: =Q12*(1+R12)*AB12*Assumpt!G39 -> 0 | AQ12: =R12*(1+S12)*AC12*Assumpt!H39 -> 0 | AR12: =S12*(1+T12)*AD12*Assumpt!I39 -> 0 | AS12: =SUM(AM12:AR12) -> 73125 | AU12: =T12*(1+U12)*AE12*Assumpt!J39 -> 0 | AV12: =U12*(1+V12)*AF12*Assumpt!K39 -> 0 | AW12: =V12*(1+W12)*AG12*Assumpt!L39 -> 0 | AX12: =W12*(1+X12)*AH12*Assumpt!M39 -> 0 | AY12: =SUM(AU12:AX12) -> 0 | AZ12: =AL12+AS12+AY12 -> 73125 | BC12: =AV12-AU12 -> 0
B13: Development Canada | H13: =CONCATENATE(K13,I13) -> 2Labor | I13: Labor | J13: =B13 -> Development Canada | K13: 2 | M13: =120000/2080*0.75 -> 43.269231 | O13: ='Application Development'!F163 -> 6735.3 | X13: =SUM(P13:W13) -> 0 | Y13: 6735 | AI13: =SUM(Y13:AH13) -> 6735 | AJ13: =AI13+X13 -> 6735 | AL13: =$M13*(1+$N13)*X13*Assumpt!C$39 -> 0 | AM13: =$M13*(1+$N13)*Y13*Assumpt!D$39 -> 291418.27 | AN13: =$M13*(1+P13)*Z13*Assumpt!E$39 -> 0 | AO13: =P13*(1+Q13)*AA13*Assumpt!F40 -> 0 | AP13: =Q13*(1+R13)*AB13*Assumpt!G40 -> 0 | AQ13: =R13*(1+S13)*AC13*Assumpt!H40 -> 0 | AR13: =S13*(1+T13)*AD13*Assumpt!I40 -> 0 | AS13: =SUM(AM13:AR13) -> 291418.27 | AU13: =T13*(1+U13)*AE13*Assumpt!J40 -> 0 | AV13: =U13*(1+V13)*AF13*Assumpt!K40 -> 0 | AW13: =V13*(1+W13)*AG13*Assumpt!L40 -> 0 | AX13: =W13*(1+X13)*AH13*Assumpt!M40 -> 0 | AY13: =SUM(AU13:AX13) -> 0 | AZ13: =AL13+AS13+AY13 -> 291418.27 | BC13: =AV13-AU13 -> 0
B14: Support Canada | H14: =CONCATENATE(K14,I14) -> 11Labor | I14: Labor | J14: =B14 -> Support Canada | K14: 11 | M14: =120000/2080*0.75 -> 43.269231 | O14: 0 | X14: =SUM(P14:W14) -> 0 | Y14: =$O$14*Assumpt!$E$50 -> 0 | Z14: =$O$14*Assumpt!$E$50 -> 0 | AA14: =$O$14*Assumpt!$E$50 -> 0 | AB14: =$O$14*Assumpt!$E$50 -> 0 | AC14: =$O$14*Assumpt!$E$50 -> 0 | AD14: =$O$14*Assumpt!$E$50 -> 0 | AE14: =$O$14*Assumpt!$E$50 -> 0 | AF14: =$O$14*Assumpt!$E$50 -> 0 | ... AH14: =$O$14*Assumpt!$E$50 -> 0 | AI14: =SUM(Y14:AH14) -> 0 | AJ14: =AI14+X14 -> 0 | AL14: =$M14*(1+$N14)*X14*Assumpt!C$39 -> 0 | AM14: =$M14*(1+$N14)*Y14*Assumpt!D$39 -> 0 | AS14: =SUM(AM14:AR14) -> 0 | AY14: =SUM(AU14:AX14) -> 0 | AZ14: =AL14+AS14+AY14 -> 0 | BC14: =AV14-AU14 -> 0
B15: Support Canada | H15: =CONCATENATE(K15,I15) -> 11Labor | I15: Labor | J15: =B15 -> Support Canada | K15: 11 | M15: =120000/2080*0.75 -> 43.269231 | O15: 1.5 | X15: =SUM(P15:W15) -> 0 | Y15: =$O$15*Assumpt!$E$50 -> 2844 | Z15: =$O$15*Assumpt!$E$50 -> 2844 | AA15: =$O$15*Assumpt!$E$50 -> 2844 | AB15: =$O$15*Assumpt!$E$50 -> 2844 | AC15: =$O$15*Assumpt!$E$50 -> 2844 | AD15: =$O$15*Assumpt!$E$50 -> 2844 | AE15: =$O$15*Assumpt!$E$50 -> 2844 | AF15: =$O$15*Assumpt!$E$50 -> 2844 | ... AH15: =$O$15*Assumpt!$E$50 -> 2844 | AI15: =SUM(Y15:AH15) -> 28440 | AJ15: =AI15+X15 -> 28440 | AL15: =$M15*(1+$N15)*X15*Assumpt!C$39 -> 0 | AM15: =$M15*(1+$N15)*Y15*Assumpt!D$39 -> 123057.69 | AN15: =$M15*(1+$N15)*Z15*Assumpt!E$39 -> 126749.42 | AO15: =$M15*(1+$N15)*AA15*Assumpt!F$39 -> 130551.91 | AP15: =$M15*(1+$N15)*AB15*Assumpt!G$39 -> 134468.46 | AQ15: =$M15*(1+$N15)*AC15*Assumpt!H$39 -> 138502.52 | AR15: =$M15*(1+$N15)*AD15*Assumpt!I$39 -> 138502.52 | AS15: =SUM(AM15:AR15) -> 791832.52 | AU15: =$M15*(1+$N15)*AE15*Assumpt!J$39 -> 138502.52 | AV15: =$M15*(1+$N15)*AF15*Assumpt!K$39 -> 138502.52 | AW15: =$M15*(1+$N15)*AG15*Assumpt!L$39 -> 138502.52 | AX15: =SUM(AU15:AW15) -> 415507.55 | AY15: =SUM(AU15:AX15) -> 831015.1 | AZ15: =AL15+AS15+AY15 -> 1622847.6 | BC15: =AV15-AU15 -> 0
B16: Fringe | H16: =CONCATENATE(K16,I16) -> 11Labor | I16: Labor | J16: canada Fringe | K16: 11 | M16: =120000/2080*0.75 -> 43.269231 | N16: 0.3 | AL16: =SUM(AL12:AL15)*$N$16 -> 0 | AM16: =SUM(AM12:AM15)*$N$16 -> 146280.29 | AN16: =SUM(AN12:AN15)*$N$16 -> 38024.827 | AO16: =SUM(AO12:AO15)*$N$16 -> 39165.572 | AP16: =SUM(AP12:AP15)*$N$16 -> 40340.539 | AQ16: =SUM(AQ12:AQ15)*$N$16 -> 41550.755 | AR16: =SUM(AR12:AR15)*$N$16 -> 41550.755 | AS16: =SUM(AM16:AR16) -> 346912.74 | AU16: =SUM(AU12:AU15)*$N$16 -> 41550.755 | AV16: =SUM(AV12:AV15)*$N$16 -> 41550.755 | AW16: =SUM(AW12:AW15)*$N$16 -> 41550.755 | AX16: =SUM(AX12:AX15)*$N$16 -> 124652.27 | AY16: =SUM(AU16:AX16) -> 249304.53 | AZ16: =AL16+AS16+AY16 -> 596217.27 | BC16: =AV16-AU16 -> 0
A17: US labor | H17: =CONCATENATE(K17,I17) | AS17: =SUM(AM17:AR17) -> 0 | AY17: =SUM(AU17:AX17) -> 0 | AZ17: =AL17+AS17+AY17 -> 0 | BC17: =AV17-AU17 -> 0
B18: MGT | H18: =CONCATENATE(K18,I18) -> 11Labor | I18: Labor | J18: MGT | K18: 11 | Y18: 100360 | Z18: 133640 | AA18: =Z18 -> 133640 | AB18: =AA18 -> 133640 | AC18: =AB18 -> 133640 | AD18: =AC18 -> 133640 | AE18: =AD18 -> 133640 | AF18: =AE18 -> 133640 | AG18: =AF18 -> 133640 | AH18: =AG18 -> 133640 | AI18: =SUM(Y18:AH18) -> 1303120 | AJ18: =AI18+X18 -> 1303120 | AM18: =3734738.36177112*0.9 -> 3361264.5 | AN18: =5070844.87466104*0.8 -> 4056675.9 | AO18: =AN18*Assumpt!F38 -> 4178376.2 | AP18: =AO18*Assumpt!G38 -> 4303727.5 | AQ18: =AP18*Assumpt!H38 -> 4432839.3 | AR18: =AQ18*Assumpt!I38 -> 4432839.3 | AS18: =SUM(AM18:AR18) -> 24765723 | AU18: =AR18*Assumpt!J38 -> 4432839.3 | AV18: =AU18*Assumpt!K38 -> 4432839.3 | AW18: =AV18*Assumpt!L38 -> 4432839.3 | AX18: =AW18*Assumpt!M38 -> 4432839.3 | AY18: =SUM(AU18:AX18) -> 17731357 | AZ18: =AL18+AS18+AY18 -> 42497080 | BC18: =AV18-AU18 -> 0
B19: Union | H19: =CONCATENATE(K19,I19) -> 11Labor | I19: Labor | J19: Union | K19: 11 | Y19: 315380.78 | Z19: 424064 | AA19: =Z19 -> 424064 | AB19: =AA19 -> 424064 | AC19: =AB19 -> 424064 | AD19: =AC19 -> 424064 | AE19: =AD19 -> 424064 | AF19: =AE19 -> 424064 | AG19: =AF19 -> 424064 | AH19: =AG19 -> 424064 | AI19: =SUM(Y19:AH19) -> 4131956.8 | AJ19: =AI19+X19 -> 4131956.8 | AM19: =AN19*0.75 -> 6789354 | AN19: 9052472 | AO19: =AN19*Assumpt!F42 -> 9142996.7 | AP19: =AO19*Assumpt!G42 -> 9234426.7 | AQ19: =AP19*Assumpt!H42 -> 9326771 | AR19: =AQ19*Assumpt!I42 -> 9420038.7 | AS19: =SUM(AM19:AR19) -> 52966059 | AU19: =AR19*Assumpt!J42 -> 9514239.1 | AV19: =AU19*Assumpt!K42 -> 9609381.4 | AW19: =AV19*Assumpt!L42 -> 9705475.3 | AX19: =AW19*Assumpt!M42 -> 9802530 | AY19: =SUM(AU19:AX19) -> 38631626 | AZ19: =AL19+AS19+AY19 -> 91597685 | BC19: =AV19-AU19 -> 95142.391
B20: Union Fringe | H20: =CONCATENATE(K20,I20) -> 11Labor | I20: Labor | J20: MGT Fringe | K20: 11 | N20: 0.4025 | AM20: =$N$20*AM18 -> 1352909 | AN20: =$N$20*AN18 -> 1632812 | AO20: =$N$20*AO18 -> 1681796.4 | AP20: =$N$20*AP18 -> 1732250.3 | AQ20: =$N$20*AQ18 -> 1784217.8 | AR20: =$N$20*AR18 -> 1784217.8 | AS20: =SUM(AM20:AR20) -> 9968203.4 | AU20: =$N$20*AU18 -> 1784217.8 | AV20: =$N$20*AV18 -> 1784217.8 | AW20: =$N$20*AW18 -> 1784217.8 | AX20: =$N$20*AX18 -> 1784217.8 | AY20: =SUM(AU20:AX20) -> 7136871.3 | AZ20: =AL20+AS20+AY20 -> 17105075 | BC20: =AV20-AU20 -> 0
B21: Union Fringe | H21: =CONCATENATE(K21,I21) -> 11Labor | I21: Labor | J21: Union Fringe | K21: 11 | N21: 0.63 | AM21: =$N$21*AM19 -> 4277293 | AN21: =$N$21*AN19 -> 5703057.4 | AO21: =$N$21*AO19 -> 5760087.9 | AP21: =$N$21*AP19 -> 5817688.8 | AQ21: =$N$21*AQ19 -> 5875865.7 | AR21: =$N$21*AR19 -> 5934624.4 | AS21: =SUM(AM21:AR21) -> 33368617 | AU21: =$N$21*AU19 -> 5993970.6 | AV21: =$N$21*AV19 -> 6053910.3 | AW21: =$N$21*AW19 -> 6114449.4 | AX21: =$N$21*AX19 -> 6175593.9 | AY21: =SUM(AU21:AX21) -> 24337924 | AZ21: =AL21+AS21+AY21 -> 57706541 | BC21: =AV21-AU21 -> 59939.706
H22: =CONCATENATE(K22,I22) | AS22: =SUM(AM22:AR22) -> 0 | AY22: =SUM(AU22:AX22) -> 0 | AZ22: =AL22+AS22+AY22 -> 0 | BC22: =AV22-AU22 -> 0
H23: =CONCATENATE(K23,I23) | AS23: =SUM(AM23:AR23) -> 0 | AY23: =SUM(AU23:AX23) -> 0 | AZ23: =AL23+AS23+AY23 -> 0 | BC23: =AV23-AU23 -> 0
A24: ODCS | H24: =CONCATENATE(K24,I24) | AS24: =SUM(AM24:AR24) -> 0 | AY24: =SUM(AU24:AX24) -> 0 | AZ24: =AL24+AS24+AY24 -> 0 | BC24: =AV24-AU24 -> 0
H25: =CONCATENATE(K25,I25) -> 9Capital | I25: Capital | J25: Infrastructure one time | K25: 9 | M25: =infrastructure!P86*0.6 -> 658723.95 | Y25: 1 | AL25: =$M25*(1+$N25)*X25*Assumpt!C$39 -> 0 | AM25: =$M25*(1+$N25)*Y25*Assumpt!D$41 -> 658723.95 | AS25: =SUM(AM25:AR25) -> 658723.95 | AY25: =SUM(AU25:AX25) -> 0 | AZ25: =AL25+AS25+AY25 -> 658723.95 | BC25: =AV25-AU25 -> 0
H26: =CONCATENATE(K26,I26) -> 11ODCS | I26: ODCS | J26: Infrastructure recurring | K26: 11 | M26: =infrastructure!T86 -> 610708.4 | Y26: 1 | Z26: 1 | AA26: 1 | AB26: 1 | AC26: 1 | AD26: 1 | AE26: 1 | AF26: 1 | AG26: 1 | AH26: 1 | AL26: =$M26*(1+$N26)*X26*Assumpt!C$39 -> 0 | AM26: =$M26*(1+$N26)*Y26*Assumpt!D$41 -> 610708.4 | AN26: =infrastructure!W86 -> 568790.9 | AO26: =infrastructure!X86 -> 574315.9 | AP26: =infrastructure!Y86 -> 574315.9 | AQ26: =$M26*(1+$N26)*AC26*Assumpt!H$41 -> 610708.4 | AR26: =$M26*(1+$N26)*AD26*Assumpt!I$41 -> 610708.4 | AS26: =SUM(AM26:AR26) -> 3549547.9 | AU26: =$M26*(1+$N26)*AE26*Assumpt!J$41 -> 610708.4 | AV26: =$M26*(1+$N26)*AF26*Assumpt!K$41 -> 610708.4 | AW26: =$M26*(1+$N26)*AG26*Assumpt!L$41 -> 610708.4 | AX26: =$M26*(1+$N26)*AH26*Assumpt!M$41 -> 610708.4 | AY26: =SUM(AU26:AX26) -> 2442833.6 | AZ26: =AL26+AS26+AY26 -> 5992381.5 | BC26: =AV26-AU26 -> 0
H27: =CONCATENATE(K27,I27) -> 11Capital | I27: Capital | J27: Infrastructure refresh | K27: 11 | M27: =infrastructure!AB81 -> 434200 | AE27: 1 | AL27: =$M27*(1+$N27)*X27*Assumpt!C$39 -> 0 | AS27: =SUM(AM27:AR27) -> 0 | AU27: =$M27*(1+$N27)*AE27 -> 434200 | AY27: =SUM(AU27:AX27) -> 434200 | AZ27: =AL27+AS27+AY27 -> 434200 | BC27: =AV27-AU27 -> -434200
A28: Facility | H28: =CONCATENATE(K28,I28) | AS28: =SUM(AM28:AR28) -> 0 | AY28: =SUM(AU28:AX28) -> 0 | AZ28: =AL28+AS28+AY28 -> 0 | BC28: =AV28-AU28 -> 0
H29: =CONCATENATE(K29,I29) | AS29: =SUM(AM29:AR29) -> 0 | AY29: =SUM(AU29:AX29) -> 0 | AZ29: =AL29+AS29+AY29 -> 0 | BC29: =AV29-AU29 -> 0
H30: =CONCATENATE(K30,I30) | AS30: =SUM(AM30:AR30) -> 0 | AY30: =SUM(AU30:AX30) -> 0 | AZ30: =AL30+AS30+AY30 -> 0 | BC30: =AV30-AU30 -> 0
H31: =CONCATENATE(K31,I31) | AS31: =SUM(AM31:AR31) -> 0 | AY31: =SUM(AU31:AX31) -> 0 | AZ31: =AL31+AS31+AY31 -> 0 | BC31: =AV31-AU31 -> 0
H32: =CONCATENATE(K32,I32) -> 11ODCS | I32: ODCS | J32: Cyber security BOND | K32: 11 | M32: 0 | Y32: 1 | Z32: 1 | AA32: 1 | AB32: 1 | AC32: 1 | AD32: 1 | AE32: 1 | AF32: 1 | AG32: 1 | AH32: 1 | AL32: =$M32*(1+$N32)*X32*Assumpt!C$39 -> 0 | AN32: =$M32*(1+$N32)*Z32*Assumpt!E$41 -> 0 | AO32: =$M32*(1+$N32)*AA32*Assumpt!F$41 -> 0 | AP32: =$M32*(1+$N32)*AB32*Assumpt!G$41 -> 0 | AQ32: =$M32*(1+$N32)*AC32*Assumpt!H$41 -> 0 | AR32: =$M32*(1+$N32)*AD32*Assumpt!I$41 -> 0 | AS32: =SUM(AM32:AR32) -> 0 | AU32: =$M32*(1+$N32)*AE32*Assumpt!J$39 -> 0 | AV32: =$M32*(1+$N32)*AF32*Assumpt!K$39 -> 0 | AW32: =$M32*(1+$N32)*AG32*Assumpt!L$39 -> 0 | AX32: =$M32*(1+$N32)*AH32*Assumpt!M$39 -> 0 | AY32: =SUM(AU32:AX32) -> 0 | AZ32: =AL32+AS32+AY32 -> 0 | BC32: =AV32-AU32 -> 0
H33: =CONCATENATE(K33,I33) -> 11ODCS | I33: ODCS | J33: Insurance | K33: 11 | M33: 0 | Y33: 0.75 | Z33: 1 | AA33: 1 | AB33: 1 | AC33: 1 | AD33: 1 | AE33: 1 | AF33: 1 | AG33: 1 | AH33: 1 | AL33: =$M33*(1+$N33)*X33*Assumpt!C$39 -> 0 | AN33: =$M33*(1+$N33)*Z33*Assumpt!E$41 -> 0 | AO33: =$M33*(1+$N33)*AA33*Assumpt!F$41 -> 0 | AP33: =$M33*(1+$N33)*AB33*Assumpt!G$41 -> 0 | AQ33: =$M33*(1+$N33)*AC33*Assumpt!H$41 -> 0 | AR33: =$M33*(1+$N33)*AD33*Assumpt!I$41 -> 0 | AS33: =SUM(AM33:AR33) -> 0 | AU33: =$M33*(1+$N33)*AE33*Assumpt!J$39 -> 0 | AV33: =$M33*(1+$N33)*AF33*Assumpt!K$39 -> 0 | AW33: =$M33*(1+$N33)*AG33*Assumpt!L$39 -> 0 | AX33: =$M33*(1+$N33)*AH33*Assumpt!M$39 -> 0 | AY33: =SUM(AU33:AX33) -> 0 | AZ33: =AL33+AS33+AY33 -> 0 | BC33: =AV33-AU33 -> 0
H34: =CONCATENATE(K34,I34) -> 11ODCS | I34: ODCS | J34: Security testing | K34: 11 | M34: 0 | Y34: 1 | Z34: 1 | AA34: 1 | AB34: 1 | AC34: 1 | AD34: 1 | AE34: 1 | AF34: 1 | AG34: 1 | AH34: 1 | AL34: =$M34*(1+$N34)*X34*Assumpt!C$39 -> 0 | AN34: =$M34*(1+$N34)*Z34*Assumpt!E$41 -> 0 | AO34: =$M34*(1+$N34)*AA34*Assumpt!F$41 -> 0 | AP34: =$M34*(1+$N34)*AB34*Assumpt!G$41 -> 0 | AQ34: =$M34*(1+$N34)*AC34*Assumpt!H$41 -> 0 | AR34: =$M34*(1+$N34)*AD34*Assumpt!I$41 -> 0 | AS34: =SUM(AM34:AR34) -> 0 | AU34: =$M34*(1+$N34)*AE34*Assumpt!J$39 -> 0 | AV34: =$M34*(1+$N34)*AF34*Assumpt!K$39 -> 0 | AW34: =$M34*(1+$N34)*AG34*Assumpt!L$39 -> 0 | AX34: =$M34*(1+$N34)*AH34*Assumpt!M$39 -> 0 | AY34: =SUM(AU34:AX34) -> 0 | AZ34: =AL34+AS34+AY34 -> 0 | BC34: =AV34-AU34 -> 0
H35: =CONCATENATE(K35,I35) -> 11ODCS | I35: ODCS | J35: Contingency | K35: 11 | M35: 250000 | Y35: 0.75 | Z35: 1 | AA35: 1 | AB35: 1 | AC35: 1 | AD35: 1 | AE35: 1 | AF35: 1 | AG35: 1 | AH35: 1 | AN35: =$M35*(1+$N35)*Z35*Assumpt!E$41 -> 250000 | AO35: =$M35*(1+$N35)*AA35*Assumpt!F$41 -> 250000 | AP35: =$M35*(1+$N35)*AB35*Assumpt!G$41 -> 250000 | AQ35: =$M35*(1+$N35)*AC35*Assumpt!H$41 -> 250000 | AR35: =$M35*(1+$N35)*AD35*Assumpt!I$41 -> 250000 | AS35: =SUM(AM35:AR35) -> 1250000 | AU35: =$M35*(1+$N35)*AE35*Assumpt!J$39 -> 281377.2 | AV35: =$M35*(1+$N35)*AF35*Assumpt!K$39 -> 281377.2 | AW35: =$M35*(1+$N35)*AG35*Assumpt!L$39 -> 281377.2 | AX35: =$M35*(1+$N35)*AH35*Assumpt!M$39 -> 281377.2 | AY35: =SUM(AU35:AX35) -> 1125508.8 | AZ35: =AL35+AS35+AY35 -> 2375508.8 | BC35: =AV35-AU35 -> 0
A36: ODCS from Arden | H36: =CONCATENATE(K36,I36) | AS36: =SUM(AM36:AR36) -> 0 | AY36: =SUM(AU36:AX36) -> 0 | AZ36: =AL36+AS36+AY36 -> 0 | BC36: =AV36-AU36 -> 0
H37: =CONCATENATE(K37,I37) | AS37: =SUM(AM37:AR37) -> 0 | AY37: =SUM(AU37:AX37) -> 0 | AZ37: =AL37+AS37+AY37 -> 0 | BC37: =AV37-AU37 -> 0
H38: =CONCATENATE(K38,I38) | AS38: =SUM(AM38:AR38) -> 0 | AY38: =SUM(AU38:AX38) -> 0 | AZ38: =AL38+AS38+AY38 -> 0 | BC38: =AV38-AU38 -> 0
H39: =CONCATENATE(K39,I39) -> 11ODCS | I39: ODCS | J39: Depreciation | K39: 11 | AS39: =SUM(AM39:AR39) -> 0 | AU39: =AR39*Assumpt!$E$40 -> 0 | AV39: =AU39*Assumpt!$E$40 -> 0 | AW39: =AV39*Assumpt!$E$40 -> 0 | AX39: =AW39*Assumpt!$E$40 -> 0 | AY39: =SUM(AU39:AX39) -> 0 | AZ39: =AL39+AS39+AY39 -> 0 | BC39: =AV39-AU39 -> 0
H40: =CONCATENATE(K40,I40) -> 11ODCS | I40: ODCS | J40: Other Penalities | K40: 11 | AM40: 0 | AN40: 0 | AO40: =AN40*Assumpt!$E$40 -> 0 | AP40: =AO40*Assumpt!$E$40 -> 0 | AQ40: =AP40*Assumpt!$E$40 -> 0 | AR40: =AQ40*Assumpt!$E$40 -> 0 | AS40: =SUM(AM40:AR40) -> 0 | AU40: =AR40*Assumpt!$E$40 -> 0 | AV40: =AU40*Assumpt!$E$40 -> 0 | AW40: =AV40*Assumpt!$E$40 -> 0 | AX40: =AW40*Assumpt!$E$40 -> 0 | AY40: =SUM(AU40:AX40) -> 0 | AZ40: =AL40+AS40+AY40 -> 0 | BC40: =AV40-AU40 -> 0
H41: =CONCATENATE(K41,I41) -> 11ODCS | I41: ODCS | J41: Office Supplies - Construction | K41: 11 | AM41: 0 | AN41: 0 | AO41: =AN41*Assumpt!$E$40 -> 0 | AP41: =AO41*Assumpt!$E$40 -> 0 | AQ41: =AP41*Assumpt!$E$40 -> 0 | AR41: =AQ41*Assumpt!$E$40 -> 0 | AS41: =SUM(AM41:AR41) -> 0 | AU41: =AR41*Assumpt!$E$40 -> 0 | AV41: =AU41*Assumpt!$E$40 -> 0 | AW41: =AV41*Assumpt!$E$40 -> 0 | AX41: =AW41*Assumpt!$E$40 -> 0 | AY41: =SUM(AU41:AX41) -> 0 | AZ41: =AL41+AS41+AY41 -> 0 | BC41: =AV41-AU41 -> 0
H42: =CONCATENATE(K42,I42) -> 11ODCS | I42: ODCS | J42: MCI VID System | K42: 11 | AM42: 0 | AN42: 0 | AO42: =AN42*Assumpt!$E$40 -> 0 | AP42: =AO42*Assumpt!$E$40 -> 0 | AQ42: =AP42*Assumpt!$E$40 -> 0 | AR42: =AQ42*Assumpt!$E$40 -> 0 | AS42: =SUM(AM42:AR42) -> 0 | AU42: =AR42*Assumpt!$E$40 -> 0 | AV42: =AU42*Assumpt!$E$40 -> 0 | AW42: =AV42*Assumpt!$E$40 -> 0 | AX42: =AW42*Assumpt!$E$40 -> 0 | AY42: =SUM(AU42:AX42) -> 0 | AZ42: =AL42+AS42+AY42 -> 0 | BC42: =AV42-AU42 -> 0
H43: =CONCATENATE(K43,I43) -> 11ODCS | I43: ODCS | J43: PO Receipts not invoiced | K43: 11 | AM43: 0 | AN43: 0 | AO43: =AN43*Assumpt!$E$40 -> 0 | AP43: =AO43*Assumpt!$E$40 -> 0 | AQ43: =AP43*Assumpt!$E$40 -> 0 | AR43: =AQ43*Assumpt!$E$40 -> 0 | AS43: =SUM(AM43:AR43) -> 0 | AU43: =AR43*Assumpt!$E$40 -> 0 | AV43: =AU43*Assumpt!$E$40 -> 0 | AW43: =AV43*Assumpt!$E$40 -> 0 | AX43: =AW43*Assumpt!$E$40 -> 0 | AY43: =SUM(AU43:AX43) -> 0 | AZ43: =AL43+AS43+AY43 -> 0 | BC43: =AV43-AU43 -> 0
H44: =CONCATENATE(K44,I44) -> 11ODCS | I44: ODCS | J44: Reservation System (ProtectAir) | K44: 11 | AM44: 0 | AN44: 0 | AO44: =AN44*Assumpt!$E$40 -> 0 | AP44: =AO44*Assumpt!$E$40 -> 0 | AQ44: =AP44*Assumpt!$E$40 -> 0 | AR44: =AQ44*Assumpt!$E$40 -> 0 | AS44: =SUM(AM44:AR44) -> 0 | AU44: =AR44*Assumpt!$E$40 -> 0 | AV44: =AU44*Assumpt!$E$40 -> 0 | AW44: =AV44*Assumpt!$E$40 -> 0 | AX44: =AW44*Assumpt!$E$40 -> 0 | AY44: =SUM(AU44:AX44) -> 0 | AZ44: =AL44+AS44+AY44 -> 0 | BC44: =AV44-AU44 -> 0
H45: =CONCATENATE(K45,I45) -> 11ODCS | I45: ODCS | J45: Safety Equipment Warranty (Hunter) | K45: 11 | AM45: 42780.746 | AN45: 57069.408 | AO45: =AN45*Assumpt!F$40 -> 57069.408 | AP45: =AO45*Assumpt!G$40 -> 57069.408 | AQ45: =AP45*Assumpt!H$40 -> 57069.408 | AR45: =AQ45*Assumpt!I$40 -> 57069.408 | AS45: =SUM(AM45:AR45) -> 328127.79 | AU45: =AR45*Assumpt!J40 -> 57069.408 | AV45: =AU45*Assumpt!$E$40 -> 57069.408 | AW45: =AV45*Assumpt!$E$40 -> 57069.408 | AX45: =AW45*Assumpt!$E$40 -> 57069.408 | AY45: =SUM(AU45:AX45) -> 228277.63 | AZ45: =AL45+AS45+AY45 -> 556405.42 | BC45: =AV45-AU45 -> 0
H46: =CONCATENATE(K46,I46) -> 11ODCS | I46: ODCS | J46: Snow Removal | K46: 11 | AM46: 725000 | AN46: 1000000 | AO46: =AN46*Assumpt!F$40 -> 1000000 | AP46: =AO46*Assumpt!G$40 -> 1000000 | AQ46: =AP46*Assumpt!H$40 -> 1000000 | AR46: =AQ46*Assumpt!I$40 -> 1000000 | AS46: =SUM(AM46:AR46) -> 5725000 | AU46: =AR46*Assumpt!$E$40 -> 1000000 | AV46: =AU46*Assumpt!$E$40 -> 1000000 | AW46: =AV46*Assumpt!$E$40 -> 1000000 | AX46: =AW46*Assumpt!$E$40 -> 1000000 | AY46: =SUM(AU46:AX46) -> 4000000 | AZ46: =AL46+AS46+AY46 -> 9725000 | BC46: =AV46-AU46 -> 0
H47: =CONCATENATE(K47,I47) -> 11ODCS | I47: ODCS | J47: Safety (1.6m + .2m) | K47: 11 | AM47: 22025.928 | AN47: 29382.533 | AO47: =AN47*Assumpt!F$40 -> 29382.533 | AP47: =AO47*Assumpt!G$40 -> 29382.533 | AQ47: =AP47*Assumpt!H$40 -> 29382.533 | AR47: =AQ47*Assumpt!I$40 -> 29382.533 | AS47: =SUM(AM47:AR47) -> 168938.59 | AU47: =AR47*Assumpt!$E$40 -> 29382.533 | AV47: =AU47*Assumpt!$E$40 -> 29382.533 | AW47: =AV47*Assumpt!$E$40 -> 29382.533 | AX47: =AW47*Assumpt!$E$40 -> 29382.533 | AY47: =SUM(AU47:AX47) -> 117530.13 | AZ47: =AL47+AS47+AY47 -> 286468.72 | BC47: =AV47-AU47 -> 0
H48: =CONCATENATE(K48,I48) -> 11ODCS | I48: ODCS | J48: Calibration Gas | K48: 11 | AM48: 86.090865 | AN48: 114.845 | AO48: =AN48*Assumpt!F$40 -> 114.845 | AP48: =AO48*Assumpt!G$40 -> 114.845 | AQ48: =AP48*Assumpt!H$40 -> 114.845 | AR48: =AQ48*Assumpt!I$40 -> 114.845 | AS48: =SUM(AM48:AR48) -> 660.31587 | AU48: =AR48*Assumpt!$E$40 -> 114.845 | AV48: =AU48*Assumpt!$E$40 -> 114.845 | AW48: =AV48*Assumpt!$E$40 -> 114.845 | AX48: =AW48*Assumpt!$E$40 -> 114.845 | AY48: =SUM(AU48:AX48) -> 459.38 | AZ48: =AL48+AS48+AY48 -> 1119.6959 | BC48: =AV48-AU48 -> 0
H49: =CONCATENATE(K49,I49) -> 11ODCS | I49: ODCS | J49: Leased Facilities - Office Rent | K49: 11 | AM49: 203979.21 | AN49: =272107.754068047*0.8 -> 217686.2 | AO49: =AN49*Assumpt!F$40 -> 217686.2 | AP49: =AO49*Assumpt!G$40 -> 217686.2 | AQ49: =AP49*Assumpt!H$40 -> 217686.2 | AR49: =AQ49*Assumpt!I$40 -> 217686.2 | AS49: =SUM(AM49:AR49) -> 1292410.2 | AU49: =AR49*Assumpt!$E$40 -> 217686.2 | AV49: =AU49*Assumpt!$E$40 -> 217686.2 | AW49: =AV49*Assumpt!$E$40 -> 217686.2 | AX49: =AW49*Assumpt!$E$40 -> 217686.2 | AY49: =SUM(AU49:AX49) -> 870744.81 | AZ49: =AL49+AS49+AY49 -> 2163155 | BC49: =AV49-AU49 -> 0
H50: =CONCATENATE(K50,I50) -> 11ODCS | I50: ODCS | J50: Bonds/Insurance/Taxes/Fees | K50: 11 | AM50: =276000*0.75 -> 207000 | AN50: 276000 | AO50: =AN50*Assumpt!F$40 -> 276000 | AP50: =AO50*Assumpt!G$40 -> 276000 | AQ50: =AP50*Assumpt!H$40 -> 276000 | AR50: =AQ50*Assumpt!I$40 -> 276000 | AS50: =SUM(AM50:AR50) -> 1587000 | AU50: =AR50*Assumpt!$E$40 -> 276000 | AV50: =AU50*Assumpt!$E$40 -> 276000 | AW50: =AV50*Assumpt!$E$40 -> 276000 | AX50: =AW50*Assumpt!$E$40 -> 276000 | AY50: =SUM(AU50:AX50) -> 1104000 | AZ50: =AL50+AS50+AY50 -> 2691000 | BC50: =AV50-AU50 -> 0
H51: =CONCATENATE(K51,I51) -> 11ODCS | I51: ODCS | J51: Lane Tech Licenses | K51: 11 | AM51: 11433.247 | AN51: 15251.923 | AO51: =AN51*Assumpt!F$40 -> 15251.923 | AP51: =AO51*Assumpt!G$40 -> 15251.923 | AQ51: =AP51*Assumpt!H$40 -> 15251.923 | AR51: =AQ51*Assumpt!I$40 -> 15251.923 | AS51: =SUM(AM51:AR51) -> 87692.862 | AU51: =AR51*Assumpt!$E$40 -> 15251.923 | AV51: =AU51*Assumpt!$E$40 -> 15251.923 | AW51: =AV51*Assumpt!$E$40 -> 15251.923 | AX51: =AW51*Assumpt!$E$40 -> 15251.923 | AY51: =SUM(AU51:AX51) -> 61007.692 | AZ51: =AL51+AS51+AY51 -> 148700.55 | BC51: =AV51-AU51 -> 0
H52: =CONCATENATE(K52,I52) -> 11ODCS | I52: ODCS | J52: Travel (Gas/Mileage) | K52: 11 | AM52: 177063.03 | AN52: 236774.68 | AO52: =AN52*Assumpt!F$40 -> 236774.68 | AP52: =AO52*Assumpt!G$40 -> 236774.68 | AQ52: =AP52*Assumpt!H$40 -> 236774.68 | AR52: =AQ52*Assumpt!I$40 -> 236774.68 | AS52: =SUM(AM52:AR52) -> 1360936.4 | AU52: =AR52*Assumpt!$E$40 -> 236774.68 | AV52: =AU52*Assumpt!$E$40 -> 236774.68 | AW52: =AV52*Assumpt!$E$40 -> 236774.68 | AX52: =AW52*Assumpt!$E$40 -> 236774.68 | AY52: =SUM(AU52:AX52) -> 947098.71 | AZ52: =AL52+AS52+AY52 -> 2308035.1 | BC52: =AV52-AU52 -> 0
H53: =CONCATENATE(K53,I53) -> 11ODCS | I53: ODCS | J53: Employee Recognition/Sunshine Fund (9234) | K53: 11 | AM53: 22946.183 | AN53: 30684.413 | AO53: =AN53*[8]Assumpt!F$40 -> 30684.413 | AP53: =AO53*[8]Assumpt!G$40 -> 30684.413 | AQ53: =AP53*[8]Assumpt!H$40 -> 30684.413 | AR53: =AQ53*[8]Assumpt!I$40 -> 30684.413 | AS53: =SUM(AM53:AR53) -> 176368.25 | AU53: =AR53*Assumpt!$E$40 -> 30684.413 | AV53: =AU53*Assumpt!$E$40 -> 30684.413 | AW53: =AV53*Assumpt!$E$40 -> 30684.413 | AX53: =AW53*Assumpt!$E$40 -> 30684.413 | AY53: =SUM(AU53:AX53) -> 122737.65 | AZ53: =AL53+AS53+AY53 -> 299105.9 | BC53: =AV53-AU53 -> 0
H54: =CONCATENATE(K54,I54) -> 11ODCS | I54: ODCS | J54: Training | K54: 11 | AM54: 3374.9757 | AN54: 4502.2092 | AO54: =AN54*Assumpt!F$40 -> 4502.2092 | AP54: =AO54*Assumpt!G$40 -> 4502.2092 | AQ54: =AP54*Assumpt!H$40 -> 4502.2092 | AR54: =AQ54*Assumpt!I$40 -> 4502.2092 | AS54: =SUM(AM54:AR54) -> 25886.022 | AU54: =AR54*Assumpt!$E$40 -> 4502.2092 | AV54: =AU54*Assumpt!$E$40 -> 4502.2092 | AW54: =AV54*Assumpt!$E$40 -> 4502.2092 | AX54: =AW54*Assumpt!$E$40 -> 4502.2092 | AY54: =SUM(AU54:AX54) -> 18008.837 | AZ54: =AL54+AS54+AY54 -> 43894.859 | BC54: =AV54-AU54 -> 0
H55: =CONCATENATE(K55,I55) -> 11ODCS | I55: ODCS | J55: Miscellaneous | K55: 11 | AM55: 3870.7401 | AN55: 5163.5576 | AO55: =AN55*Assumpt!F$40 -> 5163.5576 | AP55: =AO55*Assumpt!G$40 -> 5163.5576 | AQ55: =AP55*Assumpt!H$40 -> 5163.5576 | AR55: =AQ55*Assumpt!I$40 -> 5163.5576 | AS55: =SUM(AM55:AR55) -> 29688.528 | AU55: =AR55*Assumpt!$E$40 -> 5163.5576 | AV55: =AU55*Assumpt!$E$40 -> 5163.5576 | AW55: =AV55*Assumpt!$E$40 -> 5163.5576 | AX55: =AW55*Assumpt!$E$40 -> 5163.5576 | AY55: =SUM(AU55:AX55) -> 20654.23 | AZ55: =AL55+AS55+AY55 -> 50342.758 | BC55: =AV55-AU55 -> 0
H56: =CONCATENATE(K56,I56) -> 11ODCS | I56: ODCS | J56: Incentive Payments | K56: 11 | AM56: 0 | AN56: 0 | AO56: =AN56*Assumpt!F$40 -> 0 | AP56: =AO56*Assumpt!G$40 -> 0 | AQ56: =AP56*Assumpt!H$40 -> 0 | AR56: =AQ56*Assumpt!I$40 -> 0 | AS56: =SUM(AM56:AR56) -> 0 | AU56: =AR56*Assumpt!$E$40 -> 0 | AV56: =AU56*Assumpt!$E$40 -> 0 | AW56: =AV56*Assumpt!$E$40 -> 0 | AX56: =AW56*Assumpt!$E$40 -> 0 | AY56: =SUM(AU56:AX56) -> 0 | AZ56: =AL56+AS56+AY56 -> 0 | BC56: =AV56-AU56 -> 0
H57: =CONCATENATE(K57,I57) -> 11ODCS | I57: ODCS | J57: Uniforms | K57: 11 | AM57: 69623.62 | AN57: 92877.736 | AO57: =AN57*Assumpt!F$40 -> 92877.736 | AP57: =AO57*Assumpt!G$40 -> 92877.736 | AQ57: =AP57*Assumpt!H$40 -> 92877.736 | AR57: =AQ57*Assumpt!I$40 -> 92877.736 | AS57: =SUM(AM57:AR57) -> 534012.3 | AU57: =AR57*Assumpt!$E$40 -> 92877.736 | AV57: =AU57*Assumpt!$E$40 -> 92877.736 | AW57: =AV57*Assumpt!$E$40 -> 92877.736 | AX57: =AW57*Assumpt!$E$40 -> 92877.736 | AY57: =SUM(AU57:AX57) -> 371510.94 | AZ57: =AL57+AS57+AY57 -> 905523.24 | BC57: =AV57-AU57 -> 0
H58: =CONCATENATE(K58,I58) -> 11ODCS | I58: ODCS | J58: Recruiting | K58: 11 | AM58: 0 | AN58: 0 | AO58: =AN58*Assumpt!F$40 -> 0 | AP58: =AO58*Assumpt!G$40 -> 0 | AQ58: =AP58*Assumpt!H$40 -> 0 | AR58: =AQ58*Assumpt!I$40 -> 0 | AS58: =SUM(AM58:AR58) -> 0 | AU58: =AR58*Assumpt!$E$40 -> 0 | AV58: =AU58*Assumpt!$E$40 -> 0 | AW58: =AV58*Assumpt!$E$40 -> 0 | AX58: =AW58*Assumpt!$E$40 -> 0 | AY58: =SUM(AU58:AX58) -> 0 | AZ58: =AL58+AS58+AY58 -> 0 | BC58: =AV58-AU58 -> 0
H59: =CONCATENATE(K59,I59) -> 11ODCS | I59: ODCS | J59: Drug Testing | K59: 11 | AM59: 8186.728 | AN59: 10921.075 | AO59: =AN59*Assumpt!F$40 -> 10921.075 | AP59: =AO59*Assumpt!G$40 -> 10921.075 | AQ59: =AP59*Assumpt!H$40 -> 10921.075 | AR59: =AQ59*Assumpt!I$40 -> 10921.075 | AS59: =SUM(AM59:AR59) -> 62792.102 | AU59: =AR59*Assumpt!$E$40 -> 10921.075 | AV59: =AU59*Assumpt!$E$40 -> 10921.075 | AW59: =AV59*Assumpt!$E$40 -> 10921.075 | AX59: =AW59*Assumpt!$E$40 -> 10921.075 | AY59: =SUM(AU59:AX59) -> 43684.299 | AZ59: =AL59+AS59+AY59 -> 106476.4 | BC59: =AV59-AU59 -> 0
H60: =CONCATENATE(K60,I60) -> 11ODCS | I60: ODCS | J60: Moving / Relocation | K60: 11 | AM60: 0 | AN60: 0 | AO60: =AN60*Assumpt!F$40 -> 0 | AP60: =AO60*Assumpt!G$40 -> 0 | AQ60: =AP60*Assumpt!H$40 -> 0 | AR60: =AQ60*Assumpt!I$40 -> 0 | AS60: =SUM(AM60:AR60) -> 0 | AU60: =AR60*Assumpt!$E$40 -> 0 | AV60: =AU60*Assumpt!$E$40 -> 0 | AW60: =AV60*Assumpt!$E$40 -> 0 | AX60: =AW60*Assumpt!$E$40 -> 0 | AY60: =SUM(AU60:AX60) -> 0 | AZ60: =AL60+AS60+AY60 -> 0 | BC60: =AV60-AU60 -> 0
H61: =CONCATENATE(K61,I61) -> 11ODCS | I61: ODCS | J61: Leased Equipment - Auto | K61: 11 | AM61: 0 | AN61: 0 | AO61: =AN61*Assumpt!F$40 -> 0 | AP61: =AO61*Assumpt!G$40 -> 0 | AQ61: =AP61*Assumpt!H$40 -> 0 | AR61: =AQ61*Assumpt!I$40 -> 0 | AS61: =SUM(AM61:AR61) -> 0 | AU61: =AR61*Assumpt!$E$40 -> 0 | AV61: =AU61*Assumpt!$E$40 -> 0 | AW61: =AV61*Assumpt!$E$40 -> 0 | AX61: =AW61*Assumpt!$E$40 -> 0 | AY61: =SUM(AU61:AX61) -> 0 | AZ61: =AL61+AS61+AY61 -> 0 | BC61: =AV61-AU61 -> 0
H62: =CONCATENATE(K62,I62) -> 11ODCS | I62: ODCS | J62: Public Relations | K62: 11 | AM62: 225013.35 | AN62: 293208.88 | AO62: =AN62*Assumpt!F$40 -> 293208.88 | AP62: =AO62*Assumpt!G$40 -> 293208.88 | AQ62: =AP62*Assumpt!H$40 -> 293208.88 | AR62: =AQ62*Assumpt!I$40 -> 293208.88 | AS62: =SUM(AM62:AR62) -> 1691057.8 | AU62: =AR62*Assumpt!$E$40 -> 293208.88 | AV62: =AU62*Assumpt!$E$40 -> 293208.88 | AW62: =AV62*Assumpt!$E$40 -> 293208.88 | AX62: =AW62*Assumpt!$E$40 -> 293208.88 | AY62: =SUM(AU62:AX62) -> 1172835.5 | AZ62: =AL62+AS62+AY62 -> 2863893.3 | BC62: =AV62-AU62 -> 0
H63: =CONCATENATE(K63,I63) -> 11ODCS | I63: ODCS | J63: Office Supplies - O & M | K63: 11 | AM63: 11651.966 | AN63: 15543.693 | AO63: =AN63*Assumpt!F$40 -> 15543.693 | AP63: =AO63*Assumpt!G$40 -> 15543.693 | AQ63: =AP63*Assumpt!H$40 -> 15543.693 | AR63: =AQ63*Assumpt!I$40 -> 15543.693 | AS63: =SUM(AM63:AR63) -> 89370.433 | AU63: =AR63*Assumpt!$E$40 -> 15543.693 | AV63: =AU63*Assumpt!$E$40 -> 15543.693 | AW63: =AV63*Assumpt!$E$40 -> 15543.693 | AX63: =AW63*Assumpt!$E$40 -> 15543.693 | AY63: =SUM(AU63:AX63) -> 62174.774 | AZ63: =AL63+AS63+AY63 -> 151545.21 | BC63: =AV63-AU63 -> 0
H64: =CONCATENATE(K64,I64) -> 11ODCS | I64: ODCS | J64: Job Materials & Supplies | K64: 11 | AM64: 122305.35 | AN64: 163155.04 | AO64: =AN64*Assumpt!F$40 -> 163155.04 | AP64: =AO64*Assumpt!G$40 -> 163155.04 | AQ64: =AP64*Assumpt!H$40 -> 163155.04 | AR64: =AQ64*Assumpt!I$40 -> 163155.04 | AS64: =SUM(AM64:AR64) -> 938080.53 | AU64: =AR64*Assumpt!$E$40 -> 163155.04 | AV64: =AU64*Assumpt!$E$40 -> 163155.04 | AW64: =AV64*Assumpt!$E$40 -> 163155.04 | AX64: =AW64*Assumpt!$E$40 -> 163155.04 | AY64: =SUM(AU64:AX64) -> 652620.14 | AZ64: =AL64+AS64+AY64 -> 1590700.7 | BC64: =AV64-AU64 -> 0
H65: =CONCATENATE(K65,I65) -> 11ODCS | I65: ODCS | J65: Inventoriable Expense | K65: 11 | AM65: 0 | AN65: =424428.382248521-150000 -> 274428.38 | AO65: =AN65*Assumpt!F$40 -> 274428.38 | AP65: =AO65*Assumpt!G$40 -> 274428.38 | AQ65: =AP65*Assumpt!H$40 -> 274428.38 | AR65: =AQ65*Assumpt!I$40 -> 274428.38 | AS65: =SUM(AM65:AR65) -> 1372141.9 | AU65: =AR65*Assumpt!$E$40 -> 274428.38 | AV65: =AU65*Assumpt!$E$40 -> 274428.38 | AW65: =AV65*Assumpt!$E$40 -> 274428.38 | AX65: =AW65*Assumpt!$E$40 -> 274428.38 | AY65: =SUM(AU65:AX65) -> 1097713.5 | AZ65: =AL65+AS65+AY65 -> 2469855.4 | BC65: =AV65-AU65 -> 0
H66: =CONCATENATE(K66,I66) -> 11ODCS | I66: ODCS | J66: Winter Jackets / Summer | K66: 11 | AM66: 4798.2814 | AN66: 6400.8954 | AO66: =AN66*Assumpt!F$40 -> 6400.8954 | AP66: =AO66*Assumpt!G$40 -> 6400.8954 | AQ66: =AP66*Assumpt!H$40 -> 6400.8954 | AR66: =AQ66*Assumpt!I$40 -> 6400.8954 | AS66: =SUM(AM66:AR66) -> 36802.758 | AU66: =AR66*Assumpt!$E$40 -> 6400.8954 | AV66: =AU66*Assumpt!$E$40 -> 6400.8954 | AW66: =AV66*Assumpt!$E$40 -> 6400.8954 | AX66: =AW66*Assumpt!$E$40 -> 6400.8954 | AY66: =SUM(AU66:AX66) -> 25603.582 | AZ66: =AL66+AS66+AY66 -> 62406.34 | BC66: =AV66-AU66 -> 0
H67: =CONCATENATE(K67,I67) -> 11ODCS | I67: ODCS | J67: Lane Software | K67: 11 | AM67: 0 | AN67: 0 | AO67: =AN67*Assumpt!F$40 -> 0 | AP67: =AO67*Assumpt!G$40 -> 0 | AQ67: =AP67*Assumpt!H$40 -> 0 | AR67: =AQ67*Assumpt!I$40 -> 0 | AS67: =SUM(AM67:AR67) -> 0 | AU67: =AR67*Assumpt!$E$40 -> 0 | AV67: =AU67*Assumpt!$E$40 -> 0 | AW67: =AV67*Assumpt!$E$40 -> 0 | AX67: =AW67*Assumpt!$E$40 -> 0 | AY67: =SUM(AU67:AX67) -> 0 | AZ67: =AL67+AS67+AY67 -> 0 | BC67: =AV67-AU67 -> 0
H68: =CONCATENATE(K68,I68) -> 11ODCS | I68: ODCS | J68: Freight | K68: 11 | AM68: 9893.122 | AN68: 13229.418 | AO68: =AN68*Assumpt!F$40 -> 13229.418 | AP68: =AO68*Assumpt!G$40 -> 13229.418 | AQ68: =AP68*Assumpt!H$40 -> 13229.418 | AR68: =AQ68*Assumpt!I$40 -> 13229.418 | AS68: =SUM(AM68:AR68) -> 76040.21 | AU68: =AR68*Assumpt!$E$40 -> 13229.418 | AV68: =AU68*Assumpt!$E$40 -> 13229.418 | AW68: =AV68*Assumpt!$E$40 -> 13229.418 | AX68: =AW68*Assumpt!$E$40 -> 13229.418 | AY68: =SUM(AU68:AX68) -> 52917.67 | AZ68: =AL68+AS68+AY68 -> 128957.88 | BC68: =AV68-AU68 -> 0
H69: =CONCATENATE(K69,I69) -> 11ODCS | I69: ODCS | J69: Express Mail | K69: 11 | AM69: 1530.0586 | AN69: 2047.828 | AO69: =AN69*Assumpt!F$40 -> 2047.828 | AP69: =AO69*Assumpt!G$40 -> 2047.828 | AQ69: =AP69*Assumpt!H$40 -> 2047.828 | AR69: =AQ69*Assumpt!I$40 -> 2047.828 | AS69: =SUM(AM69:AR69) -> 11769.199 | AU69: =AR69*Assumpt!$E$40 -> 2047.828 | AV69: =AU69*Assumpt!$E$40 -> 2047.828 | AW69: =AV69*Assumpt!$E$40 -> 2047.828 | AX69: =AW69*Assumpt!$E$40 -> 2047.828 | AY69: =SUM(AU69:AX69) -> 8191.312 | AZ69: =AL69+AS69+AY69 -> 19960.511 | BC69: =AV69-AU69 -> 0
H70: =CONCATENATE(K70,I70) -> 11ODCS | I70: ODCS | J70: Postage | K70: 11 | AM70: 1397.6773 | AN70: 1864.4981 | AO70: =AN70*Assumpt!F$40 -> 1864.4981 | AP70: =AO70*Assumpt!G$40 -> 1864.4981 | AQ70: =AP70*Assumpt!H$40 -> 1864.4981 | AR70: =AQ70*Assumpt!I$40 -> 1864.4981 | AS70: =SUM(AM70:AR70) -> 10720.168 | AU70: =AR70*Assumpt!$E$40 -> 1864.4981 | AV70: =AU70*Assumpt!$E$40 -> 1864.4981 | AW70: =AV70*Assumpt!$E$40 -> 1864.4981 | AX70: =AW70*Assumpt!$E$40 -> 1864.4981 | AY70: =SUM(AU70:AX70) -> 7457.9923 | AZ70: =AL70+AS70+AY70 -> 18178.16 | BC70: =AV70-AU70 -> 0
H71: =CONCATENATE(K71,I71) -> 11ODCS | I71: ODCS | J71: Copier | K71: 11 | AM71: 12374.307 | AN71: 16507.295 | AO71: =AN71*Assumpt!F$40 -> 16507.295 | AP71: =AO71*Assumpt!G$40 -> 16507.295 | AQ71: =AP71*Assumpt!H$40 -> 16507.295 | AR71: =AQ71*Assumpt!I$40 -> 16507.295 | AS71: =SUM(AM71:AR71) -> 94910.782 | AU71: =AR71*Assumpt!$E$40 -> 16507.295 | AV71: =AU71*Assumpt!$E$40 -> 16507.295 | AW71: =AV71*Assumpt!$E$40 -> 16507.295 | AX71: =AW71*Assumpt!$E$40 -> 16507.295 | AY71: =SUM(AU71:AX71) -> 66029.18 | AZ71: =AL71+AS71+AY71 -> 160939.96 | BC71: =AV71-AU71 -> 0
H72: =CONCATENATE(K72,I72) -> 11ODCS | I72: ODCS | J72: Reproduction | K72: 11 | AM72: 0 | AN72: 0 | AO72: =AN72*Assumpt!F$40 -> 0 | AP72: =AO72*Assumpt!G$40 -> 0 | AQ72: =AP72*Assumpt!H$40 -> 0 | AR72: =AQ72*Assumpt!I$40 -> 0 | AS72: =SUM(AM72:AR72) -> 0 | AU72: =AR72*Assumpt!$E$40 -> 0 | AV72: =AU72*Assumpt!$E$40 -> 0 | AW72: =AV72*Assumpt!$E$40 -> 0 | AX72: =AW72*Assumpt!$E$40 -> 0 | AY72: =SUM(AU72:AX72) -> 0 | AZ72: =AL72+AS72+AY72 -> 0 | BC72: =AV72-AU72 -> 0
H73: =CONCATENATE(K73,I73) -> 11ODCS | I73: ODCS | J73: Technical Publications | K73: 11 | AM73: 0 | AN73: 0 | AO73: =AN73*Assumpt!F$40 -> 0 | AP73: =AO73*Assumpt!G$40 -> 0 | AQ73: =AP73*Assumpt!H$40 -> 0 | AR73: =AQ73*Assumpt!I$40 -> 0 | AS73: =SUM(AM73:AR73) -> 0 | AU73: =AR73*Assumpt!$E$40 -> 0 | AV73: =AU73*Assumpt!$E$40 -> 0 | AW73: =AV73*Assumpt!$E$40 -> 0 | AX73: =AW73*Assumpt!$E$40 -> 0 | AY73: =SUM(AU73:AX73) -> 0 | AZ73: =AL73+AS73+AY73 -> 0 | BC73: =AV73-AU73 -> 0
H74: =CONCATENATE(K74,I74) -> 11ODCS | I74: ODCS | J74: Telephone | K74: 11 | AM74: 101036.68 | AN74: 134782.68 | AO74: =AN74*Assumpt!F$40 -> 134782.68 | AP74: =AO74*Assumpt!G$40 -> 134782.68 | AQ74: =AP74*Assumpt!H$40 -> 134782.68 | AR74: =AQ74*Assumpt!I$40 -> 134782.68 | AS74: =SUM(AM74:AR74) -> 774950.1 | AU74: =AR74*Assumpt!J$40 -> 134782.68 | AV74: =AU74*Assumpt!$E$40 -> 134782.68 | AW74: =AV74*Assumpt!$E$40 -> 134782.68 | AX74: =AW74*Assumpt!$E$40 -> 134782.68 | AY74: =SUM(AU74:AX74) -> 539130.73 | AZ74: =AL74+AS74+AY74 -> 1314080.8 | BC74: =AV74-AU74 -> 0
H75: =CONCATENATE(K75,I75) -> 11ODCS | I75: ODCS | J75: Computers | K75: 11 | AM75: 161079.84 | AN75: 214880.1 | AO75: =AN75*Assumpt!F$40 -> 214880.1 | AP75: =AO75*Assumpt!G$40 -> 214880.1 | AQ75: =AP75*Assumpt!H$40 -> 214880.1 | AR75: =AQ75*Assumpt!I$40 -> 214880.1 | AS75: =SUM(AM75:AR75) -> 1235480.3 | AU75: =AR75*Assumpt!$E$40 -> 214880.1 | AV75: =AU75*Assumpt!$E$40 -> 214880.1 | AW75: =AV75*Assumpt!$E$40 -> 214880.1 | AX75: =AW75*Assumpt!$E$40 -> 214880.1 | AY75: =SUM(AU75:AX75) -> 859520.41 | AZ75: =AL75+AS75+AY75 -> 2095000.8 | BC75: =AV75-AU75 -> 0
H76: =CONCATENATE(K76,I76) -> 11ODCS | I76: ODCS | J76: Non Capital Equipment Purchases | K76: 11 | AM76: 0 | AN76: 0 | AO76: =AN76*Assumpt!F$40 -> 0 | AP76: =AO76*Assumpt!G$40 -> 0 | AQ76: =AP76*Assumpt!H$40 -> 0 | AR76: =AQ76*Assumpt!I$40 -> 0 | AS76: =SUM(AM76:AR76) -> 0 | AU76: =AR76*Assumpt!$E$40 -> 0 | AV76: =AU76*Assumpt!$E$40 -> 0 | AW76: =AV76*Assumpt!$E$40 -> 0 | AX76: =AW76*Assumpt!$E$40 -> 0 | AY76: =SUM(AU76:AX76) -> 0 | AZ76: =AL76+AS76+AY76 -> 0 | BC76: =AV76-AU76 -> 0
H77: =CONCATENATE(K77,I77) -> 11ODCS | I77: ODCS | J77: Repairs & Maintenance - Equip | K77: 11 | AM77: 22252.247 | AN77: 29684.442 | AO77: =AN77*Assumpt!F$40 -> 29684.442 | AP77: =AO77*Assumpt!G$40 -> 29684.442 | AQ77: =AP77*Assumpt!H$40 -> 29684.442 | AR77: =AQ77*Assumpt!I$40 -> 29684.442 | AS77: =SUM(AM77:AR77) -> 170674.45 | AU77: =AR77*Assumpt!$E$40 -> 29684.442 | AV77: =AU77*Assumpt!$E$40 -> 29684.442 | AW77: =AV77*Assumpt!$E$40 -> 29684.442 | AX77: =AW77*Assumpt!$E$40 -> 29684.442 | AY77: =SUM(AU77:AX77) -> 118737.77 | AZ77: =AL77+AS77+AY77 -> 289412.22 | BC77: =AV77-AU77 -> 0
H78: =CONCATENATE(K78,I78) -> 11ODCS | I78: ODCS | J78: Recovery Credits | K78: 11 | AM78: 0 | AN78: 0 | AO78: =AN78*Assumpt!F$40 -> 0 | AP78: =AO78*Assumpt!G$40 -> 0 | AQ78: =AP78*Assumpt!H$40 -> 0 | AR78: =AQ78*Assumpt!I$40 -> 0 | AS78: =SUM(AM78:AR78) -> 0 | AU78: =AR78*Assumpt!$E$40 -> 0 | AV78: =AU78*Assumpt!$E$40 -> 0 | AW78: =AV78*Assumpt!$E$40 -> 0 | AX78: =AW78*Assumpt!$E$40 -> 0 | AY78: =SUM(AU78:AX78) -> 0 | AZ78: =AL78+AS78+AY78 -> 0 | BC78: =AV78-AU78 -> 0
H79: =CONCATENATE(K79,I79) -> 11ODCS | I79: ODCS | J79: Legal Expenses | K79: 11 | AM79: =363176.884393491 -> 363176.88 | AN79: =484477.059230769 -> 484477.06 | AO79: =AN79*Assumpt!F$40-230000 -> 254477.06 | AP79: =AO79*Assumpt!G$40 -> 254477.06 | AQ79: =AP79*Assumpt!H$40 -> 254477.06 | AR79: =AQ79*Assumpt!I$40 -> 254477.06 | AS79: =SUM(AM79:AR79) -> 1865562.2 | AU79: =AR79*Assumpt!$E$40 -> 254477.06 | AV79: =AU79*Assumpt!$E$40 -> 254477.06 | AW79: =AV79*Assumpt!$E$40 -> 254477.06 | AX79: =AW79*Assumpt!$E$40 -> 254477.06 | AY79: =SUM(AU79:AX79) -> 1017908.2 | AZ79: =AL79+AS79+AY79 -> 2883470.4 | BC79: =AV79-AU79 -> 0
H80: =CONCATENATE(K80,I80) -> 11ODCS | I80: ODCS | J80: Sunshine Fund (see 9234) | K80: 11 | AM80: 0 | AN80: 0 | AO80: =AN80*Assumpt!F$40 -> 0 | AP80: =AO80*Assumpt!G$40 -> 0 | AQ80: =AP80*Assumpt!H$40 -> 0 | AR80: =AQ80*Assumpt!I$40 -> 0 | AS80: =SUM(AM80:AR80) -> 0 | AU80: =AR80*Assumpt!$E$40 -> 0 | AV80: =AU80*Assumpt!$E$40 -> 0 | AW80: =AV80*Assumpt!$E$40 -> 0 | AX80: =AW80*Assumpt!$E$40 -> 0 | AY80: =SUM(AU80:AX80) -> 0 | AZ80: =AL80+AS80+AY80 -> 0 | BC80: =AV80-AU80 -> 0
H81: =CONCATENATE(K81,I81) -> 11ODCS | I81: ODCS | J81: Consulting/Temporary Labor | K81: 11 | AM81: 108722.98 | AN81: 145000 | AO81: 0 | AP81: =AO81*Assumpt!G$40 -> 0 | AQ81: =AP81*Assumpt!H$40 -> 0 | AR81: =AQ81*Assumpt!I$40 -> 0 | AS81: =SUM(AM81:AR81) -> 253722.98 | AU81: =AR81*Assumpt!$E$40 -> 0 | AV81: =AU81*Assumpt!$E$40 -> 0 | AW81: =AV81*Assumpt!$E$40 -> 0 | AX81: =AW81*Assumpt!$E$40 -> 0 | AY81: =SUM(AU81:AX81) -> 0 | AZ81: =AL81+AS81+AY81 -> 253722.98 | BC81: =AV81-AU81 -> 0
H82: =CONCATENATE(K82,I82) -> 11ODCS | I82: ODCS | J82: IS Labor | K82: 11 | AM82: 0 | AN82: 0 | AO82: =AN82*Assumpt!F$40 -> 0 | AP82: =AO82*Assumpt!G$40 -> 0 | AQ82: =AP82*Assumpt!H$40 -> 0 | AR82: =AQ82*Assumpt!I$40 -> 0 | AS82: =SUM(AM82:AR82) -> 0 | AU82: =AR82*Assumpt!$E$40 -> 0 | AV82: =AU82*Assumpt!$E$40 -> 0 | AW82: =AV82*Assumpt!$E$40 -> 0 | AX82: =AW82*Assumpt!$E$40 -> 0 | AY82: =SUM(AU82:AX82) -> 0 | AZ82: =AL82+AS82+AY82 -> 0 | BC82: =AV82-AU82 -> 0
H83: =CONCATENATE(K83,I83) -> 11ODCS | I83: ODCS | J83: Repairs & Mtc - Non Client Facility | K83: 11 | AM83: 4995.5271 | AN83: 6664.0208 | AO83: =AN83*Assumpt!F$40 -> 6664.0208 | AP83: =AO83*Assumpt!G$40 -> 6664.0208 | AQ83: =AP83*Assumpt!H$40 -> 6664.0208 | AR83: =AQ83*Assumpt!I$40 -> 6664.0208 | AS83: =SUM(AM83:AR83) -> 38315.631 | AU83: =AR83*Assumpt!$E$40 -> 6664.0208 | AV83: =AU83*Assumpt!$E$40 -> 6664.0208 | AW83: =AV83*Assumpt!$E$40 -> 6664.0208 | AX83: =AW83*Assumpt!$E$40 -> 6664.0208 | AY83: =SUM(AU83:AX83) -> 26656.083 | AZ83: =AL83+AS83+AY83 -> 64971.714 | BC83: =AV83-AU83 -> 0
H84: =CONCATENATE(K84,I84) -> 11ODCS | I84: ODCS | J84: Utilities | K84: 11 | AM84: 470748.62 | AN84: 629500.98 | AO84: =(AN84-160000)*Assumpt!F$40 -> 469500.98 | AP84: =AO84*Assumpt!G$40 -> 469500.98 | AQ84: =AP84*Assumpt!H$40 -> 469500.98 | AR84: =AQ84*Assumpt!I$40 -> 469500.98 | AS84: =SUM(AM84:AR84) -> 2978253.5 | AU84: =AR84*Assumpt!$E$40 -> 469500.98 | AV84: =AU84*Assumpt!$E$40 -> 469500.98 | AW84: =AV84*Assumpt!$E$40 -> 469500.98 | AX84: =AW84*Assumpt!$E$40 -> 469500.98 | AY84: =SUM(AU84:AX84) -> 1878003.9 | AZ84: =AL84+AS84+AY84 -> 4856257.4 | BC84: =AV84-AU84 -> 0
H85: =CONCATENATE(K85,I85) -> 11ODCS | I85: ODCS | J85: Janitorial | K85: 11 | AM85: 293821.29 | AN85: 394483.22 | AO85: =AN85*Assumpt!F$40 -> 394483.22 | AP85: =AO85*Assumpt!G$40 -> 394483.22 | AQ85: =AP85*Assumpt!H$40 -> 394483.22 | AR85: =AQ85*Assumpt!I$40 -> 394483.22 | AS85: =SUM(AM85:AR85) -> 2266237.4 | AU85: =AR85*Assumpt!$E$40 -> 394483.22 | AV85: =AU85*Assumpt!$E$40 -> 394483.22 | AW85: =AV85*Assumpt!$E$40 -> 394483.22 | AX85: =AW85*Assumpt!$E$40 -> 394483.22 | AY85: =SUM(AU85:AX85) -> 1577932.9 | AZ85: =AL85+AS85+AY85 -> 3844170.3 | BC85: =AV85-AU85 -> 0
H86: =CONCATENATE(K86,I86) -> 11ODCS | I86: ODCS | J86: Security - Alarm Companies | K86: 11 | AM86: 52436.572 | AN86: 69950.257 | AO86: =AN86*Assumpt!F$40 -> 69950.257 | AP86: =AO86*Assumpt!G$40 -> 69950.257 | AQ86: =AP86*Assumpt!H$40 -> 69950.257 | AR86: =AQ86*Assumpt!I$40 -> 69950.257 | AS86: =SUM(AM86:AR86) -> 402187.86 | AU86: =AR86*Assumpt!$E$40 -> 69950.257 | AV86: =AU86*Assumpt!$E$40 -> 69950.257 | AW86: =AV86*Assumpt!$E$40 -> 69950.257 | AX86: =AW86*Assumpt!$E$40 -> 69950.257 | AY86: =SUM(AU86:AX86) -> 279801.03 | AZ86: =AL86+AS86+AY86 -> 681988.88 | BC86: =AV86-AU86 -> 0
H87: =CONCATENATE(K87,I87) -> 11ODCS | I87: ODCS | J87: Pest Control | K87: 11 | AM87: 35165.82 | AN87: 46911.116 | AO87: =AN87*Assumpt!F$40 -> 46911.116 | AP87: =AO87*Assumpt!G$40 -> 46911.116 | AQ87: =AP87*Assumpt!H$40 -> 46911.116 | AR87: =AQ87*Assumpt!I$40 -> 46911.116 | AS87: =SUM(AM87:AR87) -> 269721.4 | AU87: =AR87*Assumpt!$E$40 -> 46911.116 | AV87: =AU87*Assumpt!$E$40 -> 46911.116 | AW87: =AV87*Assumpt!$E$40 -> 46911.116 | AX87: =AW87*Assumpt!$E$40 -> 46911.116 | AY87: =SUM(AU87:AX87) -> 187644.46 | AZ87: =AL87+AS87+AY87 -> 457365.86 | BC87: =AV87-AU87 -> 0
H88: =CONCATENATE(K88,I88) -> 11ODCS | I88: ODCS | J88: Lawn Care | K88: 11 | AM88: 217237.62 | AN88: 270598.95 | AO88: =AN88*Assumpt!F$40 -> 270598.95 | AP88: =AO88*Assumpt!G$40 -> 270598.95 | AQ88: =AP88*Assumpt!H$40 -> 270598.95 | AR88: =AQ88*Assumpt!I$40 -> 270598.95 | AS88: =SUM(AM88:AR88) -> 1570232.4 | AU88: =AR88*Assumpt!$E$40 -> 270598.95 | AV88: =AU88*Assumpt!$E$40 -> 270598.95 | AW88: =AV88*Assumpt!$E$40 -> 270598.95 | AX88: =AW88*Assumpt!$E$40 -> 270598.95 | AY88: =SUM(AU88:AX88) -> 1082395.8 | AZ88: =AL88+AS88+AY88 -> 2652628.2 | BC88: =AV88-AU88 -> 0
H89: =CONCATENATE(K89,I89) -> 11ODCS | I89: ODCS | J89: Repairs & Maintenance - Bldg -Billable | K89: 11 | AM89: 0 | AN89: 0 | AO89: =AN89*Assumpt!F$40 -> 0 | AP89: =AO89*Assumpt!G$40 -> 0 | AQ89: =AP89*Assumpt!H$40 -> 0 | AR89: =AQ89*Assumpt!I$40 -> 0 | AS89: =SUM(AM89:AR89) -> 0 | AU89: =AR89*Assumpt!$E$40 -> 0 | AV89: =AU89*Assumpt!$E$40 -> 0 | AW89: =AV89*Assumpt!$E$40 -> 0 | AX89: =AW89*Assumpt!$E$40 -> 0 | AY89: =SUM(AU89:AX89) -> 0 | AZ89: =AL89+AS89+AY89 -> 0 | BC89: =AV89-AU89 -> 0
H90: =CONCATENATE(K90,I90) -> 11ODCS | I90: ODCS | J90: Trash | K90: 11 | AM90: 97431.696 | AN90: 129973.64 | AO90: =AN90*Assumpt!F$40 -> 129973.64 | AP90: =AO90*Assumpt!G$40 -> 129973.64 | AQ90: =AP90*Assumpt!H$40 -> 129973.64 | AR90: =AQ90*Assumpt!I$40 -> 129973.64 | AS90: =SUM(AM90:AR90) -> 747299.9 | AU90: =AR90*Assumpt!$E$40 -> 129973.64 | AV90: =AU90*Assumpt!$E$40 -> 129973.64 | AW90: =AV90*Assumpt!$E$40 -> 129973.64 | AX90: =AW90*Assumpt!$E$40 -> 129973.64 | AY90: =SUM(AU90:AX90) -> 519894.56 | AZ90: =AL90+AS90+AY90 -> 1267194.5 | BC90: =AV90-AU90 -> 0
H91: =CONCATENATE(K91,I91) -> 11ODCS | I91: ODCS | J91: Repairs & Maintenance - Bldg - Not Billable | K91: 11 | AM91: 12418.983 | AN91: 16566.892 | AO91: =AN91*Assumpt!F$40 -> 16566.892 | AP91: =AO91*Assumpt!G$40 -> 16566.892 | AQ91: =AP91*Assumpt!H$40 -> 16566.892 | AR91: =AQ91*Assumpt!I$40 -> 16566.892 | AS91: =SUM(AM91:AR91) -> 95253.441 | AU91: =AR91*Assumpt!$E$40 -> 16566.892 | AV91: =AU91*Assumpt!$E$40 -> 16566.892 | AW91: =AV91*Assumpt!$E$40 -> 16566.892 | AX91: =AW91*Assumpt!$E$40 -> 16566.892 | AY91: =SUM(AU91:AX91) -> 66267.567 | AZ91: =AL91+AS91+AY91 -> 161521.01 | BC91: =AV91-AU91 -> 0
H92: =CONCATENATE(K92,I92) -> 11ODCS | I92: ODCS | J92: Wait time penalties | K92: 11 | AM92: 370000 | AN92: 500000 | AO92: =AN92*Assumpt!F$40 -> 500000 | AP92: =AO92*Assumpt!G$40 -> 500000 | AQ92: =AP92*Assumpt!H$40 -> 500000 | AR92: =AQ92*Assumpt!I$40 -> 500000 | AS92: =SUM(AM92:AR92) -> 2870000 | AU92: =AR92*Assumpt!$E$40 -> 500000 | AV92: =AU92*Assumpt!$E$40 -> 500000 | AW92: =AV92*Assumpt!$E$40 -> 500000 | AX92: =AW92*Assumpt!$E$40 -> 500000 | AY92: =SUM(AU92:AX92) -> 2000000 | AZ92: =AL92+AS92+AY92 -> 4870000 | BC92: =AV92-AU92 -> 0
H93: =CONCATENATE(K93,I93) -> 11ODCS | I93: ODCS | J93: Contributions/Non-Billable Expense | K93: 11 | AM93: 0 | AN93: 0 | AO93: =AN93*Assumpt!F$40 -> 0 | AP93: =AO93*Assumpt!G$40 -> 0 | AQ93: =AP93*Assumpt!H$40 -> 0 | AR93: =AQ93*Assumpt!I$40 -> 0 | AS93: =SUM(AM93:AR93) -> 0 | AU93: =AR93*Assumpt!$E$40 -> 0 | AV93: =AU93*Assumpt!$E$40 -> 0 | AW93: =AV93*Assumpt!$E$40 -> 0 | AX93: =AW93*Assumpt!$E$40 -> 0 | AY93: =SUM(AU93:AX93) -> 0 | AZ93: =AL93+AS93+AY93 -> 0 | BC93: =AV93-AU93 -> 0
H94: =CONCATENATE(K94,I94) -> 11ODCS | I94: ODCS | J94: cap repairs | K94: 11 | AM94: =600000 -> 600000 | AN94: =AM94 -> 600000 | AO94: =AN94*Assumpt!F$40 -> 600000 | AP94: =AO94*Assumpt!G$40 -> 600000 | AQ94: =AP94*Assumpt!H$40 -> 600000 | AR94: =AQ94*Assumpt!I$40 -> 600000 | AS94: =SUM(AM94:AR94) -> 3600000 | AU94: =AR94*Assumpt!$E$40 -> 600000 | AV94: =AU94*Assumpt!$E$40 -> 600000 | AW94: =AV94*Assumpt!$E$40 -> 600000 | AX94: =AW94*Assumpt!$E$40 -> 600000 | AY94: =SUM(AU94:AX94) -> 2400000 | AZ94: =AL94+AS94+AY94 -> 6000000 | BC94: =AV94-AU94 -> 0
H95: =CONCATENATE(K95,I95) -> 11ODCS | I95: ODCS | J95: Capital Repairs | K95: 11 | AM95: 0 | AN95: 0 | AO95: =AN95*Assumpt!F$40 -> 0 | AP95: =AO95*Assumpt!G$40 -> 0 | AQ95: =AP95*Assumpt!H$40 -> 0 | AR95: =AQ95*Assumpt!I$40 -> 0 | AS95: =SUM(AM95:AR95) -> 0 | AU95: 0 | AV95: 0 | AW95: 0 | AX95: 0 | AY95: =SUM(AU95:AX95) -> 0 | AZ95: =AL95+AS95+AY95 -> 0 | BC95: =AV95-AU95 -> 0
H96: =CONCATENATE(K96,I96) | AO96: =AN96*Assumpt!F$40 -> 0 | AP96: =AO96*Assumpt!G$40 -> 0 | AQ96: =AP96*Assumpt!H$40 -> 0 | AR96: =AQ96*Assumpt!I$40 -> 0 | AS96: =SUM(AM96:AR96) -> 0 | AY96: =SUM(AU96:AX96) -> 0 | AZ96: =AL96+AS96+AY96 -> 0 | BC96: =AV96-AU96 -> 0
B97: PIF Pricing Desktop | H97: =CONCATENATE(K97,I97) -> 3Capital | I97: Capital | J97: PIF Desktop | K97: 3 | M97: ='DESKTOP (PIF)'!E20 -> 1634 | Y97: =Assumpt!D79 -> 1250 | AM97: =$M97*(1+$N97)*Y97*Assumpt!D$41 -> 2042500 | AO97: =AN97*Assumpt!F$40 -> 0 | AP97: =AO97*Assumpt!G$40 -> 0 | AQ97: =AP97*Assumpt!H$40 -> 0 | AR97: =AQ97*Assumpt!I$40 -> 0 | AS97: =SUM(AM97:AR97) -> 2042500 | AY97: =SUM(AU97:AX97) -> 0 | AZ97: =AL97+AS97+AY97 -> 2042500 | BC97: =AV97-AU97 -> 0
H98: =CONCATENATE(K98,I98) | AO98: =AN98*Assumpt!F$40 -> 0 | AP98: =AO98*Assumpt!G$40 -> 0 | AQ98: =AP98*Assumpt!H$40 -> 0 | AR98: =AQ98*Assumpt!I$40 -> 0 | AS98: =SUM(AM98:AR98) -> 0 | AY98: =SUM(AU98:AX98) -> 0 | AZ98: =AL98+AS98+AY98 -> 0 | BC98: =AV98-AU98 -> 0
H99: =CONCATENATE(K99,I99) -> 6Capital | I99: Capital | J99: Spare equipment for pifs | K99: 6 | M99: ='DESKTOP (PIF)'!E20 -> 1634 | Z99: =Assumpt!E79*5% -> 62.5 | AA99: =Assumpt!F79*5% -> 62.5 | AB99: =Assumpt!G79*5% -> 62.5 | AC99: =Assumpt!H79*5% -> 62.5 | AD99: =Assumpt!I79*5% -> 62.5 | AE99: =Assumpt!J79*5% -> 62.5 | AF99: =Assumpt!K79*5% -> 62.5 | AG99: =Assumpt!L79*5% -> 62.5 | AH99: =Assumpt!M79*5% -> 62.5 | AM99: =$M99*(1+$N99)*Y99*Assumpt!D$41 -> 0 | AN99: =$M99*(1+$N99)*Z99*Assumpt!E$41-30000 -> 72125 | AO99: =AN99*Assumpt!F$40 -> 72125 | AP99: =AO99*Assumpt!G$40 -> 72125 | AQ99: =AP99*Assumpt!H$40 -> 72125 | AR99: =AQ99*Assumpt!I$40 -> 72125 | AS99: =SUM(AM99:AR99) -> 360625 | AU99: =$M99*(1+$N99)*AE99*Assumpt!J41 -> 102125 | AV99: =$M99*(1+$N99)*AF99*Assumpt!K41 -> 102125 | AW99: =$M99*(1+$N99)*AG99*Assumpt!L41 -> 102125 | AX99: =$M99*(1+$N99)*AH99*Assumpt!M41 -> 102125 | AY99: =SUM(AU99:AX99) -> 408500 | AZ99: =AL99+AS99+AY99 -> 769125 | BC99: =AV99-AU99 -> 0
H100: =CONCATENATE(K100,I100) -> 6ODCS | I100: ODCS | J100: Consumables | K100: 6 | M100: 50 | Z100: =Assumpt!E79 -> 1250 | AA100: =Assumpt!F79 -> 1250 | AB100: =Assumpt!G79 -> 1250 | AC100: =Assumpt!H79 -> 1250 | AD100: =Assumpt!I79 -> 1250 | AE100: =Assumpt!J79 -> 1250 | AF100: =Assumpt!K79 -> 1250 | AG100: =Assumpt!L79 -> 1250 | AH100: =Assumpt!M79 -> 1250 | AM100: =$M100*(1+$N100)*Y100*Assumpt!D$41 -> 0 | AN100: =$M100*(1+$N100)*Z100*Assumpt!E$41 -> 62500 | AO100: =AN100*Assumpt!F$40 -> 62500 | AP100: =AO100*Assumpt!G$40 -> 62500 | AQ100: =AP100*Assumpt!H$40 -> 62500 | AR100: =AQ100*Assumpt!I$40 -> 62500 | AS100: =SUM(AM100:AR100) -> 312500 | AU100: =$M100*(1+$N100)*AE100*Assumpt!J$41 -> 62500 | AV100: =$M100*(1+$N100)*AF100*Assumpt!K$41 -> 62500 | AW100: =$M100*(1+$N100)*AG100*Assumpt!L$41 -> 62500 | AX100: =$M100*(1+$N100)*AH100*Assumpt!M$41 -> 62500 | AY100: =SUM(AU100:AX100) -> 250000 | AZ100: =AL100+AS100+AY100 -> 562500 | BC100: =AV100-AU100 -> 0
AS101: =SUM(AM101:AR101) -> 0 | AY101: =SUM(AU101:AX101) -> 0 | AZ101: =AL101+AS101+AY101 -> 0 | BC101: =AV101-AU101 -> 0
AS102: =SUM(AM102:AR102) -> 0 | AY102: =SUM(AU102:AX102) -> 0 | AZ102: =AL102+AS102+AY102 -> 0 | BC102: =AV102-AU102 -> 0
...

Sheet cash flow
F2: startup | G2: Year 1 | H2: Year 2 | I2: Year 3 | J2: Year 4 | K2: Year 5 | L2: Year 6 | M2: Total Years 0 - 6 | V2: Year 7 costs | W2: Year 8 costs | X2: Year 9 costs | Y2: Year 10 costs | Z2: Total costs Years 7-10
A3: Summary
B4: Revenue | G4: =G21 -> 25400586 | H4: =H21 -> 32254194 | I4: =I21 -> 29991650 | J4: =J21 -> 30343573 | K4: =K21 -> 30741693 | L4: =L21 -> 30903854 | M4: =SUM(G4:L4) -> 1.7963555e+08 | V4: =V21 -> 31564253 | W4: =W21 -> 31266527 | X4: =X21 -> 31433602 | Y4: =Y21 -> 31986462 | Z4: =Z21 -> 1.2625084e+08 | AA4: =Z4+M4 -> 3.058864e+08
B5: Expenses | G5: =G34 -> 25165256 | H5: =H34 -> 28036995 | I5: =I34 -> 27830703 | J5: =J34 -> 28160631 | K5: =K34 -> 28533868 | L5: =L34 -> 28685895 | M5: =SUM(G5:L5) -> 1.6641335e+08 | V5: =V34 -> 29335018 | W5: =W34 -> 29055901 | X5: =X34 -> 29212534 | Y5: =Y34 -> 29730839 | Z5: =Z34 -> 1.1733429e+08 | AA5: =Z5+M5 -> 2.8374764e+08
B6: Profit | G6: =G4-G5 -> 235329.55 | H6: =H4-H5 -> 4217198.6 | I6: =I4-I5 -> 2160946.9 | J6: =J4-J5 -> 2182942.1 | K6: =K4-K5 -> 2207824.6 | L6: =L4-L5 -> 2217959.6 | M6: =SUM(G6:L6) -> 13222201 | O6: =M6-P150 -> 1.4901161e-08 | V6: =V4-V5 -> 2229234.6 | W6: =W4-W5 -> 2210626.7 | X6: =X4-X5 -> 2221068.9 | Y6: =Y4-Y5 -> 2255622.6 | Z6: =Z4-Z5 -> 8916552.8 | AA6: =AA4-AA5 -> 22138754 | AB6: =AC150-Z6 -> 0
B7: Cumulative profit | G7: =G6 -> 235329.55 | H7: =G7+H6 -> 4452528.2 | I7: =H7+I6 -> 6613475.1 | J7: =I7+J6 -> 8796417.1 | K7: =J7+K6 -> 11004242 | L7: =K7+L6 -> 13222201 | V7: =V6 -> 2229234.6 | W7: =V7+W6 -> 4439861.3 | X7: =W7+X6 -> 6660930.2 | Y7: =X7+Y6 -> 8916552.8 | AA7: =Z7 -> 0
L8: GP& | M8: =(M4-M5)/M5 -> 0.07945397 | Y8: GP& | Z8: =(Z4-Z5)/Z5 -> 0.075992727 | AA8: =(AA4-AA5)/AA5 -> 0.07802269
A11: Revenue totals
A12: 1 | B12: All NGVID Required Documents Bid Solicitation Section 3.51, 3.52 | G12: =G54 -> 81251.111 | M12: =SUM(G12:L12) -> 81251.111 | V12: =V59 -> 0 | W12: =W59 -> 0 | X12: =X59 -> 0 | Y12: =Y59 -> 0 | Z12: =SUM(V12:Y12) -> 0
A13: 2 | B13: Design, Development, and Implementation Bid Solicitation Section 3.38, 3.39.1 | G13: =G57 -> 323798.08 | M13: =SUM(G13:L13) -> 323798.08 | V13: =V60 -> 0 | W13: =W60 -> 0 | X13: =X60 -> 0 | Y13: =Y60 -> 0 | Z13: =SUM(V13:Y13) -> 0
A14: 3 | B14: PIF desktop | G14: =G61 -> 680833.33 | H14: =H61 -> 2042500 | M14: =SUM(G14:L14) -> 2723333.3 | V14: =V61 -> 0 | W14: =W61 -> 0 | X14: =X61 -> 0 | Y14: =Y61 -> 0 | Z14: =SUM(V14:Y14) -> 0
A15: 5 | B15: Inspection transaction fee for PIFs and PFFs (days 91 - 365, maintenance only)Bid Solicitation Section 3.1.3 & 3.27 | G15: =G66 -> 0 | M15: =SUM(G15:L15) -> 0 | Z15: =SUM(V15:Y15) -> 0
A16: 6 | B16: Inspection transaction fee for PIFs and PFFs (days 91 - 365, maintenance only)Bid Solicitation Section 3.1.3 & 3.27 | G16: =G72 -> 814810 | H16: =H72 -> 1282500 | I16: =I72 -> 1282500 | J16: =J72 -> 1282500 | K16: =K72 -> 1282500 | L16: =L72 -> 1282500 | M16: =SUM(G16:L16) -> 7227310 | V16: =V72 -> 1282500 | W16: =W72 -> 1282500 | X16: =X72 -> 1282500 | Y16: =Y72 -> 1282500 | Z16: =SUM(V16:Y16) -> 5130000
A17: 9 | B17: CIF Retrofit | G17: =O128 -> 1444985.5 | M17: =SUM(G17:L17) -> 1444985.5 | V17: =AC128 -> 0 | W17: =AD128 -> 0 | X17: =AE128 -> 0 | Y17: =AF128 -> 0 | Z17: =SUM(V17:Y17) -> 0
A18: 10 | B18: Revenue CIF | G18: =G82 -> 0 | M18: =SUM(G18:L18) -> 0 | Z18: =SUM(V18:Y18) -> 0
A19: 11 | B19: Revenue CIF | G19: =G147 -> 22054908 | H19: =H147 -> 28929194 | I19: =I147 -> 28709150 | J19: =J147 -> 29061073 | K19: =K147 -> 29459193 | L19: =L147 -> 29621354 | M19: =SUM(G19:L19) -> 1.6783487e+08 | V19: =V86 -> 30281753 | W19: =W86 -> 29984027 | X19: =X86 -> 30151102 | Y19: =Y86 -> 30703962 | Z19: =SUM(V19:Y19) -> 1.2112084e+08
M20: =SUM(G20:L20) -> 0 | Z20: =SUM(V20:Y20) -> 0
B21: Total | G21: =SUM(G12:G19) -> 25400586 | H21: =SUM(H12:H19) -> 32254194 | I21: =SUM(I12:I19) -> 29991650 | J21: =SUM(J12:J19) -> 30343573 | K21: =SUM(K12:K19) -> 30741693 | L21: =SUM(L12:L19) -> 30903854 | M21: =SUM(G21:L21) -> 1.7963555e+08 | N21: =M21-M87 -> 0 | V21: =SUM(V12:V19) -> 31564253 | W21: =SUM(W12:W19) -> 31266527 | X21: =SUM(X12:X19) -> 31433602 | Y21: =SUM(Y12:Y19) -> 31986462 | Z21: =SUM(V21:Y21) -> 1.2625084e+08
A23: Expense totals
A24: 1 | B24: All NGVID Required Documents Bid Solicitation Section 3.51, 3.52 | G24: =G93 -> 73125 | H24: =H93 -> 1 | I24: =I93 -> 0 | J24: =J93 -> 0 | K24: =K93 -> 0 | L24: =L93 -> 0 | M24: =SUM(G24:L24) -> 73126 | V24: =V93 -> 0 | W24: =W93 -> 0 | X24: =X93 -> 0 | Y24: =Y93 -> 0 | Z24: =SUM(V24:Y24) -> 0
A25: 2 | B25: Design, Development, and Implementation Bid Solicitation Section 3.38, 3.39.1 | G25: =G98 -> 291418.27 | H25: =H98 -> 0 | I25: =I98 -> 0 | J25: =J98 -> 0 | K25: =K98 -> 0 | L25: =L98 -> 0 | M25: =SUM(G25:L25) -> 291418.27 | V25: =V98 -> 0 | W25: =W98 -> 0 | X25: =X98 -> 0 | Y25: =Y98 -> 0 | Z25: =SUM(V25:Y25) -> 0
A26: 3 | B26: PIF desktop | G26: =G104 -> 2042500 | H26: =H104 -> 0 | I26: =I104 -> 0 | J26: =J104 -> 0 | K26: =K104 -> 0 | L26: =L104 -> 0 | M26: =SUM(G26:L26) -> 2042500 | V26: =V104 -> 0 | W26: =W104 -> 0 | X26: =X104 -> 0 | Y26: =Y104 -> 0 | Z26: =SUM(V26:Y26) -> 0
M27: =SUM(G27:L27) -> 0 | Z27: =SUM(V27:Y27) -> 0
A28: 5 | B28: Inspection transaction fee for PIFs and PFFs (days 91 - 365, maintenance only)Bid Solicitation Section 3.1.3 & 3.27 | G28: =G109 -> 0 | M28: =SUM(G28:L28) -> 0 | V28: =V109 -> 0 | W28: =W109 -> 0 | X28: =X109 -> 0 | Y28: =Y109 -> 0 | Z28: =SUM(V28:Y28) -> 0
A29: 6 | B29: Inspection transaction fee for PIFs and PFFs (including NGVID & all maintenance) Bid Solicitation Section 3.1.2 | H29: =H117 -> 134625 | I29: =I117 -> 134625 | J29: =J117 -> 134625 | K29: =K117 -> 134625 | L29: =L117 -> 134625 | M29: =SUM(G29:L29) -> 673125 | V29: =V117 -> 164625 | W29: =W117 -> 164625 | X29: =X117 -> 164625 | Y29: =Y117 -> 164625 | Z29: =SUM(V29:Y29) -> 658500
A30: 9 | B30: CIF Retrofit | G30: =G128 -> 1300486.9 | H30: =H128 -> 0 | I30: =I128 -> 0 | J30: =J128 -> 0 | K30: =K128 -> 0 | L30: =L128 -> 0 | M30: =SUM(G30:L30) -> 1300486.9 | V30: =V128 -> 0 | W30: =W128 -> 0 | X30: =X128 -> 0 | Y30: =Y128 -> 0 | Z30: =SUM(V30:Y30) -> 0
A31: 10 | B31: Revenue CIF | G31: =G134 -> 0 | M31: =SUM(G31:L31) -> 0 | V31: =V134 -> 0 | W31: =W134 -> 0 | X31: =X134 -> 0 | Y31: =Y134 -> 0 | Z31: =SUM(V31:Y31) -> 0
A32: 11 | B32: Revenue CIF | G32: =G141 -> 21457726 | H32: =H141 -> 27902369 | I32: =I141 -> 27696078 | J32: =J141 -> 28026006 | K32: =K141 -> 28399243 | L32: =L141 -> 28551270 | M32: =SUM(G32:L32) -> 1.6203269e+08 | V32: =V141 -> 29170393 | W32: =W141 -> 28891276 | X32: =X141 -> 29047909 | Y32: =Y141 -> 29566214 | Z32: =SUM(V32:Y32) -> 1.1667579e+08
Z33: =SUM(V33:Y33) -> 0
B34: Total | G34: =SUM(G24:G32) -> 25165256 | H34: =SUM(H24:H32) -> 28036995 | I34: =SUM(I24:I32) -> 27830703 | J34: =SUM(J24:J32) -> 28160631 | K34: =SUM(K24:K32) -> 28533868 | L34: =SUM(L24:L32) -> 28685895 | M34: =SUM(G34:L34) -> 1.6641335e+08 | V34: =SUM(V24:V32) -> 29335018 | W34: =SUM(W24:W32) -> 29055901 | X34: =SUM(X24:X32) -> 29212534 | Y34: =SUM(Y24:Y32) -> 29730839 | Z34: =SUM(V34:Y34) -> 1.1733429e+08
F36: xcheck | G36: ='Pricing details'!AM139-G34 -> 0 | H36: ='Pricing details'!AN139-H34 -> 0 | I36: ='Pricing details'!AO139-I34 -> 0 | J36: ='Pricing details'!AP139-J34 -> 0 | K36: ='Pricing details'!AQ139-K34 -> 0 | L36: ='Pricing details'!AR139-L34 -> 0 | M36: ='Pricing details'!AS139-M34 -> 0 | V36: ='Pricing details'!AU122-'cash flow'!V34 -> 0 | W36: ='Pricing details'!AV122-'cash flow'!W34 -> 0 | X36: ='Pricing details'!AW122-'cash flow'!X34 -> 0 | Y36: ='Pricing details'!AX122-'cash flow'!Y34 -> 0 | Z36: =SUM(V36:Y36) -> 0
A37: Profit totals
A38: 1 | B38: All NGVID Required Documents Bid Solicitation Section 3.51, 3.52 | G38: =G12-G24 -> 8126.1111 | H38: =H12-H24 -> -1 | I38: =I12-I24 -> 0 | J38: =J12-J24 -> 0 | K38: =K12-K24 -> 0 | L38: =L12-L24 -> 0 | M38: =SUM(G38:L38) -> 8125.1111 | V38: =V12-V24 -> 0 | W38: =W12-W24 -> 0 | X38: =X12-X24 -> 0 | Y38: =Y12-Y24 -> 0 | Z38: =SUM(T38:Y38) -> 0
A39: 2 | B39: Design, Development, and Implementation Bid Solicitation Section 3.38, 3.39.1 | G39: =G13-G25 -> 32379.808 | H39: =H13-H25 -> 0 | I39: =I13-I25 -> 0 | J39: =J13-J25 -> 0 | K39: =K13-K25 -> 0 | L39: =L13-L25 -> 0 | M39: =SUM(G39:L39) -> 32379.808 | V39: =V13-V25 -> 0 | W39: =W13-W25 -> 0 | X39: =X13-X25 -> 0 | Y39: =Y13-Y25 -> 0 | Z39: =SUM(T39:Y39) -> 0
A40: 3 | B40: PIF desktop | G40: =G14-G26 -> -1361666.7 | H40: =H14-H26 -> 2042500 | I40: =I14-I26 -> 0 | J40: =J14-J26 -> 0 | K40: =K14-K26 -> 0 | L40: =L14-L26 -> 0 | M40: =SUM(G40:L40) -> 680833.33 | V40: =V14-V26 -> 0 | W40: =W14-W26 -> 0 | X40: =X14-X26 -> 0 | Y40: =Y14-Y26 -> 0 | Z40: =SUM(T40:Y40) -> 0
A41: 5 | B41: Inspection transaction fee for PIFs and PFFs (days 91 - 365, maintenance only)Bid Solicitation Section 3.1.3 & 3.27 | G41: =G15-G28 -> 0 | M41: =SUM(G41:L41) -> 0 | Z41: =SUM(T41:Y41) -> 0
A42: 6 | B42: Inspection transaction fee for PIFs and PFFs (including NGVID & all maintenance) Bid Solicitation Section 3.1.2 | G42: =G16-G29 -> 814810 | H42: =H16-H29 -> 1147875 | I42: =I16-I29 -> 1147875 | J42: =J16-J29 -> 1147875 | K42: =K16-K29 -> 1147875 | L42: =L16-L29 -> 1147875 | M42: =SUM(G42:L42) -> 6554185 | O42: =M42-P119 -> 0 | V42: =V16-V29 -> 1117875 | W42: =W16-W29 -> 1117875 | X42: =X16-X29 -> 1117875 | Y42: =Y16-Y29 -> 1117875 | Z42: =SUM(T42:Y42) -> 4471500
A43: 9 | B43: CIF Retrofit | G43: =(G17-G30)+(H17-H30) -> 144498.55 | I43: =I17-I30 -> 0 | J43: =J17-J30 -> 0 | K43: =K17-K30 -> 0 | L43: =L17-L30 -> 0 | M43: =SUM(G43:L43) -> 144498.55 | V43: =V17-V30 -> 0 | W43: =W17-W30 -> 0 | X43: =X17-X30 -> 0 | Y43: =Y17-Y30 -> 0 | Z43: =SUM(T43:Y43) -> 0
A44: 10 | B44: Revenue CIF | G44: =G18-G31 -> 0 | M44: =SUM(G44:L44) -> 0 | Z44: =SUM(T44:Y44) -> 0
A45: 11 | B45: Revenue CIF | G45: =G19-G32 -> 597181.75 | H45: =H19-H32 -> 1026824.6 | I45: =I19-I32 -> 1013071.9 | J45: =J19-J32 -> 1035067.1 | K45: =K19-K32 -> 1059949.6 | L45: =L19-L32 -> 1070084.6 | M45: =SUM(G45:L45) -> 5802179.5 | V45: =V19-V32 -> 1111359.6 | W45: =W19-W32 -> 1092751.7 | X45: =X19-X32 -> 1103193.9 | Y45: =Y19-Y32 -> 1137747.6 | Z45: =SUM(T45:Y45) -> 4445052.8
B47: Total | G47: =SUM(G38:G45) -> 235329.55 | H47: =SUM(H38:H45) -> 4217198.6 | I47: =SUM(I38:I45) -> 2160946.9 | J47: =SUM(J38:J45) -> 2182942.1 | K47: =SUM(K38:K45) -> 2207824.6 | L47: =SUM(L38:L45) -> 2217959.6 | M47: =SUM(G47:L47) -> 13222201 | V47: =SUM(V38:V45) -> 2229234.6 | W47: =SUM(W38:W45) -> 2210626.7 | X47: =SUM(X38:X45) -> 2221068.9 | Y47: =SUM(Y38:Y45) -> 2255622.6 | Z47: =SUM(T47:Y47) -> 8916552.8
B48: Cumulative total | G48: =G47 -> 235329.55 | H48: =G48+H47 -> 4452528.2 | I48: =H48+I47 -> 6613475.1 | J48: =I48+J47 -> 8796417.1 | K48: =J48+K47 -> 11004242 | L48: =K48+L47 -> 13222201 | V48: =U48+V47 -> 2229234.6 | W48: =V48+W47 -> 4439861.3 | X48: =W48+X47 -> 6660930.2 | Y48: =X48+Y47 -> 8916552.8
L49: GP% | M49: =M47/M34 -> 0.07945397 | Y49: GP% | Z49: =Z47/Z34 -> 0.075992727
A52: Revenue
A53: Line item
A54: 1 | B54: All NGVID Required Documents Bid Solicitation Section 3.51, 3.52 | G54: =O90 -> 81251.111 | M54: =SUM(G54:L54) -> 81251.111
A57: 2 | B57: Design, Development, and Implementation Bid Solicitation Section 3.38, 3.39.1 | G57: =O98 -> 323798.08 | M57: =SUM(G57:L57) -> 323798.08
A60: 3 | B60: PIF desktop | C60: Units
C61: Revenue | G61: =O103*0.25 -> 680833.33 | H61: =O103*0.75 -> 2042500 | M61: =SUM(G61:L61) -> 2723333.3
A63: 5 | B63: Inspection transaction fee for PIFs and PFFs (days 91 - 365, maintenance only)Bid Solicitation Section 3.1.3 & 3.27 | C63: Test volume
C64: Calculated Test fee
C65: Use test Fee
E66: total | M66: =SUM(G66:L66) -> 0
A69: 6 | B69: Inspection transaction fee for PIFs and PFFs (including NGVID & all maintenance) Bid Solicitation Section 3.1.2 | C69: Use test Fee | G69: =Assumpt!D65 -> 205000 | H69: =Assumpt!E65 -> 255000 | I69: =Assumpt!F65 -> 255000 | J69: =Assumpt!G65 -> 255000 | K69: =Assumpt!H65 -> 255000 | L69: =Assumpt!I65 -> 255000 | V69: =Assumpt!J65 -> 255000 | W69: =Assumpt!K65 -> 255000 | X69: =Assumpt!L65 -> 255000 | Y69: =Assumpt!M65 -> 255000
C70: Calculated Test fee | G70: =$O$121 -> 1.0662538 | H70: =$O$121 -> 1.0662538 | I70: =$O$121 -> 1.0662538 | J70: =$O$121 -> 1.0662538 | K70: =$O$121 -> 1.0662538 | L70: =$O$121 -> 1.0662538 | V70: =$AB$121 -> 1.4767052 | W70: =$AB$121 -> 1.4767052 | X70: =$AB$121 -> 1.4767052 | Y70: =$AB$121 -> 1.4767052
C71: Use test Fee | G71: =G120 -> 3.9746829 | H71: =H120 -> 5.0294118 | I71: =I120 -> 5.0294118 | J71: =J120 -> 5.0294118 | K71: =K120 -> 5.0294118 | L71: =L120 -> 5.0294118 | V71: =V120 -> 5.0294118 | W71: =W120 -> 5.0294118 | X71: =X120 -> 5.0294118 | Y71: =Y120 -> 5.0294118
E72: Total | G72: =G69*G71 -> 814810 | H72: =H69*H71 -> 1282500 | I72: =I69*I71 -> 1282500 | J72: =J69*J71 -> 1282500 | K72: =K69*K71 -> 1282500 | L72: =L69*L71 -> 1282500 | M72: =SUM(F72:L72) -> 7227310 | V72: =V69*V71 -> 1282500 | W72: =W69*W71 -> 1282500 | X72: =X69*X71 -> 1282500 | Y72: =Y69*Y71 -> 1282500 | Z72: =SUM(V72:Y72) -> 5130000
A76: 9 | B76: CIF Retrofit | G76: =O128 -> 1444985.5 | M76: =SUM(F76:L76) -> 1444985.5
A79: 10 | B79: Revenue CIF | C79: Test volume | H79: =Assumpt!E57 -> 0 | I79: =Assumpt!F57 -> 0 | J79: =Assumpt!G57 -> 0 | K79: =Assumpt!H57 -> 0 | L79: =Assumpt!I57 -> 0
C80: Test fee per year calculated
C81: Use ==> | G81: =G80 -> 0 | H81: =H80 -> 0 | I81: =I80 -> 0 | J81: =J80 -> 0 | K81: =K80 -> 0 | L81: =L80 -> 0
C82: Test fees | G82: =G79*G81 -> 0 | H82: =H79*H81 -> 0 | I82: =I79*I81 -> 0 | J82: =J79*J81 -> 0 | K82: =K79*K81 -> 0 | L82: =L79*L81 -> 0 | M82: =SUM(F82:L82) -> 0 | O82: =O137 -> with profit
A83: 11 | B83: Revenue CIF | C83: Test volume | G83: =Assumpt!D61 -> 1425000 | H83: =Assumpt!E61 -> 1900000 | I83: =Assumpt!F61 -> 1900000 | J83: =Assumpt!G61 -> 1900000 | K83: =Assumpt!H61 -> 1900000 | L83: =Assumpt!I61 -> 1900000 | V83: =Assumpt!J61 -> 1900000 | W83: =Assumpt!K61 -> 1900000 | X83: =Assumpt!L61 -> 1900000 | Y83: =Assumpt!M61 -> 1900000
C84: Test fee per year calculated | G84: =$O$143 -> 15.820126 | H84: =$O$143 -> 15.820126 | I84: =$O$143 -> 15.820126 | J84: =$O$143 -> 15.820126 | K84: =$O$143 -> 15.820126 | L84: =$O$143 -> 15.820126 | V84: =$AB$143 -> 0 | W84: =$AB$143 -> 0 | X84: =$AB$143 -> 0 | Y84: =$AB$143 -> 0
C85: Use ==> | G85: =G148 -> 15.477128 | H85: =H148 -> 15.225892 | I85: =I148 -> 15.110079 | J85: =J148 -> 15.295302 | K85: =K148 -> 15.504838 | L85: =L148 -> 15.590186 | V85: =V148 -> 15.937765 | W85: =W148 -> 15.781067 | X85: =X148 -> 15.869001 | Y85: =Y148 -> 16.15998
C86: Test fees | G86: =G83*G85 -> 22054908 | H86: =H83*H85 -> 28929194 | I86: =I83*I85 -> 28709150 | J86: =J83*J85 -> 29061073 | K86: =K83*K85 -> 29459193 | L86: =L83*L85 -> 29621354 | M86: =SUM(F86:L86) -> 1.6783487e+08 | O86: =O141 -> 1.7283487e+08 | V86: =V83*V85 -> 30281753 | W86: =W83*W85 -> 29984027 | X86: =X83*X85 -> 30151102 | Y86: =Y83*Y85 -> 30703962 | Z86: =SUM(V86:Y86) -> 1.2112084e+08 | AD86: =AD141 -> 0
M87: =SUM(M54:M86) -> 1.7963555e+08
G88: =G86+G82+G76+G72+G66+G61+G57+G54 -> 25400586 | H88: =H86+H82+H76+H72+H66+H61+H57+H54 -> 32254194 | I88: =I86+I82+I76+I72+I66+I61+I57+I54 -> 29991650 | J88: =J86+J82+J76+J72+J66+J61+J57+J54 -> 30343573 | K88: =K86+K82+K76+K72+K66+K61+K57+K54 -> 30741693 | L88: =L86+L82+L76+L72+L66+L61+L57+L54 -> 30903854 | M88: =SUM(G88:L88) -> 1.7963555e+08
A89: Expenses | E89: margin % | O89: with profit | AB89: With Profit
A90: 1 | B90: =B54 -> All NGVID Required Documents Bid Solicitation Section 3.51, 3.52 | C90: Labor | D90: =CONCATENATE(A90,C90) -> 1Labor | E90: 0.1 | G90: =SUMIF('Pricing details'!$H$12:$H$121,$D90:$D92,'Pricing details'!AM$12:AM$121) -> 73125 | H90: =SUMIF('Pricing details'!$H$12:$H$121,$D90:$D92,'Pricing details'!AN$12:AN$121) -> 1 | I90: =SUMIF('Pricing details'!$H$12:$H$121,$D90:$D92,'Pricing details'!AO$12:AO$121) -> 0 | J90: =SUMIF('Pricing details'!$H$12:$H$121,$D90:$D92,'Pricing details'!AP$12:AP$121) -> 0 | K90: =SUMIF('Pricing details'!$H$12:$H$121,$D90:$D92,'Pricing details'!AQ$12:AQ$121) -> 0 | L90: =SUMIF('Pricing details'!$H$12:$H$121,$D90:$D92,'Pricing details'!AR$12:AR$121) -> 0 | M90: =SUM(G90:L90) -> 73126 | O90: =M90/(1-E90) -> 81251.111 | R90: Labor | S90: =CONCATENATE(P90,R90) -> Labor | T90: 0.1 | V90: =SUMIF('Pricing details'!$H$12:$H$121,$D90:$D92,'Pricing details'!AU$12:AU$121) -> 0 | W90: =SUMIF('Pricing details'!$H$12:$H$121,$D90:$D92,'Pricing details'!AV$12:AV$121) -> 0 | X90: =SUMIF('Pricing details'!$H$12:$H$121,$D90:$D92,'Pricing details'!AW$12:AW$121) -> 0 | Y90: =SUMIF('Pricing details'!$H$12:$H$121,$D90:$D92,'Pricing details'!AX$12:AX$121) -> 0 | Z90: =SUM(V90:Y90) -> 0 | AB90: =Z90/(1-T90) -> 0
A91: 1 | C91: ODCS | D91: =CONCATENATE(A91,C91) -> 1ODCS | E91: 0.1 | G91: =SUMIF('Pricing details'!$H$12:$H$121,$D91:$D93,'Pricing details'!AM$12:AM$121) -> 0 | H91: =SUMIF('Pricing details'!$H$12:$H$121,$D91:$D93,'Pricing details'!AN$12:AN$121) -> 0 | I91: =SUMIF('Pricing details'!$H$12:$H$121,$D91:$D93,'Pricing details'!AO$12:AO$121) -> 0 | J91: =SUMIF('Pricing details'!$H$12:$H$121,$D91:$D93,'Pricing details'!AP$12:AP$121) -> 0 | K91: =SUMIF('Pricing details'!$H$12:$H$121,$D91:$D93,'Pricing details'!AQ$12:AQ$121) -> 0 | L91: =SUMIF('Pricing details'!$H$12:$H$121,$D91:$D93,'Pricing details'!AR$12:AR$121) -> 0 | M91: =SUM(G91:L91) -> 0 | O91: =M91/(1-E91) -> 0 | R91: ODCS | S91: =CONCATENATE(P91,R91) -> ODCS | T91: 0.1 | V91: =SUMIF('Pricing details'!$H$12:$H$121,$D91:$D93,'Pricing details'!AU$12:AU$121) -> 0 | W91: =SUMIF('Pricing details'!$H$12:$H$121,$D91:$D93,'Pricing details'!AV$12:AV$121) -> 0 | X91: =SUMIF('Pricing details'!$H$12:$H$121,$D91:$D93,'Pricing details'!AW$12:AW$121) -> 0 | Y91: =SUMIF('Pricing details'!$H$12:$H$121,$D91:$D93,'Pricing details'!AX$12:AX$121) -> 0 | Z91: =SUM(V91:Y91) -> 0 | AB91: =Z91/(1-T91) -> 0
A92: 1 | C92: Capital | D92: =CONCATENATE(A92,C92) -> 1Capital | E92: 0.1 | G92: =SUMIF('Pricing details'!$H$12:$H$121,$D92:$D95,'Pricing details'!AM$12:AM$121) -> 0 | H92: =SUMIF('Pricing details'!$H$12:$H$121,$D92:$D95,'Pricing details'!AN$12:AN$121) -> 0 | I92: =SUMIF('Pricing details'!$H$12:$H$121,$D92:$D95,'Pricing details'!AO$12:AO$121) -> 0 | J92: =SUMIF('Pricing details'!$H$12:$H$121,$D92:$D95,'Pricing details'!AP$12:AP$121) -> 0 | K92: =SUMIF('Pricing details'!$H$12:$H$121,$D92:$D95,'Pricing details'!AQ$12:AQ$121) -> 0 | L92: =SUMIF('Pricing details'!$H$12:$H$121,$D92:$D95,'Pricing details'!AR$12:AR$121) -> 0 | M92: =SUM(G92:L92) -> 0 | O92: =M92/(1-E92) -> 0 | R92: Capital | S92: =CONCATENATE(P92,R92) -> Capital | T92: 0.1 | V92: =SUMIF('Pricing details'!$H$12:$H$121,$D92:$D94,'Pricing details'!AU$12:AU$121) -> 0 | W92: =SUMIF('Pricing details'!$H$12:$H$121,$D92:$D94,'Pricing details'!AV$12:AV$121) -> 0 | X92: =SUMIF('Pricing details'!$H$12:$H$121,$D92:$D94,'Pricing details'!AW$12:AW$121) -> 0 | Y92: =SUMIF('Pricing details'!$H$12:$H$121,$D92:$D94,'Pricing details'!AX$12:AX$121) -> 0 | Z92: =SUM(V92:Y92) -> 0 | AB92: =Z92/(1-T92) -> 0
G93: =SUM(G90:G92) -> 73125 | H93: =SUM(H90:H92) -> 1 | I93: =SUM(I90:I92) -> 0 | J93: =SUM(J90:J92) -> 0 | K93: =SUM(K90:K92) -> 0 | L93: =SUM(L90:L92) -> 0 | M93: =SUM(M90:M92) -> 73126 | O93: =SUM(O90:O92) -> 81251.111 | P93: =O93-M93 -> 8125.1111 | V93: =SUM(V90:V92) -> 0 | W93: =SUM(W90:W92) -> 0 | X93: =SUM(X90:X92) -> 0 | Y93: =SUM(Y90:Y92) -> 0 | Z93: =SUM(Z90:Z92) -> 0 | AB93: =Z93/(1-T93) -> 0
A95: 2 | B95: =B57 -> Design, Development, and Implementation Bid Solicitation Section 3.38, 3.39.1 | C95: Labor | D95: =CONCATENATE(A95,C95) -> 2Labor | E95: 0.1 | G95: =SUMIF('Pricing details'!$H$12:$H$121,$D95:$D97,'Pricing details'!AM$12:AM$121) -> 291418.27 | H95: =SUMIF('Pricing details'!$H$12:$H$121,$D95:$D97,'Pricing details'!AN$12:AN$121) -> 0 | I95: =SUMIF('Pricing details'!$H$12:$H$121,$D95:$D97,'Pricing details'!AO$12:AO$121) -> 0 | J95: =SUMIF('Pricing details'!$H$12:$H$121,$D95:$D97,'Pricing details'!AP$12:AP$121) -> 0 | K95: =SUMIF('Pricing details'!$H$12:$H$121,$D95:$D97,'Pricing details'!AQ$12:AQ$121) -> 0 | L95: =SUMIF('Pricing details'!$H$12:$H$121,$D95:$D97,'Pricing details'!AR$12:AR$121) -> 0 | M95: =SUM(G95:L95) -> 291418.27 | O95: =M95/(1-E95) -> 323798.08 | R95: Labor | S95: =CONCATENATE(P95,R95) -> Labor | T95: 0.1 | V95: =SUMIF('Pricing details'!$H$12:$H$121,$D95:$D97,'Pricing details'!AU$12:AU$121) -> 0 | W95: =SUMIF('Pricing details'!$H$12:$H$121,$D95:$D97,'Pricing details'!AV$12:AV$121) -> 0 | X95: =SUMIF('Pricing details'!$H$12:$H$121,$D95:$D97,'Pricing details'!AW$12:AW$121) -> 0 | Y95: =SUMIF('Pricing details'!$H$12:$H$121,$D95:$D97,'Pricing details'!AX$12:AX$121) -> 0 | Z95: =SUMIF('Pricing details'!$H$12:$H$121,$D95:$D97,'Pricing details'!AY$12:AY$121) -> 0 | AB95: =Z95/(1-T95) -> 0
A96: 2 | C96: ODCS | D96: =CONCATENATE(A96,C96) -> 2ODCS | E96: 0.1 | G96: =SUMIF('Pricing details'!$H$12:$H$121,$D96:$D98,'Pricing details'!AM$12:AM$121) -> 0 | H96: =SUMIF('Pricing details'!$H$12:$H$121,$D96:$D98,'Pricing details'!AN$12:AN$121) -> 0 | I96: =SUMIF('Pricing details'!$H$12:$H$121,$D96:$D98,'Pricing details'!AO$12:AO$121) -> 0 | J96: =SUMIF('Pricing details'!$H$12:$H$121,$D96:$D98,'Pricing details'!AP$12:AP$121) -> 0 | K96: =SUMIF('Pricing details'!$H$12:$H$121,$D96:$D98,'Pricing details'!AQ$12:AQ$121) -> 0 | L96: =SUMIF('Pricing details'!$H$12:$H$121,$D96:$D98,'Pricing details'!AR$12:AR$121) -> 0 | M96: =SUM(G96:L96) -> 0 | O96: =M96/(1-E96) -> 0 | R96: ODCS | S96: =CONCATENATE(P96,R96) -> ODCS | T96: 0.1 | V96: =SUMIF('Pricing details'!$H$12:$H$121,$D96:$D98,'Pricing details'!AU$12:AU$121) -> 0 | W96: =SUMIF('Pricing details'!$H$12:$H$121,$D96:$D98,'Pricing details'!AV$12:AV$121) -> 0 | X96: =SUMIF('Pricing details'!$H$12:$H$121,$D96:$D98,'Pricing details'!AW$12:AW$121) -> 0 | Y96: =SUMIF('Pricing details'!$H$12:$H$121,$D96:$D98,'Pricing details'!AX$12:AX$121) -> 0 | Z96: =SUMIF('Pricing details'!$H$12:$H$121,$D96:$D98,'Pricing details'!AY$12:AY$121) -> 0 | AB96: =Z96/(1-T96) -> 0
A97: 2 | C97: Capital | D97: =CONCATENATE(A97,C97) -> 2Capital | E97: 0.1 | G97: =SUMIF('Pricing details'!$H$12:$H$121,$D97:$D101,'Pricing details'!AM$12:AM$121) -> 0 | H97: =SUMIF('Pricing details'!$H$12:$H$121,$D97:$D101,'Pricing details'!AN$12:AN$121) -> 0 | I97: =SUMIF('Pricing details'!$H$12:$H$121,$D97:$D101,'Pricing details'!AO$12:AO$121) -> 0 | J97: =SUMIF('Pricing details'!$H$12:$H$121,$D97:$D101,'Pricing details'!AP$12:AP$121) -> 0 | K97: =SUMIF('Pricing details'!$H$12:$H$121,$D97:$D101,'Pricing details'!AQ$12:AQ$121) -> 0 | L97: =SUMIF('Pricing details'!$H$12:$H$121,$D97:$D101,'Pricing details'!AR$12:AR$121) -> 0 | M97: =SUM(G97:L97) -> 0 | O97: =M97/(1-E97) -> 0 | R97: Capital | S97: =CONCATENATE(P97,R97) -> Capital | T97: 0.1 | V97: =SUMIF('Pricing details'!$H$12:$H$121,$D97:$D99,'Pricing details'!AU$12:AU$121) -> 0 | W97: =SUMIF('Pricing details'!$H$12:$H$121,$D97:$D99,'Pricing details'!AV$12:AV$121) -> 0 | X97: =SUMIF('Pricing details'!$H$12:$H$121,$D97:$D99,'Pricing details'!AW$12:AW$121) -> 0 | Y97: =SUMIF('Pricing details'!$H$12:$H$121,$D97:$D99,'Pricing details'!AX$12:AX$121) -> 0 | Z97: =SUMIF('Pricing details'!$H$12:$H$121,$D97:$D99,'Pricing details'!AY$12:AY$121) -> 0 | AB97: =Z97/(1-T97) -> 0
G98: =SUM(G95:G97) -> 291418.27 | H98: =SUM(H95:H97) -> 0 | I98: =SUM(I95:I97) -> 0 | J98: =SUM(J95:J97) -> 0 | K98: =SUM(K95:K97) -> 0 | L98: =SUM(L95:L97) -> 0 | M98: =SUM(G98:L98) -> 291418.27 | O98: =SUM(O95:O97) -> 323798.08 | P98: =O98-M98 -> 32379.808 | V98: =SUM(V95:V97) -> 0 | W98: =SUM(W95:W97) -> 0 | X98: =SUM(X95:X97) -> 0 | Y98: =SUM(Y95:Y97) -> 0 | Z98: =SUM(Z95:Z97) -> 0 | AB98: =Z98/(1-T98) -> 0
A101: 3 | B101: =B60 -> PIF desktop | C101: Labor | D101: =CONCATENATE(A101,C101) -> 3Labor | E101: 0.1 | G101: =SUMIF('Pricing details'!$H$12:$H$121,$D101:$D103,'Pricing details'!AM$12:AM$121) -> 0 | H101: =SUMIF('Pricing details'!$H$12:$H$121,$D101:$D103,'Pricing details'!AN$12:AN$121) -> 0 | I101: =SUMIF('Pricing details'!$H$12:$H$121,$D101:$D103,'Pricing details'!AO$12:AO$121) -> 0 | J101: =SUMIF('Pricing details'!$H$12:$H$121,$D101:$D103,'Pricing details'!AP$12:AP$121) -> 0 | K101: =SUMIF('Pricing details'!$H$12:$H$121,$D101:$D103,'Pricing details'!AQ$12:AQ$121) -> 0 | L101: =SUMIF('Pricing details'!$H$12:$H$121,$D101:$D103,'Pricing details'!AR$12:AR$121) -> 0 | M101: =SUM(G101:L101) -> 0 | O101: =M101/(1-E101) -> 0 | R101: Labor | S101: =CONCATENATE(P101,R101) -> Labor | T101: 0.1
A102: 3 | C102: ODCS | D102: =CONCATENATE(A102,C102) -> 3ODCS | E102: 0.1 | G102: =SUMIF('Pricing details'!$H$12:$H$121,$D102:$D104,'Pricing details'!AM$12:AM$121) -> 0 | H102: =SUMIF('Pricing details'!$H$12:$H$121,$D102:$D104,'Pricing details'!AN$12:AN$121) -> 0 | I102: =SUMIF('Pricing details'!$H$12:$H$121,$D102:$D104,'Pricing details'!AO$12:AO$121) -> 0 | J102: =SUMIF('Pricing details'!$H$12:$H$121,$D102:$D104,'Pricing details'!AP$12:AP$121) -> 0 | K102: =SUMIF('Pricing details'!$H$12:$H$121,$D102:$D104,'Pricing details'!AQ$12:AQ$121) -> 0 | L102: =SUMIF('Pricing details'!$H$12:$H$121,$D102:$D104,'Pricing details'!AR$12:AR$121) -> 0 | M102: =SUM(G102:L102) -> 0 | O102: =M102/(1-E102) -> 0 | R102: ODCS | S102: =CONCATENATE(P102,R102) -> ODCS | T102: 0.1
A103: 3 | C103: Capital | D103: =CONCATENATE(A103,C103) -> 3Capital | E103: 0.25 | G103: =SUMIF('Pricing details'!$H$12:$H$121,$D103:$D105,'Pricing details'!AM$12:AM$121) -> 2042500 | H103: =SUMIF('Pricing details'!$H$12:$H$121,$D103:$D105,'Pricing details'!AN$12:AN$121) -> 0 | I103: =SUMIF('Pricing details'!$H$12:$H$121,$D103:$D105,'Pricing details'!AO$12:AO$121) -> 0 | J103: =SUMIF('Pricing details'!$H$12:$H$121,$D103:$D105,'Pricing details'!AP$12:AP$121) -> 0 | K103: =SUMIF('Pricing details'!$H$12:$H$121,$D103:$D105,'Pricing details'!AQ$12:AQ$121) -> 0 | L103: =SUMIF('Pricing details'!$H$12:$H$121,$D103:$D105,'Pricing details'!AR$12:AR$121) -> 0 | M103: =SUM(G103:L103) -> 2042500 | O103: =M103/(1-E103) -> 2723333.3 | P103: =O103-M103 -> 680833.33 | R103: Capital | S103: =CONCATENATE(P103,R103) -> 680833.333333333Capital | T103: 0.25
G104: =SUM(G101:G103) -> 2042500 | H104: =SUM(H101:H103) -> 0 | I104: =SUM(I101:I103) -> 0 | J104: =SUM(J101:J103) -> 0 | K104: =SUM(K101:K103) -> 0 | L104: =SUM(L101:L103) -> 0 | M104: =SUM(G104:L104) -> 2042500 | O104: =O103/1250 -> 2178.6667
O105: with profit
A106: 5 | B106: Inspection transaction fee for PIFs and PFFs (days 91 - 365, maintenance only)Bid Solicitation Section 3.1.3 & 3.27 | C106: Labor | D106: =CONCATENATE(6,C106) -> 6Labor | E106: 0.1 | G106: =SUMIF('Pricing details'!$H$12:$H$121,$D106:$D108,'Pricing details'!AM$12:AM$121) -> 0 | M106: =SUM(G106:L106) -> 0 | O106: =M106/(1-E106) -> 0 | R106: Labor | S106: =CONCATENATE(6,R106) -> 6Labor | T106: 0.1
A107: 5 | C107: ODCS | D107: =CONCATENATE(6,C107) -> 6ODCS | E107: 0.1 | G107: =SUMIF('Pricing details'!$H$12:$H$121,$D107:$D114,'Pricing details'!AM$12:AM$121) -> 0 | M107: =SUM(G107:L107) -> 0 | O107: =M107/(1-E107) -> 0 | R107: ODCS | S107: =CONCATENATE(6,R107) -> 6ODCS | T107: 0.1
A108: 5 | C108: Capital | D108: =CONCATENATE(6,C108) -> 6Capital | E108: 0.25 | G108: =SUMIF('Pricing details'!$H$12:$H$121,$D108:$D115,'Pricing details'!AM$12:AM$121) -> 0 | M108: =SUM(G108:L108) -> 0 | O108: =M108/(1-E108) -> 0 | R108: Capital | S108: =CONCATENATE(6,R108) -> 6Capital | T108: 0.25
G109: =SUM(G106:G108) -> 0 | H109: =SUM(H106:H108) -> 0 | I109: =SUM(I106:I108) -> 0 | J109: =SUM(J106:J108) -> 0 | K109: =SUM(K106:K108) -> 0 | L109: =SUM(L106:L108) -> 0 | M109: =SUM(G109:L109) -> 0
N110: add vidfee
P111: =O111-M109 -> 0
N112: test Fee==>
A114: 6 | B114: =B69 -> Inspection transaction fee for PIFs and PFFs (including NGVID & all maintenance) Bid Solicitation Section 3.1.2 | C114: Labor | D114: =CONCATENATE(A114,C114) -> 6Labor | E114: 0.1 | G114: =SUMIF('Pricing details'!$H$12:$H$121,$D114:$D116,'Pricing details'!AM$12:AM$121) -> 0 | H114: =SUMIF('Pricing details'!$H$12:$H$121,$D114:$D116,'Pricing details'!AN$12:AN$121) -> 0 | I114: =SUMIF('Pricing details'!$H$12:$H$121,$D114:$D116,'Pricing details'!AO$12:AO$121) -> 0 | J114: =SUMIF('Pricing details'!$H$12:$H$121,$D114:$D116,'Pricing details'!AP$12:AP$121) -> 0 | K114: =SUMIF('Pricing details'!$H$12:$H$121,$D114:$D116,'Pricing details'!AQ$12:AQ$121) -> 0 | L114: =SUMIF('Pricing details'!$H$12:$H$121,$D114:$D116,'Pricing details'!AR$12:AR$121) -> 0 | M114: =SUM(G114:L114) -> 0 | O114: =M114/(1-E114) -> 0 | R114: Labor | S114: =CONCATENATE(P114,R114) -> Labor | T114: 0.1 | V114: =SUMIF('Pricing details'!$H$12:$H$121,$D114:$D116,'Pricing details'!AU$12:AU$121) -> 0 | W114: =SUMIF('Pricing details'!$H$12:$H$121,$D114:$D116,'Pricing details'!AV$12:AV$121) -> 0 | X114: =SUMIF('Pricing details'!$H$12:$H$121,$D114:$D116,'Pricing details'!AW$12:AW$121) -> 0 | Y114: =SUMIF('Pricing details'!$H$12:$H$121,$D114:$D116,'Pricing details'!AX$12:AX$121) -> 0 | Z114: =SUMIF('Pricing details'!$H$12:$H$121,$D114:$D116,'Pricing details'!AY$12:AY$121) -> 0 | AB114: =Z114/(1-T114) -> 0
A115: 6 | C115: ODCS | D115: =CONCATENATE(A115,C115) -> 6ODCS | E115: 0.1 | G115: =SUMIF('Pricing details'!$H$12:$H$121,$D115:$D117,'Pricing details'!AM$12:AM$121) -> 0 | H115: =SUMIF('Pricing details'!$H$12:$H$121,$D115:$D117,'Pricing details'!AN$12:AN$121) -> 62500 | I115: =SUMIF('Pricing details'!$H$12:$H$121,$D115:$D117,'Pricing details'!AO$12:AO$121) -> 62500 | J115: =SUMIF('Pricing details'!$H$12:$H$121,$D115:$D117,'Pricing details'!AP$12:AP$121) -> 62500 | K115: =SUMIF('Pricing details'!$H$12:$H$121,$D115:$D117,'Pricing details'!AQ$12:AQ$121) -> 62500 | L115: =SUMIF('Pricing details'!$H$12:$H$121,$D115:$D117,'Pricing details'!AR$12:AR$121) -> 62500 | M115: =SUM(G115:L115) -> 312500 | O115: =M115/(1-E115) -> 347222.22 | R115: ODCS | S115: =CONCATENATE(P115,R115) -> ODCS | T115: 0.1 | V115: =SUMIF('Pricing details'!$H$12:$H$121,$D115:$D117,'Pricing details'!AU$12:AU$121) -> 62500 | W115: =SUMIF('Pricing details'!$H$12:$H$121,$D115:$D117,'Pricing details'!AV$12:AV$121) -> 62500 | X115: =SUMIF('Pricing details'!$H$12:$H$121,$D115:$D117,'Pricing details'!AW$12:AW$121) -> 62500 | Y115: =SUMIF('Pricing details'!$H$12:$H$121,$D115:$D117,'Pricing details'!AX$12:AX$121) -> 62500 | Z115: =SUMIF('Pricing details'!$H$12:$H$121,$D115:$D117,'Pricing details'!AY$12:AY$121) -> 250000 | AB115: =Z115/(1-T115) -> 277777.78
A116: 6 | C116: Capital | D116: =CONCATENATE(A116,C116) -> 6Capital | E116: 0.25 | G116: =SUMIF('Pricing details'!$H$12:$H$121,$D116:$D119,'Pricing details'!AM$12:AM$121) -> 0 | H116: =SUMIF('Pricing details'!$H$12:$H$121,$D116:$D119,'Pricing details'!AN$12:AN$121) -> 72125 | I116: =SUMIF('Pricing details'!$H$12:$H$121,$D116:$D119,'Pricing details'!AO$12:AO$121) -> 72125 | J116: =SUMIF('Pricing details'!$H$12:$H$121,$D116:$D119,'Pricing details'!AP$12:AP$121) -> 72125 | K116: =SUMIF('Pricing details'!$H$12:$H$121,$D116:$D119,'Pricing details'!AQ$12:AQ$121) -> 72125 | L116: =SUMIF('Pricing details'!$H$12:$H$121,$D116:$D119,'Pricing details'!AR$12:AR$121) -> 72125 | M116: =SUM(G116:L116) -> 360625 | O116: =M116/(1-E116) -> 480833.33 | R116: Capital | S116: =CONCATENATE(P116,R116) -> Capital | T116: 0.35 | V116: =SUMIF('Pricing details'!$H$12:$H$121,$D116:$D119,'Pricing details'!AU$12:AU$121) -> 102125 | W116: =SUMIF('Pricing details'!$H$12:$H$121,$D116:$D119,'Pricing details'!AV$12:AV$121) -> 102125 | X116: =SUMIF('Pricing details'!$H$12:$H$121,$D116:$D119,'Pricing details'!AW$12:AW$121) -> 102125 | Y116: =SUMIF('Pricing details'!$H$12:$H$121,$D116:$D119,'Pricing details'!AX$12:AX$121) -> 102125 | Z116: =SUMIF('Pricing details'!$H$12:$H$121,$D116:$D119,'Pricing details'!AY$12:AY$121) -> 408500 | AB116: =Z116/(1-T116) -> 628461.54
G117: =SUM(G114:G116) -> 0 | H117: =SUM(H114:H116) -> 134625 | I117: =SUM(I114:I116) -> 134625 | J117: =SUM(J114:J116) -> 134625 | K117: =SUM(K114:K116) -> 134625 | L117: =SUM(L114:L116) -> 134625 | M117: =SUM(M114:M116) -> 673125 | O117: =SUM(O114:O116) -> 828055.56 | V117: =SUM(V114:V116) -> 164625 | W117: =SUM(W114:W116) -> 164625 | X117: =SUM(X114:X116) -> 164625 | Y117: =SUM(Y114:Y116) -> 164625 | Z117: =SUM(Z114:Z116) -> 658500 | AB117: =SUM(AB114:AB116) -> 906239.32
F119: total revenue | G119: =P164 -> 814810 | H119: =$P$165 -> 1282500 | I119: =$P$165 -> 1282500 | J119: =$P$165 -> 1282500 | K119: =$P$165 -> 1282500 | L119: =$P$165 -> 1282500 | M119: =SUM(G119:L119) -> 7227310 | N119: add vidfee | O119: 750000 | P119: =M119-M117 -> 6554185 | U119: total revenue | V119: =$P$165 -> 1282500 | W119: =$P$165 -> 1282500 | X119: =$P$165 -> 1282500 | Y119: =$P$165 -> 1282500 | Z119: =SUM(V119:Y119) -> 5130000 | AA119: add vidfee | AB119: =750000*0.8 -> 600000
F120: test fee | G120: =G119/Assumpt!D65 -> 3.9746829 | H120: =H119/Assumpt!E65 -> 5.0294118 | I120: =I119/Assumpt!F65 -> 5.0294118 | J120: =J119/Assumpt!G65 -> 5.0294118 | K120: =K119/Assumpt!H65 -> 5.0294118 | L120: =L119/Assumpt!I65 -> 5.0294118 | O120: =O117+O119 -> 1578055.6 | U120: testfee | V120: =$O$165 -> 5.0294118 | W120: =$O$165 -> 5.0294118 | X120: =$O$165 -> 5.0294118 | Y120: =$O$165 -> 5.0294118 | AB120: =AB117+AB119 -> 1506239.3 | AC120: =Z119-Z117 -> 4471500
M121: =SUM(G121:L121) -> 0 | N121: test Fee==> | O121: =(O117+O119)/(SUM(Assumpt!D65:I65)) -> 1.0662538 | AA121: test Fee==> | AB121: =AB120/SUM(U69:Y69) -> 1.4767052
M122: =M119-M117 -> 6554185 | Z122: =Z119-Z117 -> 4471500
A125: 9 | B125: =B76 -> CIF Retrofit | C125: Labor | D125: =CONCATENATE(A125,C125) -> 9Labor | E125: 0.1 | G125: =SUMIF('Pricing details'!$H$12:$H$121,$D125:$D127,'Pricing details'!AM$12:AM$121) -> 0 | H125: =SUMIF('Pricing details'!$H$12:$H$121,$D125:$D127,'Pricing details'!AN$12:AN$121) -> 0 | I125: =SUMIF('Pricing details'!$H$12:$H$121,$D125:$D127,'Pricing details'!AO$12:AO$121) -> 0 | J125: =SUMIF('Pricing details'!$H$12:$H$121,$D125:$D127,'Pricing details'!AP$12:AP$121) -> 0 | K125: =SUMIF('Pricing details'!$H$12:$H$121,$D125:$D127,'Pricing details'!AQ$12:AQ$121) -> 0 | L125: =SUMIF('Pricing details'!$H$12:$H$121,$D125:$D127,'Pricing details'!AR$12:AR$121) -> 0 | M125: =SUM(G125:L125) -> 0 | O125: =M125/(1-E125) -> 0 | R125: Labor | S125: =CONCATENATE(P125,R125) -> Labor | T125: 0.1
A126: 9 | C126: ODCS | D126: =CONCATENATE(A126,C126) -> 9ODCS | E126: 0.1 | G126: =SUMIF('Pricing details'!$H$12:$H$121,$D126:$D128,'Pricing details'!AM$12:AM$121) -> 170000 | H126: =SUMIF('Pricing details'!$H$12:$H$121,$D126:$D128,'Pricing details'!AN$12:AN$121) -> 0 | I126: =SUMIF('Pricing details'!$H$12:$H$121,$D126:$D128,'Pricing details'!AO$12:AO$121) -> 0 | J126: =SUMIF('Pricing details'!$H$12:$H$121,$D126:$D128,'Pricing details'!AP$12:AP$121) -> 0 | K126: =SUMIF('Pricing details'!$H$12:$H$121,$D126:$D128,'Pricing details'!AQ$12:AQ$121) -> 0 | L126: =SUMIF('Pricing details'!$H$12:$H$121,$D126:$D128,'Pricing details'!AR$12:AR$121) -> 0 | M126: =SUM(G126:L126) -> 170000 | O126: =M126/(1-E126) -> 188888.89 | R126: ODCS | S126: =CONCATENATE(P126,R126) -> ODCS | T126: 0.1
A127: 9 | C127: Capital | D127: =CONCATENATE(A127,C127) -> 9Capital | E127: 0.1 | G127: =SUMIF('Pricing details'!$H$12:$H$121,$D127:$D138,'Pricing details'!AM$12:AM$121) -> 1130486.9 | H127: =SUMIF('Pricing details'!$H$12:$H$121,$D127:$D138,'Pricing details'!AN$12:AN$121) -> 0 | I127: =SUMIF('Pricing details'!$H$12:$H$121,$D127:$D138,'Pricing details'!AO$12:AO$121) -> 0 | J127: =SUMIF('Pricing details'!$H$12:$H$121,$D127:$D138,'Pricing details'!AP$12:AP$121) -> 0 | K127: =SUMIF('Pricing details'!$H$12:$H$121,$D127:$D138,'Pricing details'!AQ$12:AQ$121) -> 0 | L127: =SUMIF('Pricing details'!$H$12:$H$121,$D127:$D138,'Pricing details'!AR$12:AR$121) -> 0 | M127: =SUM(G127:L127) -> 1130486.9 | O127: =M127/(1-E127) -> 1256096.6 | R127: Capital | S127: =CONCATENATE(P127,R127) -> Capital | T127: 0.1
...

Sheet price submittal form
A1: State-Supplied Price Sheet Bid Solicitation # 20DPP00471 T1628 - Enhanced Motor Vehicle Inspection Maintenance System
A2: Vendor {Bidder} Name:
A3: Instructions: | E3: Refer to Bid Solicitation Section 4.4.5 for Vendor {Bidder} instruction. The Vendor {Bidder} shall provide pricing for all of the yellow highlighted cells including the optional extension cells.
A4: Description/Service | C4: Estimated Volume Per Year | D4: Unit of Measurement | E4: Year 1 All-Inclusive Price | F4: Year 2 All-Inclusive Price | G4: Year 3 All-Inclusive Price | H4: Year 4 All-Inclusive Price | I4: Year 5 All-Inclusive Price | J4: Year 6 All-Inclusive Price | K4: Total Cost | L4: Year 7 All-Inclusive Price (Optional Extension - See Section 5.2) | M4: Year 8 All-Inclusive Price (Optional Extension - See Section 5.2) | N4: Year 9 All-Inclusive Price (Optional Extension - See Section 5.2) | O4: Year 10 All-Inclusive Price (Optional Extension - See Section 5.2)
A5: VID DEVELOPMENT - NEXT GENERATION VEHICLE INSPECTION SYSTEM | T5: Cross check
A6: 1 | B6: All NGVID Required Documents Bid Solicitation Section 3.51, 3.52 | C6: 1 | D6: TASK | K6: ='cash flow'!O93 -> 81251.111 | T6: ='cash flow'!M54 -> 81251.111 | U6: =K6-T6 -> 0
A7: 2 | B7: Design, Development, and Implementation Bid Solicitation Section 3.38, 3.39.1 | C7: 1 | D7: TASK | K7: ='cash flow'!O98 -> 323798.08 | T7: ='cash flow'!M57 -> 323798.08 | U7: =K7-T7 -> 0
A8: PIFs AND PFFs
A9: 3 | B9: NGWorkstation price to PIFs and PFFs (PC based - PC, monitor, barcode reader, printer, scan tool, keyboard, mouse) Bid Solicitation Section 3.26, 3.27, 3.28 | C9: 1250 | D9: EACH | F9: ='cash flow'!O104 -> 2178.6667 | K9: =SUM(F9:J9)*C9 -> 2723333.3 | T9: ='cash flow'!M61 -> 2723333.3 | U9: =K9-T9 -> 0
A10: 4 | B10: NGWorkstation price to PIFs and PFFs (Tablet based - Tablet, printer, scan tool) Bid Solicitation Section 3.26, 3.27, 3.28 | C10: 1250 | D10: EACH | F10: 0 | K10: =SUM(F10:J10)*C10 -> 0
A11: 5 | B11: Inspection transaction fee for PIFs and PFFs (days 91 - 365, maintenance only) Bid Solicitation Section 3.1.3 & 3.27 | C11: 205000 | D11: EACH | E11: ='cash flow'!G120 -> 3.9746829 | K11: =SUM(E11)*C11 -> 814810 | T11: ='cash flow'!G72 -> 814810 | U11: =K11-T11 -> 0
A12: 6 | B12: Inspection transaction fee for PIFs and PFFs (including NGVID & all maintenance) Bid Solicitation Section 3.1.2 | C12: 255000 | D12: EACH | F12: ='cash flow'!$H$120 -> 5.0294118 | G12: =F12 -> 5.0294118 | H12: =G12 -> 5.0294118 | I12: =H12 -> 5.0294118 | J12: =I12 -> 5.0294118 | K12: =SUM(F12:J12)*C12 -> 6412500 | L12: =J12 -> 5.0294118 | M12: =L12 -> 5.0294118 | N12: =L12 -> 5.0294118 | O12: =M12 -> 5.0294118 | T12: =SUM('cash flow'!H72:L72) -> 6412500 | U12: =K12-T12 -> 0
A13: 7 | B13: NGWorkstation price to PIFs and PFFs (Laptop based - Laptop, printer, barcode reader, scan tool) Bid Solicitation Section 3.26, 3.27, 3.28 | C13: 1250 | D13: EACH | K13: =SUM(F13:J13)*C13 -> 0
A14: CIFS - STARTUP, RETROFIT, IMPROVEMENT, AND PER INSPECTION COST
A15: 8 | B15: Training State Staff on NGSystem (Price Per Employee) Bid Solicitation Section 3.48 | C15: 150 | D15: EACH | E15: 0 | F15: 0 | G15: 0 | H15: 0 | I15: 0 | J15: 0 | L15: 0 | M15: 0 | N15: 0 | O15: 0
A16: 9 | B16: CIF Retrofit - Removal of old equipment, installation of new equipment (NGWorkstations), facility acceptance testing. Bid Solicitation Section 3.13.5 | C16: 125 | D16: EACH | E16: ='cash flow'!O129 -> 11559.884 | F16: 0 | G16: 0 | H16: 0 | I16: 0 | J16: 0 | K16: =SUM(E16:J16)*C16 -> 1444985.5 | L16: 0 | M16: 0 | N16: 0 | O16: 0 | T16: ='cash flow'!M76 -> 1444985.5 | U16: =K16-T16 -> 0
A17: 10 | B17: Cost per inspection at CIFs. Includes all CIF operational costs (days 91 - 365 [excluding the Legacy VID transaction cost]) - Inclusive of all State operational costs Bid Solicitation Section 3.1.3, 3.2.1 | C17: 1425000 | D17: EACH | E17: ='cash flow'!G85 -> 15.477128 | K17: =SUM(E17)*C17 -> 22054908 | T17: ='cash flow'!G86 -> 22054908 | U17: =K17-T17 -> 0
A18: 11 | B18: Cost per inspection at CIFs (Includes all CIF operational costs.) - Inclusive of all State operational costs Bid Solicitation Section 3.1.2 | C18: 1900000 | D18: EACH | F18: ='cash flow'!H85 -> 15.225892 | G18: ='cash flow'!I148 -> 15.110079 | H18: ='cash flow'!J148 -> 15.295302 | I18: ='cash flow'!K148 -> 15.504838 | J18: ='cash flow'!L148 -> 15.590186 | K18: =SUM(F18:J18)*C18 -> 1.4577996e+08 | L18: ='cash flow'!V85 -> 15.937765 | M18: ='cash flow'!W85 -> 15.781067 | N18: ='cash flow'!X85 -> 15.869001 | O18: ='cash flow'!Y85 -> 16.15998 | T18: =SUM('cash flow'!H86:L86) -> 1.4577996e+08 | U18: =K18-T18 -> 0
A19: Total Cost | K19: =SUM(K6:K18) -> 1.7963555e+08 | R19: Totaal cost of prgram without PIF/PFF | S19: =K6 -> 81251.111 | T19: =SUM(T6:T18) -> 1.7963555e+08 | U19: =K19-T19 -> 0
A20: MISCELLANEOUS HOURLY RATES PURSUANT TO SECTIONS 3.13.2.2, 3.14.1, 3.47 and 5.16 - review sections here and in cells below | R20: Total cost from P&L
A21: 12 | B21: Additional Work Bid Solicitation Section 3.13.2.2 | C21: 1 | D21: HOUR | R21: delta | S21: =S19-S20 -> 81251.111
A22: 13 | B22: Project Manager Bid Solicitation Section 3.14.1 | C22: 1 | D22: HOUR | E22: 121.524 | F22: 122.73924 | G22: 123.96664 | H22: 125.2063 | I22: 126.45836 | J22: 127.72295 | L22: 129.00018 | M22: 130.29018 | N22: 131.59308 | O22: 132.90901
A23: 14 | B23: Business Analyst Bid Solicitation Section 3.14.1 | C23: 1 | D23: HOUR | E23: 81.541885 | F23: 82.357304 | G23: 83.180877 | H23: 84.012685 | I23: 84.852812 | J23: 85.70134 | L23: 86.558354 | M23: 87.423937 | N23: 88.298177 | O23: 89.181158
A24: 15 | B24: User Interface Designer Bid Solicitation Section 3.14.1 | C24: 1 | D24: HOUR | E24: 119.59476 | F24: 120.79071 | G24: 121.99862 | H24: 123.21861 | I24: 124.45079 | J24: 125.6953 | L24: 126.95225 | M24: 128.22177 | N24: 129.50399 | O24: 130.79903
A25: 16 | B25: Developer Bid Solicitation Section 3.14.1 | C25: 1 | D25: HOUR | E25: 89.152461 | F25: 90.043985 | G25: 90.944425 | H25: 91.853869 | I25: 92.772408 | J25: 93.700132 | L25: 94.637133 | M25: 95.583505 | N25: 96.53934 | O25: 97.504733
A26: 17 | B26: Database Administrator Bid Solicitation Section 3.14.1 | C26: 1 | D26: HOUR | E26: 108.72251 | F26: 109.80974 | G26: 110.90784 | H26: 112.01691 | I26: 113.13708 | J26: 114.26845 | L26: 115.41114 | M26: 116.56525 | N26: 117.7309 | O26: 118.90821
A27: 18 | B27: Security Design Lead Bid Solicitation Section 3.14.1 | C27: 1 | D27: HOUR | E27: 192.0275 | F27: 193.94778 | G27: 195.88725 | H27: 197.84613 | I27: 199.82459 | J27: 201.82283 | L27: 203.84106 | M27: 205.87947 | N27: 207.93827 | O27: 210.01765
A28: 19 | B28: Security Tester Bid Solicitation Section 3.14.1 | C28: 1 | D28: HOUR | E28: 192.02235 | F28: 193.94257 | G28: 195.882 | H28: 197.84082 | I28: 199.81923 | J28: 201.81742 | L28: 203.83559 | M28: 205.87395 | N28: 207.93269 | O28: 210.01201
A29: 20 | B29: Quality Assurance Manager Bid Solicitation Section 3.14.1 | C29: 1 | D29: HOUR | E29: 81.541885 | F29: 82.357304 | G29: 83.180877 | H29: 84.012685 | I29: 84.852812 | J29: 85.70134 | L29: 86.558354 | M29: 87.423937 | N29: 88.298177 | O29: 89.181158
A30: PIF/PFF REPLACEMENT EQUIPMENT
A31: 21 | B31: Monitor Bid Solicitation Section 3.26, 3.27, 3.28 | C31: 1 | D31: UNIT
A32: 22 | B32: Keyboard Bid Solicitation Section 3.26, 3.27, 3.28 | C32: 1 | D32: UNIT
A33: 23 | B33: Mouse Bid Solicitation Section 3.26, 3.27, 3.28 | C33: 1 | D33: UNIT
A34: 24 | B34: OBD Scan Tool Bid Solicitation Section 3.26, 3.27, 3.28 | C34: 1 | D34: UNIT
A35: 25 | B35: Bar Code Scanner Bid Solicitation Section 3.26, 3.27, 3.28 | C35: 1 | D35: UNIT
A36: 26 | B36: Printer Bid Solicitation Section 3.26, 3.27, 3.28 | C36: 1 | D36: UNIT
A37: 27 | B37: Tablet Bid Solicitation Section 3.26, 3.27, 3.28 | C37: 1 | D37: UNIT
A38: 28 | B38: Computer Bid Solicitation Section 3.26, 3.27, 3.28 | C38: 1 | D38: UNIT
A39: 29 | B39: Laptop Bid Solicitation Section 3.26, 3.27, 3.28 | C39: 1 | D39: UNIT
A40: 30 | B40: Other Bid Solicitation Section 3.26, 3.27, 3.28 | C40: 1 | D40: UNIT

Sheet Application Development
A1: rate | B1: =120000/2080 -> 57.692308 | E1: Requirements | F1: Implementation | G1: Hours | H1: check | J1: Notes
A2: Fringe | B2: 1.3 | C2: =100000/2080 -> 48.076923
A3: US exchange | B3: 0.75 | C3: =C2*0.8 -> 38.461538 | E3: 0.2 | F3: 0.8
A4: US $ | B4: =B1*B2*B3 -> 56.25 | C4: =B4/0.13 -> 432.69231
A5: Misc Applications | B5: =B4/1.3 -> 43.269231 | C5: Price line
A7: Billing Application | C7: 1 | D7: =$B$4*E7 -> 1687.5 | E7: =$E$3*G7 -> 30 | G7: 150 | H7: =$B$4*G7 -> 8437.5
C8: 2 | D8: =$B$4*F8 -> 6750 | F8: =$F$3*G7 -> 120
A10: Sticker Management (reporting) | C10: 1 | D10: =$B$4*E10 -> 1125 | E10: =$E$3*G10 -> 20 | G10: 100 | H10: =$B$4*G10 -> 5625
C11: 2 | D11: =$B$4*F11 -> 4500 | F11: =$F$3*G10 -> 80
A12: Public Websites
A13: School Bus Report Card | C13: 1 | D13: =$B$4*E13 -> 1125 | E13: =$E$3*G13 -> 20 | G13: 100 | H13: =$B$4*G13 -> 5625
C14: 2 | D14: =$B$4*F14 -> 4500 | F14: =$F$3*G13 -> 80
A16: VIR Reprint | C16: 1 | D16: =$B$4*E16 -> 1125 | E16: =$E$3*G16 -> 20 | G16: 100 | H16: =$B$4*G16 -> 5625
C17: 2 | D17: =$B$4*F17 -> 4500 | F17: =$F$3*G16 -> 80
A19: Wait Queue Cameras | C19: 1 | D19: =$B$4*E19 -> 1125 | E19: =$E$3*G19 -> 20 | G19: 100 | H19: =$B$4*G19 -> 5625
C20: 2 | D20: =$B$4*F20 -> 4500 | F20: =$F$3*G19 -> 80
A21: Administration Applications
A23: Facility Admin | C23: 1 | D23: =$B$4*E23 -> 1125 | E23: =$E$3*G23 -> 20 | G23: 100 | H23: =$B$4*G23 -> 5625
C24: 2 | D24: =$B$4*F24 -> 4500 | F24: =$F$3*G23 -> 80
A25: View Facility
A26: Manage Private Facility
A27: Update Facility
A28: Activate Facility
A29: Assign/Unassign Inspector
A30: Manage Centralized Facility
A31: Manage State Facility
A33: Inspector Admin | C33: 1 | D33: =$B$4*E33 -> 1125 | E33: =$E$3*G33 -> 20 | G33: 100 | H33: =$B$4*G33 -> 5625
C34: 2 | D34: =$B$4*F34 -> 4500 | F34: =$F$3*G33 -> 80
A35: View Auditor/Inspector | C35: 2
A36: Manage Inspector
A37: Manage Auditor
A38: Assign/Unassign PIF Inspector
A40: Vehicle Admin | C40: 1 | D40: =$B$4*E40 -> 1125 | E40: =$E$3*G40 -> 20 | G40: 100 | H40: =$B$4*G40 -> 5625
C41: 2 | D41: =$B$4*F41 -> 4500 | F41: =$F$3*G40 -> 80
A42: Manage Covert Vehicle
A43: Active Covert Vehicles
A44: Covert Vehicle History
A45: Manage Collector Vehicle
A47: Workstation Admin | C47: 1 | D47: =$B$4*E47 -> 1125 | E47: =$E$3*G47 -> 20 | G47: 100 | H47: =$B$4*G47 -> 5625
C48: 2 | D48: =$B$4*F48 -> 4500 | F48: =$F$3*G47 -> 80
A50: Message Admin | C50: 1 | D50: =$B$4*E50 -> 1125 | E50: =$E$3*G50 -> 20 | G50: 100 | H50: =$B$4*G50 -> 5625
C51: 2 | D51: =$B$4*F51 -> 4500 | F51: =$F$3*G50 -> 80
A52: View Messages
A53: Send Messages
A55: Data Correction | C55: 1 | D55: =$B$4*E55 -> 1125 | E55: =$E$3*G55 -> 20 | G55: 100 | H55: =$B$4*G55 -> 5625
C56: 2 | D56: =$B$4*F56 -> 4500 | F56: =$F$3*G55 -> 80
A57: Correct Inspection Data
A59: Repair Facility | C59: 1 | D59: =$B$4*E59 -> 1125 | E59: =$E$3*G59 -> 20 | G59: 100 | H59: =$B$4*G59 -> 5625
C60: 2 | D60: =$B$4*F60 -> 4500 | F60: =$F$3*G59 -> 80
A61: Manage Repair Data
A62: Enter Repair Data
A63: View Repair Data
A64: Delete Repair Data
A65: Manage Facility Manager
A66: Setup Facility Manager
A67: Update Facility Manager
A68: Manage Facility Technician
A69: Setup Technician
A70: Update Technician
A72: Reporting | C72: 1 | D72: =$B$4*E72 -> 8437.5 | E72: =$E$3*G72 -> 150 | G72: 750 | H72: =$B$4*G72 -> 42187.5
A73: Reporting | C73: 2 | D73: =$B$4*F73 -> 33750 | F73: =$F$3*G72 -> 600
C74: 2 | F74: =$F$3*G73 -> 0
A76: User Management | C76: 1 | D76: =$B$4*E76 -> 2812.5 | E76: =$E$3*G76 -> 50 | G76: 250 | H76: =$B$4*G76 -> 14062.5
C77: 2 | D77: =$B$4*F77 -> 11250 | F77: =$F$3*G76 -> 200
A78: User Setup | B78: 2
A79: Manage User
A81: SLTA | C81: 1 | D81: =$B$4*E81 -> 1125 | E81: =$E$3*G81 -> 20 | G81: 100 | H81: =$B$4*G81 -> 5625
C82: 2 | D82: =$B$4*F82 -> 4500 | F82: =$F$3*G81 -> 80
A84: Dashboard | C84: 1 | D84: =$B$4*E84 -> 2025 | E84: =$E$3*G84 -> 36 | G84: 180 | H84: =$B$4*G84 -> 10125
C85: 2 | D85: =$B$4*F85 -> 8100 | F85: =$F$3*G84 -> 144
A87: Audit data | C87: 1 | D87: =$B$4*E87 -> 3150 | E87: =$E$3*G87 -> 56 | G87: 280 | H87: =$B$4*G87 -> 15750
C88: 2 | D88: =$B$4*F88 -> 12600 | F88: =$F$3*G87 -> 224
A90: Triggers fraud detection | C90: 1 | D90: =$B$4*E90 -> 5850 | E90: =$E$3*G90 -> 104 | G90: 520 | H90: =$B$4*G90 -> 29250 | K90: 120 | L90: 400
C91: 2 | D91: =$B$4*F91 -> 23400 | F91: =$F$3*G90 -> 416
A93: Inspection data retrieval | C93: 1 | D93: =$B$4*E93 -> 1125 | E93: =$E$3*G93 -> 20 | G93: 100 | H93: =$B$4*G93 -> 5625
C94: 2 | D94: =$B$4*F94 -> 4500 | F94: =$F$3*G93 -> 80
A96: reference table Management | C96: 1 | D96: =$B$4*E96 -> 1125 | E96: =$E$3*G96 -> 20 | G96: 100 | H96: =$B$4*G96 -> 5625 | J96: Currently a manual process to apply, negotiate??
C97: 2 | D97: =$B$4*F97 -> 4500 | F97: =$F$3*G96 -> 80
A99: Document repository | C99: 1 | D99: =$B$4*E99 -> 1125 | E99: =$E$3*G99 -> 20 | G99: 100 | H99: =$B$4*G99 -> 5625 | J99: Darryl Knowledebase??
C100: 2 | D100: =$B$4*F100 -> 4500 | F100: =$F$3*G99 -> 80
A102: JIRA integration | C102: 1 | D102: =$B$4*E102 -> 2700 | E102: =$E$3*G102 -> 48 | G102: 240 | H102: =$B$4*G102 -> 13500
C103: 2 | D103: =$B$4*F103 -> 10800 | F103: =$F$3*G102 -> 192
A105: ATP workstations | C105: 1 | D105: =$B$4*E105 -> 0 | E105: =$E$3*G105 -> 0 | H105: =$B$4*G105 -> 0 | J105: Removed; leverage crossover resources (PA/Gus) | K105: 65 | L105: 8 | M105: =K105*L105 -> 520
C106: 2 | D106: =$B$4*F106 -> 0 | F106: =$F$3*G105 -> 0
A108: Capital maintenance and repairs | C108: 1 | D108: =$B$4*E108 -> 1125 | E108: =$E$3*G108 -> 20 | G108: 100 | H108: =$B$4*G108 -> 5625
C109: 2 | D109: =$B$4*F109 -> 4500 | F109: =$F$3*G108 -> 80
A111: Facilities Management | C111: 1 | D111: =$B$4*E111 -> 1125 | E111: =$E$3*G111 -> 20 | G111: 100 | H111: =$B$4*G111 -> 5625
C112: 2 | D112: =$B$4*F112 -> 4500 | F112: =$F$3*G111 -> 80
A114: Call center | C114: 1 | D114: =$B$4*E114 -> 1125 | E114: =$E$3*G114 -> 20 | G114: 100 | H114: =$B$4*G114 -> 5625
C115: 2 | D115: =$B$4*F115 -> 4500 | F115: =$F$3*G114 -> 80
A117: Appointment system | C117: 1 | D117: =$B$4*E117 -> 2250 | E117: =$E$3*G117 -> 40 | G117: 200 | H117: =$B$4*G117 -> 11250
C118: 2 | D118: =$B$4*F118 -> 9000 | F118: =$F$3*G117 -> 160
A120: 500 hours | C120: 0 | D120: =$B$4*E120 -> 0 | E120: =$E$3*G120 -> 0 | G120: 0 | H120: =$B$4*G120 -> 0 | J120: 500 hours per year, need to accumulate unused hours
C121: 0 | D121: =$B$4*F121 -> 0 | F121: =$F$3*G120 -> 0
A123: 2 sw upgrades first year | C123: 1 | D123: =$B$4*E123 -> 0 | E123: =$E$3*G123 -> 0 | H123: =$B$4*G123 -> 0 | J123: Removed, use ancillary VID extension contract
C124: 2 | D124: =$B$4*F124 -> 0 | F124: =$F$3*G123 -> 0
A126: mvc interfaces | C126: 1 | D126: =$B$4*E126 -> 1125 | E126: =$E$3*G126 -> 20 | G126: 100 | H126: =$B$4*G126 -> 5625 | J126: negotiate to 2 mintes vs 1
C127: 2 | D127: =$B$4*F127 -> 4500 | F127: =$F$3*G126 -> 80
A129: OIT interfaces | C129: 1 | D129: =$B$4*E129 -> 1125 | E129: =$E$3*G129 -> 20 | G129: 100 | H129: =$B$4*G129 -> 5625
C130: 2 | D130: =$B$4*F130 -> 4500 | F130: =$F$3*G129 -> 80
...

Sheet infrastructureold
B1: Item | D1: Description | E1: Vendor | F1: Cost Split | J1: One-Time | N1: Recurring (Annual)
A2: Pickup | B2: RFP BUDGET IT Infrastructure Cost Model | Q2: Assumptions/Notes: Prices is US Dollars Taxes not included Recurring costs start from first year, unless specified Assume hardware refresh at year 5, 50% of initial cost
A4: x | B4: Item | D4: Description | E4: Vendor | F4: PA | G4: NJ | H4: VT | I4: MASS | J4: One-Time | N4: Recurring (Annual) | R4: Year 0 | S4: Year 1 | T4: Year 2 | U4: Year 3 | V4: Year 4 | W4: Year 5 | X4: Refresh Year 5 | Y4: Year 6 | Z4: Year 7 | AA4: Year 8 | AB4: Year 9 | AC4: Total
A5: =IF(W5>0,"x","") -> x | B5: Hosting | D5: Additional cabinet | E5: Verizon | G5: 1 | J5: 1 | K5: 5000 | L5: =J5*K5 -> 5000 | N5: =J5 -> 1 | O5: =2656*12*N5 -> 31872 | P5: =O5*N5 -> 31872 | R5: =L5+P5 -> 36872 | S5: =P5 -> 31872 | T5: =S5 -> 31872 | U5: =T5 -> 31872 | V5: =U5 -> 31872 | W5: =V5 -> 31872 | X5: =IF(C5="R",L5,) -> 0 | Y5: =V5 -> 31872 | Z5: =W5 -> 31872 | AA5: =Z5 -> 31872 | AB5: =AA5 -> 31872 | AC5: =SUM(R5:AB5) -> 323720
A6: =IF(W6>0,"x","") | B6: Cables / Wiring / Cable Management | E6: TBD | G6: 1 | J6: 1 | K6: 2000 | L6: =J6*K6 -> 2000 | N6: 1 | P6: =O6*N6 -> 0 | R6: =L6+P6 -> 2000 | S6: =P6 -> 0 | T6: =S6 -> 0 | U6: =T6 -> 0 | V6: =U6 -> 0 | W6: =V6 -> 0 | X6: =IF(C6="R",L6,) -> 0 | Y6: =V6 -> 0 | Z6: =W6 -> 0 | AA6: =Z6 -> 0 | AB6: =AA6 -> 0 | AC6: =SUM(R6:AB6) -> 2000
A7: =IF(W7>0,"x","") -> x | B7: VMware vSphere(Virtualization Hardware) | C7: R | D7: 2 x Intel® Xeon® E5-2699 v3 18-core 2.3GHz core Intel CPU, 512GB RAM, PROD | E7: HP | G7: 1 | J7: 2 | K7: 24000 | L7: =J7*K7 -> 48000 | M7: Default discount applied | N7: =J7 -> 2 | O7: =21%*K7 -> 5040 | P7: =O7*N7 -> 10080 | Q7: First year support paid at the time of purchase. Assume 50% increase for the last 2 yrs | R7: =L7+P7 -> 58080 | S7: =P7 -> 10080 | T7: =S7 -> 10080 | U7: =T7 -> 10080 | V7: =U7 -> 10080 | W7: =V7 -> 10080 | X7: =IF(C7="R",L7,) -> 48000 | Y7: =V7 -> 10080 | Z7: =W7 -> 10080 | AA7: =Z7 -> 10080 | AB7: =AA7 -> 10080 | AC7: =SUM(R7:AB7) -> 196800
A8: =IF(W8>0,"x","") -> x | B8: DB/HSM Server Refresh | D8: Oracle, T7-1, single socket 32-core SPARC CPU. System virtualized with LDOM, DB PROD, HSM PROD, all two node clusters | E8: Oracle | G8: 0.5 | I8: 0.5 | J8: 2 | K8: 40000 | L8: =J8*K8 -> 80000 | M8: Default discount applied | N8: =J8 -> 2 | O8: =15%*K8 -> 6000 | P8: =O8*N8 -> 12000 | Q8: First year support paid at the time of purchase. Assume 50% increase for the last 2 yrs | R8: =L8+P8 -> 92000 | S8: =P8 -> 12000 | T8: =S8 -> 12000 | U8: =T8 -> 12000 | V8: =U8 -> 12000 | W8: =V8 -> 12000 | X8: =IF(C8="R",L8,) -> 0 | Y8: =V8 -> 12000 | Z8: =W8 -> 12000 | AA8: =Z8 -> 12000 | AB8: =AA8 -> 12000 | AC8: =SUM(R8:AB8) -> 200000
A9: =IF(W9>0,"x","") -> x | B9: vCentre | C9: R | D9: HP DL360 G9 | E9: HP | G9: 1 | J9: 1 | K9: 8000 | L9: =J9*K9 -> 8000 | M9: Default discount applied | N9: =J9 -> 1 | O9: =21%*K9 -> 1680 | P9: =O9*N9 -> 1680 | Q9: First year support paid at the time of purchase. Assume 50% increase for the last 2 yrs | R9: =L9+P9 -> 9680 | S9: =P9 -> 1680 | T9: =S9 -> 1680 | U9: =T9 -> 1680 | V9: =U9 -> 1680 | W9: =V9 -> 1680 | X9: =IF(C9="R",L9,) -> 8000 | Y9: =V9 -> 1680 | Z9: =W9 -> 1680 | AA9: =Z9 -> 1680 | AB9: =AA9 -> 1680 | AC9: =SUM(R9:AB9) -> 32800
A10: =IF(W10>0,"x","") | B10: Centralized Logging/Network monitor/HIDS (virtualized) | D10: HP DL360 G9 | E10: HP | G10: 1 | J10: 0 | K10: 8000 | L10: =J10*K10 -> 0 | M10: Default discount applied | N10: =J10 -> 0 | O10: =21%*K10 -> 1680 | P10: =O10*N10 -> 0 | Q10: First year support paid at the time of purchase. Assume 50% increase for the last 2 yrs | R10: =L10+P10 -> 0 | S10: =P10 -> 0 | T10: =S10 -> 0 | U10: =T10 -> 0 | V10: =U10 -> 0 | W10: =V10 -> 0 | X10: =IF(C10="R",L10,) -> 0 | Y10: =V10 -> 0 | Z10: =W10 -> 0 | AA10: =Z10 -> 0 | AB10: =AA10 -> 0 | AC10: =SUM(R10:AB10) -> 0
A11: =IF(W11>0,"x","") -> x | B11: VMware storage - Oracle ZFS 3-2 | C11: R | D11: Storage Equipment for Vsphere environment | E11: Oracle | G11: 1 | J11: 1 | K11: 65000 | L11: =J11*K11 -> 65000 | M11: Default discount applied | N11: =J11 -> 1 | O11: =21%*K11 -> 13650 | P11: =O11*N11 -> 13650 | Q11: First year support paid at the time of purchase. Assume 50% increase for the last 2 yrs | R11: =L11+P11 -> 78650 | S11: =P11 -> 13650 | T11: =S11 -> 13650 | U11: =T11 -> 13650 | V11: =U11 -> 13650 | W11: =V11 -> 13650 | X11: =IF(C11="R",L11,) -> 65000 | Y11: =V11 -> 13650 | Z11: =W11 -> 13650 | AA11: =Z11 -> 13650 | AB11: =AA11 -> 13650 | AC11: =SUM(R11:AB11) -> 266500
A12: =IF(W12>0,"x","") | B12: Backup server (consolidated on the SPARC system) | D12: HP DL360 G9 | E12: HP | G12: 1 | J12: 0 | K12: 8000 | L12: =J12*K12 -> 0 | M12: Default discount applied | N12: =J12 -> 0 | O12: =21%*K12 -> 1680 | P12: =O12*N12 -> 0 | Q12: First year support paid at the time of purchase. Assume 50% increase for the last 2 yrs | R12: =L12+P12 -> 0 | S12: =P12 -> 0 | T12: =S12 -> 0 | U12: =T12 -> 0 | V12: =U12 -> 0 | W12: =V12 -> 0 | X12: =IF(C12="R",L12,) -> 0 | Y12: =V12 -> 0 | Z12: =W12 -> 0 | AA12: =Z12 -> 0 | AB12: =AA12 -> 0 | AC12: =SUM(R12:AB12) -> 0
A13: =IF(W13>0,"x","") -> x | B13: DB/HSM Server Refresh | D13: Oracle, T7-1, single socket 32-core SPARC CPU. System virtualized with LDOM, DB DTS, HSM DTS, all two node clusters | E13: Oracle | G13: 0.5 | I13: 0.5 | J13: 2 | K13: 44000 | L13: =J13*K13 -> 88000 | M13: Default discount applied | N13: =J13 -> 2 | O13: =16%*K13 -> 7040 | P13: =O13*N13 -> 14080 | Q13: First year support paid at the time of purchase. Assume 50% increase for the last 2 yrs | R13: =L13+P13 -> 102080 | S13: =P13 -> 14080 | T13: =S13 -> 14080 | U13: =T13 -> 14080 | V13: =U13 -> 14080 | W13: =V13 -> 14080 | X13: =IF(C13="R",L13,) -> 0 | Y13: =V13 -> 14080 | Z13: =W13 -> 14080 | AA13: =Z13 -> 14080 | AB13: =AA13 -> 14080 | AC13: =SUM(R13:AB13) -> 228800
A14: =IF(W14>0,"x","") -> x | B14: Switch - 10GB | C14: R | D14: Cisco 10GB Switch - assumed 40% discount | E14: Cisco | G14: 1 | J14: 4 | K14: 20400 | L14: =J14*K14 -> 81600 | M14: 40% discount | N14: =J14 -> 4 | O14: =21%*K14 -> 4284 | P14: =O14*N14 -> 17136 | Q14: First year support paid at the time of purchase. Assume 50% increase for the last 2 yrs | R14: =L14+P14 -> 98736 | S14: =P14 -> 17136 | T14: =S14 -> 17136 | U14: =T14 -> 17136 | V14: =U14 -> 17136 | W14: =V14 -> 17136 | X14: =IF(C14="R",L14,) -> 81600 | Y14: =V14 -> 17136 | Z14: =W14 -> 17136 | AA14: =Z14 -> 17136 | AB14: =AA14 -> 17136 | AC14: =SUM(R14:AB14) -> 334560
A15: =IF(W15>0,"x","") -> x | B15: Centralized Stations VPN hardware | D15: cisco 1841 | E15: Cisco | G15: 1 | J15: 36 | K15: 1200 | L15: =J15*K15 -> 43200 | N15: =J15 -> 36 | O15: =21%*K15 -> 252 | P15: =O15*N15 -> 9072 | Q15: First year support paid at the time of purchase. Assume 50% increase for the last 2 yrs | R15: =L15+P15 -> 52272 | S15: =P15 -> 9072 | T15: =S15 -> 9072 | U15: =T15 -> 9072 | V15: =U15 -> 9072 | W15: =V15 -> 9072 | X15: =IF(C15="R",L15,) -> 0 | Y15: =V15 -> 9072 | Z15: =W15 -> 9072 | AA15: =Z15 -> 9072 | AB15: =AA15 -> 9072 | AC15: =SUM(R15:AB15) -> 133920
A16: =IF(W16>0,"x","") -> x | B16: Firewall / IPS | C16: R | D16: assumed 40% discount | E16: Cisco | G16: 1 | J16: 2 | K16: 17000 | L16: =J16*K16 -> 34000 | M16: 40% discount | N16: =J16 -> 2 | O16: =21%*K16 -> 3570 | P16: =O16*N16 -> 7140 | Q16: First year support paid at the time of purchase. Assume 50% increase for the last 2 yrs | R16: =L16+P16 -> 41140 | S16: =P16 -> 7140 | T16: =S16 -> 7140 | U16: =T16 -> 7140 | V16: =U16 -> 7140 | W16: =V16 -> 7140 | X16: =IF(C16="R",L16,) -> 34000 | Y16: =V16 -> 7140 | Z16: =W16 -> 7140 | AA16: =Z16 -> 7140 | AB16: =AA16 -> 7140 | AC16: =SUM(R16:AB16) -> 139400
A17: =IF(W17>0,"x","") | B17: Link to Lawrenceville office | D17: MPLS | G17: 1 | J17: 0 | K17: 1000 | L17: =J17*K17 -> 0 | N17: =J17 -> 0 | O17: =12*1500 -> 18000 | P17: =N17*O17 -> 0 | R17: =L17+P17 -> 0 | S17: =P17 -> 0 | T17: =S17 -> 0 | U17: =T17 -> 0 | V17: =U17 -> 0 | W17: =V17 -> 0 | X17: =IF(C17="R",L17,) -> 0 | Y17: =V17 -> 0 | Z17: =W17 -> 0 | AA17: =Z17 -> 0 | AB17: =AA17 -> 0 | AC17: =SUM(R17:AB17) -> 0
A18: =IF(W18>0,"x","") | B18: Link to NJ State | D18: MPLS (VPN is used) | G18: 1 | J18: 0 | K18: 1000 | L18: =J18*K18 -> 0 | N18: =J18 -> 0 | O18: =12*1500 -> 18000 | P18: =N18*O18 -> 0 | R18: =L18+P18 -> 0 | S18: =P18 -> 0 | T18: =S18 -> 0 | U18: =T18 -> 0 | V18: =U18 -> 0 | W18: =V18 -> 0 | X18: =IF(C18="R",L18,) -> 0 | Y18: =V18 -> 0 | Z18: =W18 -> 0 | AA18: =Z18 -> 0 | AB18: =AA18 -> 0 | AC18: =SUM(R18:AB18) -> 0
A19: =IF(W19>0,"x","") -> x | B19: RDBMS Mgmt Option Packs | D19: GoldenGate (for Oracle Database) | E19: Oracle | G19: 0.5 | I19: 0.5 | J19: 6 | K19: 17500 | L19: =J19*K19*60% -> 63000 | M19: 40% Discount | N19: =J19 -> 6 | O19: =K19*22%*60% -> 2310 | P19: =O19*N19 -> 13860 | R19: =L19+P19 -> 76860 | S19: =P19 -> 13860 | T19: =S19 -> 13860 | U19: =T19 -> 13860 | V19: =U19 -> 13860 | W19: =V19 -> 13860 | X19: =IF(C19="R",L19,) -> 0 | Y19: =V19 -> 13860 | Z19: =W19 -> 13860 | AA19: =Z19 -> 13860 | AB19: =AA19 -> 13860 | AC19: =SUM(R19:AB19) -> 201600
A20: =IF(W20>0,"x","") -> x | B20: RDBMS Mgmt Option Packs | D20: GoldenGate Foundation Pack (Includes Veridata, Managament Pack & GG studio) | E20: Oracle | G20: 0.5 | I20: 0.5 | J20: 6 | K20: 7500 | L20: =J20*K20*60% -> 27000 | M20: 50% Discount | N20: =J20 -> 6 | O20: =K20*22%*60% -> 990 | P20: =O20*N20 -> 5940 | R20: =L20+P20 -> 32940 | S20: =P20 -> 5940 | T20: =S20 -> 5940 | U20: =T20 -> 5940 | V20: =U20 -> 5940 | W20: =V20 -> 5940 | X20: =IF(C20="R",L20,) -> 0 | Y20: =V20 -> 5940 | Z20: =W20 -> 5940 | AA20: =Z20 -> 5940 | AB20: =AA20 -> 5940 | AC20: =SUM(R20:AB20) -> 86400
A21: =IF(W21>0,"x","") -> x | B21: RDBMS Mgmt Option Packs | D21: Multitenant Option | E21: Oracle | G21: 0.5 | I21: 0.5 | J21: 6 | K21: 17500 | L21: =J21*K21*60% -> 63000 | M21: 50% Discount | N21: =J21 -> 6 | O21: =K21*22%*60% -> 2310 | P21: =O21*N21 -> 13860 | R21: =L21+P21 -> 76860 | S21: =P21 -> 13860 | T21: =S21 -> 13860 | U21: =T21 -> 13860 | V21: =U21 -> 13860 | W21: =V21 -> 13860 | X21: =IF(C21="R",L21,) -> 0 | Y21: =V21 -> 13860 | Z21: =W21 -> 13860 | AA21: =Z21 -> 13860 | AB21: =AA21 -> 13860 | AC21: =SUM(R21:AB21) -> 201600
A22: =IF(W22>0,"x","") -> x | B22: VIN Decoder | D22: Vin Power | E22: VINPower | G22: 1 | L22: =J22*K22 -> 0 | N22: 1 | O22: 13000 | P22: =O22*N22 -> 13000 | R22: =L22+P22 -> 13000 | S22: =P22 -> 13000 | T22: =S22 -> 13000 | U22: =T22 -> 13000 | V22: =U22 -> 13000 | W22: =V22 -> 13000 | X22: =IF(C22="R",L22,) -> 0 | Y22: =V22 -> 13000 | Z22: =W22 -> 13000 | AA22: =Z22 -> 13000 | AB22: =AA22 -> 13000 | AC22: =SUM(R22:AB22) -> 130000
A23: =IF(W23>0,"x","") -> x | B23: Business Intelligence | D23: Actuate, PROD, UAT, QAT, DEV | E23: Actuate | G23: 1 | J23: 1 | K23: =268619.25 -> 268619.25 | L23: =J23*K23 -> 268619.25 | N23: 1 | O23: =K23*20% -> 53723.85 | P23: =O23*N23 -> 53723.85 | R23: =L23+P23 -> 322343.1 | S23: =P23 -> 53723.85 | T23: =S23 -> 53723.85 | U23: =T23 -> 53723.85 | V23: =U23 -> 53723.85 | W23: =V23 -> 53723.85 | X23: =IF(C23="R",L23,) -> 0 | Y23: =V23 -> 53723.85 | Z23: =W23 -> 53723.85 | AA23: =Z23 -> 53723.85 | AB23: =AA23 -> 53723.85 | AC23: =SUM(R23:AB23) -> 805857.75
A24: =IF(W24>0,"x","") -> x | B24: Linux subscription | D24: Satellite server | E24: RedHat | G24: 1 | L24: =J24*K24 -> 0 | N24: 1 | O24: 10000 | P24: =O24*N24 -> 10000 | R24: =L24+P24 -> 10000 | S24: =P24 -> 10000 | T24: =S24 -> 10000 | U24: =T24 -> 10000 | V24: =U24 -> 10000 | W24: =V24 -> 10000 | X24: =IF(C24="R",L24,) -> 0 | Y24: =V24 -> 10000 | Z24: =W24 -> 10000 | AA24: =Z24 -> 10000 | AB24: =AA24 -> 10000 | AC24: =SUM(R24:AB24) -> 100000
A25: =IF(W25>0,"x","") -> x | B25: Linux subscription | D25: Satellite server client license | E25: RedHat | G25: 1 | L25: =J25*K25 -> 0 | N25: 200 | O25: 192 | P25: =O25*N25 -> 38400 | R25: =L25+P25 -> 38400 | S25: =P25 -> 38400 | T25: =S25 -> 38400 | U25: =T25 -> 38400 | V25: =U25 -> 38400 | W25: =V25 -> 38400 | X25: =IF(C25="R",L25,) -> 0 | Y25: =V25 -> 38400 | Z25: =W25 -> 38400 | AA25: =Z25 -> 38400 | AB25: =AA25 -> 38400 | AC25: =SUM(R25:AB25) -> 384000
A26: =IF(W26>0,"x","") | B26: Windows Server | D26: Datacenter edition | E26: Microsoft | G26: 0.5 | I26: 0.5 | J26: 2 | K26: 5000 | L26: =J26*K26 -> 10000 | N26: =J26 -> 2 | P26: =O26*N26 -> 0 | R26: =L26+P26 -> 10000 | S26: =P26 -> 0 | T26: =S26 -> 0 | U26: =T26 -> 0 | V26: =U26 -> 0 | W26: =V26 -> 0 | X26: =IF(C26="R",L26,) -> 0 | Y26: =V26 -> 0 | Z26: =W26 -> 0 | AA26: =Z26 -> 0 | AB26: =AA26 -> 0 | AC26: =SUM(R26:AB26) -> 10000
A27: =IF(W27>0,"x","") | B27: Virus Scanner (Windows Defender) | D27: Virus/Malware scanner for test units | E27: Microsoft | G27: 1 | L27: =J27*K27 -> 0 | N27: 0 | O27: 32 | P27: =O27*N27 -> 0 | R27: =L27+P27 -> 0 | S27: =P27 -> 0 | T27: =S27 -> 0 | U27: =T27 -> 0 | V27: =U27 -> 0 | W27: =V27 -> 0 | X27: =IF(C27="R",L27,) -> 0 | Y27: =V27 -> 0 | Z27: =W27 -> 0 | AA27: =Z27 -> 0 | AB27: =AA27 -> 0 | AC27: =SUM(R27:AB27) -> 0
A28: =IF(W28>0,"x","") -> x | B28: Mobile Device Management | D28: Device management for Windows 10 devices | E28: Soti | G28: 1 | L28: =J28*K28 -> 0 | N28: 1400 | O28: 36 | P28: =O28*N28 -> 50400 | R28: =L28+P28 -> 50400 | S28: =P28 -> 50400 | T28: =S28 -> 50400 | U28: =T28 -> 50400 | V28: =U28 -> 50400 | W28: =V28 -> 50400 | X28: =IF(C28="R",L28,) -> 0 | Y28: =V28 -> 50400 | Z28: =W28 -> 50400 | AA28: =Z28 -> 50400 | AB28: =AA28 -> 50400 | AC28: =SUM(R28:AB28) -> 504000
A29: =IF(W29>0,"x","") -> x | B29: Backup Software | D29: NetBackup - migration to SPARC platform | E29: Symantec | G29: 0.5 | I29: 0.5 | J29: 1 | K29: 8000 | L29: =J29*K29 -> 8000 | N29: =J29 -> 1 | O29: 2000 | P29: =O29*N29 -> 2000 | R29: =L29+P29 -> 10000 | S29: =P29 -> 2000 | T29: =S29 -> 2000 | U29: =T29 -> 2000 | V29: =U29 -> 2000 | W29: =V29 -> 2000 | X29: =IF(C29="R",L29,) -> 0 | Y29: =V29 -> 2000 | Z29: =W29 -> 2000 | AA29: =Z29 -> 2000 | AB29: =AA29 -> 2000 | AC29: =SUM(R29:AB29) -> 28000
A30: =IF(W30>0,"x","") -> x | B30: Backup client licenses | D30: Netbackup Enterprise Client (LDOMs) | E30: Symantec | G30: 0.5 | I30: 0.5 | J30: 2 | K30: 2000 | L30: =J30*K30 -> 4000 | N30: =J30 -> 2 | O30: =20%*K30 -> 400 | P30: =O30*N30 -> 800 | R30: =L30+P30 -> 4800 | S30: =P30 -> 800 | T30: =S30 -> 800 | U30: =T30 -> 800 | V30: =U30 -> 800 | W30: =V30 -> 800 | X30: =IF(C30="R",L30,) -> 0 | Y30: =V30 -> 800 | Z30: =W30 -> 800 | AA30: =Z30 -> 800 | AB30: =AA30 -> 800 | AC30: =SUM(R30:AB30) -> 12000
A31: =IF(W31>0,"x","") -> x | B31: RDBMS Mgmt Option Packs | D31: GoldenGate (for Oracle Database) | E31: Oracle | G31: 0.5 | I31: 0.5 | J31: 150 | K31: 350 | L31: =J31*K31*60% -> 31500 | M31: 40% Discount | N31: =J31 -> 150 | O31: =K31*22%*60% -> 46.2 | P31: =O31*N31 -> 6930 | R31: =L31+P31 -> 38430 | S31: =P31 -> 6930 | T31: =S31 -> 6930 | U31: =T31 -> 6930 | V31: =U31 -> 6930 | W31: =V31 -> 6930 | X31: =IF(C31="R",L31,) -> 0 | Y31: =V31 -> 6930 | Z31: =W31 -> 6930 | AA31: =Z31 -> 6930 | AB31: =AA31 -> 6930 | AC31: =SUM(R31:AB31) -> 100800
A32: =IF(W32>0,"x","") -> x | B32: RDBMS Mgmt Option Packs | D32: GoldenGate Foundation Pack (Includes Veridata, Managament Pack & GG studio) | E32: Oracle | G32: 0.5 | I32: 0.5 | J32: 150 | K32: 150 | L32: =J32*K32*60% -> 13500 | M32: 50% Discount | N32: =J32 -> 150 | O32: =K32*22%*60% -> 19.8 | P32: =O32*N32 -> 2970 | R32: =L32+P32 -> 16470 | S32: =P32 -> 2970 | T32: =S32 -> 2970 | U32: =T32 -> 2970 | V32: =U32 -> 2970 | W32: =V32 -> 2970 | X32: =IF(C32="R",L32,) -> 0 | Y32: =V32 -> 2970 | Z32: =W32 -> 2970 | AA32: =Z32 -> 2970 | AB32: =AA32 -> 2970 | AC32: =SUM(R32:AB32) -> 43200
A33: =IF(W33>0,"x","") -> x | B33: RDBMS Mgmt Option Packs | D33: Multitenant Option | E33: Oracle | G33: 0.5 | I33: 0.5 | J33: 150 | K33: 350 | L33: =J33*K33*60% -> 31500 | M33: 50% Discount | N33: =J33 -> 150 | O33: =K33*22%*60% -> 46.2 | P33: =O33*N33 -> 6930 | R33: =L33+P33 -> 38430 | S33: =P33 -> 6930 | T33: =S33 -> 6930 | U33: =T33 -> 6930 | V33: =U33 -> 6930 | W33: =V33 -> 6930 | X33: =IF(C33="R",L33,) -> 0 | Y33: =V33 -> 6930 | Z33: =W33 -> 6930 | AA33: =Z33 -> 6930 | AB33: =AA33 -> 6930 | AC33: =SUM(R33:AB33) -> 100800
A34: =IF(W34>0,"x","") | B34: Windows Server | D34: Datacenter edition | E34: Microsoft | G34: 0.5 | I34: 0.5 | J34: 2 | K34: 5000 | L34: =J34*K34 -> 10000 | N34: =J34 -> 2 | P34: =O34*N34 -> 0 | R34: =L34+P34 -> 10000 | S34: =P34 -> 0 | T34: =S34 -> 0 | U34: =T34 -> 0 | V34: =U34 -> 0 | W34: =V34 -> 0 | X34: =IF(C34="R",L34,) -> 0 | Y34: =V34 -> 0 | Z34: =W34 -> 0 | AA34: =Z34 -> 0 | AB34: =AA34 -> 0 | AC34: =SUM(R34:AB34) -> 10000
A35: =IF(W35>0,"x","") | B35: Backup client licenses | D35: Netbackup Enterprise Client (Vmware) | E35: Symantec | G35: 0.5 | I35: 0.5 | J35: 0 | K35: 2000 | L35: =J35*K35 -> 0 | N35: =J35 -> 0 | O35: =20%*K35 -> 400 | P35: =O35*N35 -> 0 | R35: =L35+P35 -> 0 | S35: =P35 -> 0 | T35: =S35 -> 0 | U35: =T35 -> 0 | V35: =U35 -> 0 | W35: =V35 -> 0 | X35: =IF(C35="R",L35,) -> 0 | Y35: =V35 -> 0 | Z35: =W35 -> 0 | AA35: =Z35 -> 0 | AB35: =AA35 -> 0 | AC35: =SUM(R35:AB35) -> 0
A36: =IF(W36>0,"x","") | B36: Tape | D36: LTO5 | E36: TBD | F36: 0 | G36: 1 | H36: 0 | I36: 0 | J36: 150 | K36: 100 | L36: =J36*K36 -> 15000 | N36: 0 | O36: 300 | P36: =O36*N36 -> 0 | R36: =L36+P36 -> 15000 | S36: =P36 -> 0 | T36: =S36 -> 0 | U36: =T36 -> 0 | V36: =U36 -> 0 | W36: =V36 -> 0 | X36: =IF(C36="R",L36,) -> 0 | Y36: =V36 -> 0 | Z36: =W36 -> 0 | AA36: =Z36 -> 0 | AB36: =AA36 -> 0 | AC36: =SUM(R36:AB36) -> 15000
A37: =IF(W37>0,"x","") -> x | B37: Hosting | D37: Additional cabinet | E37: Verizon | G37: 1 | J37: 1 | K37: 3891.25 | L37: =J37*K37 -> 3891.25 | N37: 1 | O37: =2984*12 -> 35808 | P37: =O37*N37 -> 35808 | R37: =L37+P37 -> 39699.25 | S37: =P37 -> 35808 | T37: =S37 -> 35808 | U37: =T37 -> 35808 | V37: =U37 -> 35808 | W37: =V37 -> 35808 | X37: =IF(C37="R",L37,) -> 0 | Y37: =V37 -> 35808 | Z37: =W37 -> 35808 | AA37: =Z37 -> 35808 | AB37: =AA37 -> 35808 | AC37: =SUM(R37:AB37) -> 361971.25
A38: =IF(W38>0,"x","") -> x | B38: VMware vSphere(Virtualization Hardware) | C38: R | D38: 2 x Intel® Xeon® E5-2699 v3 18-core 2.3GHz core Intel CPU, 512GB RAM, PROD | E38: HP | G38: 1 | J38: 2 | K38: 24000 | L38: =J38*K38 -> 48000 | M38: Default discount applied | N38: =J38 -> 2 | O38: =21%*K38 -> 5040 | P38: =O38*N38 -> 10080 | Q38: First year paid at the time of purchase. Assume 50% increase for the last 2 yrs | R38: =L38+P38 -> 58080 | S38: =P38 -> 10080 | T38: =S38 -> 10080 | U38: =T38 -> 10080 | V38: =U38 -> 10080 | W38: =V38 -> 10080 | X38: =IF(C38="R",L38,) -> 48000 | Y38: =V38 -> 10080 | Z38: =W38 -> 10080 | AA38: =Z38 -> 10080 | AB38: =AA38 -> 10080 | AC38: =SUM(R38:AB38) -> 196800
A39: =IF(W39>0,"x","") -> x | B39: DB/HSM Server Refresh | D39: Oracle, T7-1, single socket 32-core SPARC CPU. System virtualized with LDOM, DR-DB PROD,DR-HSM PROD, all two node clusters | E39: Oracle | G39: 0.5 | I39: 0.5 | J39: 1 | K39: 44000 | L39: =J39*K39 -> 44000 | M39: Default discount applied | N39: =J39 -> 1 | O39: =16%*K39 -> 7040 | P39: =O39*N39 -> 7040 | Q39: First year paid at the time of purchase. Assume 50% increase for the last 2 yrs | R39: =L39+P39 -> 51040 | S39: =P39 -> 7040 | T39: =S39 -> 7040 | U39: =T39 -> 7040 | V39: =U39 -> 7040 | W39: =V39 -> 7040 | X39: =IF(C39="R",L39,) -> 0 | Y39: =V39 -> 7040 | Z39: =W39 -> 7040 | AA39: =Z39 -> 7040 | AB39: =AA39 -> 7040 | AC39: =SUM(R39:AB39) -> 114400
A40: =IF(W40>0,"x","") -> x | B40: vCentre | C40: R | D40: HP DL360 G9 | E40: HP | G40: 1 | J40: 1 | K40: 8000 | L40: =K40*J40 -> 8000 | N40: =J40 -> 1 | O40: =21%*K40 -> 1680 | P40: =O40*N40 -> 1680 | Q40: First year paid at the time of purchase. Assume 50% increase for the last 2 yrs | R40: =L40+P40 -> 9680 | S40: =P40 -> 1680 | T40: =S40 -> 1680 | U40: =T40 -> 1680 | V40: =U40 -> 1680 | W40: =V40 -> 1680 | X40: =IF(C40="R",L40,) -> 8000 | Y40: =V40 -> 1680 | Z40: =W40 -> 1680 | AA40: =Z40 -> 1680 | AB40: =AA40 -> 1680 | AC40: =SUM(R40:AB40) -> 32800
A41: =IF(W41>0,"x","") -> x | B41: Centralized Logging/Network monitor/HIDS (virtualized) | C41: R | D41: HP DL360 G9 | E41: HP | G41: 1 | J41: 1 | K41: 8000 | L41: =K41*J41 -> 8000 | N41: =J41 -> 1 | O41: =21%*K41 -> 1680 | P41: =O41*N41 -> 1680 | Q41: First year paid at the time of purchase. Assume 50% increase for the last 2 yrs | R41: =L41+P41 -> 9680 | S41: =P41 -> 1680 | T41: =S41 -> 1680 | U41: =T41 -> 1680 | V41: =U41 -> 1680 | W41: =V41 -> 1680 | X41: =IF(C41="R",L41,) -> 8000 | Y41: =V41 -> 1680 | Z41: =W41 -> 1680 | AA41: =Z41 -> 1680 | AB41: =AA41 -> 1680 | AC41: =SUM(R41:AB41) -> 32800
A42: =IF(W42>0,"x","") -> x | B42: VMware storage - Oracle ZFS 3-2 | C42: R | D42: Storage Equipment for Vsphere environment | E42: Oracle | G42: 1 | J42: 1 | K42: 65000 | L42: =J42*K42 -> 65000 | N42: =J42 -> 1 | O42: =21%*K42 -> 13650 | P42: =O42*N42 -> 13650 | R42: =L42+P42 -> 78650 | S42: =P42 -> 13650 | T42: =S42 -> 13650 | U42: =T42 -> 13650 | V42: =U42 -> 13650 | W42: =V42 -> 13650 | X42: =IF(C42="R",L42,) -> 65000 | Y42: =V42 -> 13650 | Z42: =W42 -> 13650 | AA42: =Z42 -> 13650 | AB42: =AA42 -> 13650 | AC42: =SUM(R42:AB42) -> 266500
A43: =IF(W43>0,"x","") | B43: Backup server (consolidated on the SPARC system) | C43: R | D43: HP DL360 G9 | E43: HP | G43: 1 | J43: 0 | K43: 8000 | L43: =J43*K43 -> 0 | N43: =J43 -> 0 | O43: =21%*K43 -> 1680 | P43: =O43*N43 -> 0 | Q43: First year paid at the time of purchase. Assume 50% increase for the last 2 yrs | R43: =L43+P43 -> 0 | S43: =P43 -> 0 | T43: =S43 -> 0 | U43: =T43 -> 0 | V43: =U43 -> 0 | W43: =V43 -> 0 | X43: =IF(C43="R",L43,) -> 0 | Y43: =V43 -> 0 | Z43: =W43 -> 0 | AA43: =Z43 -> 0 | AB43: =AA43 -> 0 | AC43: =SUM(R43:AB43) -> 0
A44: =IF(W44>0,"x","") | B44: Tape | C44: R | D44: LTO5 | E44: TBD | F44: 0 | G44: 1 | H44: 0 | I44: 0 | J44: 150 | K44: 100 | L44: =J44*K44 -> 15000 | N44: 0 | O44: 300 | P44: =O44*N44 -> 0 | R44: =L44+P44 -> 15000 | S44: =P44 -> 0 | T44: =S44 -> 0 | U44: =T44 -> 0 | V44: =U44 -> 0 | W44: =V44 -> 0 | X44: =IF(C44="R",L44,) -> 15000 | Y44: =V44 -> 0 | Z44: =W44 -> 0 | AA44: =Z44 -> 0 | AB44: =AA44 -> 0 | AC44: =SUM(R44:AB44) -> 30000
A45: =IF(W45>0,"x","") -> x | B45: Switch - 10GB | C45: R | D45: Cisco 10GB Switch - assumed 40% discount | E45: Cisco | G45: 1 | J45: 4 | K45: 20400 | L45: =J45*K45 -> 81600 | N45: =J45 -> 4 | O45: =21%*K45 -> 4284 | P45: =O45*N45 -> 17136 | Q45: First year paid at the time of purchase. Assume 50% increase for the last 2 yrs | R45: =L45+P45 -> 98736 | S45: =P45 -> 17136 | T45: =S45 -> 17136 | U45: =T45 -> 17136 | V45: =U45 -> 17136 | W45: =V45 -> 17136 | X45: =IF(C45="R",L45,) -> 81600 | Y45: =V45 -> 17136 | Z45: =W45 -> 17136 | AA45: =Z45 -> 17136 | AB45: =AA45 -> 17136 | AC45: =SUM(R45:AB45) -> 334560
A46: =IF(W46>0,"x","") -> x | B46: Firewall / IPS | C46: R | D46: assumed 40% discount | E46: Cisco | G46: 1 | J46: 1 | K46: 17000 | L46: =J46*K46 -> 17000 | N46: =J46 -> 1 | O46: 3567.6 | P46: =O46*N46 -> 3567.6 | Q46: First year paid at the time of purchase. Assume 50% increase for the last 2 yrs | R46: =L46+P46 -> 20567.6 | S46: =P46 -> 3567.6 | T46: =S46 -> 3567.6 | U46: =T46 -> 3567.6 | V46: =U46 -> 3567.6 | W46: =V46 -> 3567.6 | X46: =IF(C46="R",L46,) -> 17000 | Y46: =V46 -> 3567.6 | Z46: =W46 -> 3567.6 | AA46: =Z46 -> 3567.6 | AB46: =AA46 -> 3567.6 | AC46: =SUM(R46:AB46) -> 69676
A47: =IF(W47>0,"x","") | B47: Internet Link | D47: Inspection facility internet link | G47: 1 | J47: 0 | K47: 1000 | L47: =J47*K47 -> 0 | N47: 0 | O47: =12*300 -> 3600 | P47: =O47*N47 -> 0 | R47: =L47+P47 -> 0 | S47: =P47 -> 0 | T47: =S47 -> 0 | U47: =T47 -> 0 | V47: =U47 -> 0 | W47: =V47 -> 0 | X47: =IF(C47="R",L47,) -> 0 | Y47: =V47 -> 0 | Z47: =W47 -> 0 | AA47: =Z47 -> 0 | AB47: =AA47 -> 0 | AC47: =SUM(R47:AB47) -> 0
A48: =IF(W48>0,"x","") | B48: Link to the State | D48: MPLS (VPN is used) | G48: 1 | J48: 0 | K48: 1000 | L48: =J48*K48 -> 0 | N48: =J48 -> 0 | O48: =12*1500 -> 18000 | P48: =N48*O48 -> 0 | R48: =L48+P48 -> 0 | S48: =P48 -> 0 | T48: =S48 -> 0 | U48: =T48 -> 0 | V48: =U48 -> 0 | W48: =V48 -> 0 | X48: =IF(C48="R",L48,) -> 0 | Y48: =V48 -> 0 | Z48: =W48 -> 0 | AA48: =Z48 -> 0 | AB48: =AA48 -> 0 | AC48: =SUM(R48:AB48) -> 0
A49: =IF(W49>0,"x","") -> x | B49: RDBMS Mgmt Option Packs | D49: GoldenGate (for Oracle Database) | E49: Oracle | G49: 0.5 | I49: 0.5 | J49: 3 | K49: 17500 | L49: =J49*K49*60% -> 31500 | M49: 40% Discount | N49: =J49 -> 3 | O49: =K49*22%*60% -> 2310 | P49: =O49*N49 -> 6930 | R49: =L49+P49 -> 38430 | S49: =P49 -> 6930 | T49: =S49 -> 6930 | U49: =T49 -> 6930 | V49: =U49 -> 6930 | W49: =V49 -> 6930 | X49: =IF(C49="R",L49,) -> 0 | Y49: =V49 -> 6930 | Z49: =W49 -> 6930 | AA49: =Z49 -> 6930 | AB49: =AA49 -> 6930 | AC49: =SUM(R49:AB49) -> 100800
A50: =IF(W50>0,"x","") -> x | B50: RDBMS Mgmt Option Packs | D50: GoldenGate Foundation Pack (Includes Veridata, Managament Pack & GG studio) | E50: Oracle | G50: 0.5 | I50: 0.5 | J50: 3 | K50: 7500 | L50: =J50*K50*60% -> 13500 | M50: 50% Discount | N50: =J50 -> 3 | O50: =K50*22%*60% -> 990 | P50: =O50*N50 -> 2970 | R50: =L50+P50 -> 16470 | S50: =P50 -> 2970 | T50: =S50 -> 2970 | U50: =T50 -> 2970 | V50: =U50 -> 2970 | W50: =V50 -> 2970 | X50: =IF(C50="R",L50,) -> 0 | Y50: =V50 -> 2970 | Z50: =W50 -> 2970 | AA50: =Z50 -> 2970 | AB50: =AA50 -> 2970 | AC50: =SUM(R50:AB50) -> 43200
A51: =IF(W51>0,"x","") -> x | B51: RDBMS Mgmt Option Packs | D51: Multitenant Option | E51: Oracle | G51: 0.5 | I51: 0.5 | J51: 3 | K51: 17500 | L51: =J51*K51*60% -> 31500 | M51: 50% Discount | N51: =J51 -> 3 | O51: =K51*22%*60% -> 2310 | P51: =O51*N51 -> 6930 | R51: =L51+P51 -> 38430 | S51: =P51 -> 6930 | T51: =S51 -> 6930 | U51: =T51 -> 6930 | V51: =U51 -> 6930 | W51: =V51 -> 6930 | X51: =IF(C51="R",L51,) -> 0 | Y51: =V51 -> 6930 | Z51: =W51 -> 6930 | AA51: =Z51 -> 6930 | AB51: =AA51 -> 6930 | AC51: =SUM(R51:AB51) -> 100800
A52: =IF(W52>0,"x","") | B52: Windows Server | D52: Datacenter edition | E52: Microsoft | G52: 0.5 | I52: 0.5 | J52: 2 | K52: 5000 | L52: =J52*K52 -> 10000 | N52: =J52 -> 2 | P52: =O52*N52 -> 0 | R52: =L52+P52 -> 10000 | S52: =P52 -> 0 | T52: =S52 -> 0 | U52: =T52 -> 0 | V52: =U52 -> 0 | W52: =V52 -> 0 | X52: =IF(C52="R",L52,) -> 0 | Y52: =V52 -> 0 | Z52: =W52 -> 0 | AA52: =Z52 -> 0 | AB52: =AA52 -> 0 | AC52: =SUM(R52:AB52) -> 10000
A53: =IF(W53>0,"x","") -> x | B53: Backup Software | D53: NetBackup - migration to SPARC platform | E53: Symantec | G53: 0.5 | I53: 0.5 | J53: 1 | K53: 8000 | L53: =J53*K53 -> 8000 | N53: =J53 -> 1 | O53: 2000 | P53: =O53*N53 -> 2000 | R53: =L53+P53 -> 10000 | S53: =P53 -> 2000 | T53: =S53 -> 2000 | U53: =T53 -> 2000 | V53: =U53 -> 2000 | W53: =V53 -> 2000 | X53: =IF(C53="R",L53,) -> 0 | Y53: =V53 -> 2000 | Z53: =W53 -> 2000 | AA53: =Z53 -> 2000 | AB53: =AA53 -> 2000 | AC53: =SUM(R53:AB53) -> 28000
A54: =IF(W54>0,"x","") -> x | B54: Backup client licenses | D54: Netbackup Enterprise Client (LDOM) | E54: Symantec | G54: 0.5 | I54: 0.5 | J54: 1 | K54: 2000 | L54: =J54*K54 -> 2000 | N54: =J54 -> 1 | O54: =20%*K54 -> 400 | P54: =O54*N54 -> 400 | R54: =L54+P54 -> 2400 | S54: =P54 -> 400 | T54: =S54 -> 400 | U54: =T54 -> 400 | V54: =U54 -> 400 | W54: =V54 -> 400 | X54: =IF(C54="R",L54,) -> 0 | Y54: =V54 -> 400 | Z54: =W54 -> 400 | AA54: =Z54 -> 400 | AB54: =AA54 -> 400 | AC54: =SUM(R54:AB54) -> 6000 | AD54: 6320065
B57: Grand Total | L57: =SUM(L5:L54) -> 1386910.5 | P57: =SUM(P5:P54) -> 445395.45 | R57: =SUM(R5:R54) -> 1832306 | S57: =SUM(S5:S54) -> 445395.45 | T57: =SUM(T5:T54) -> 445395.45 | U57: =SUM(U5:U54) -> 445395.45 | V57: =SUM(V5:V54) -> 445395.45 | W57: =SUM(W5:W54) -> 445395.45 | X57: =SUM(X5:X54) -> 479200 | Y57: =SUM(Y5:Y54) -> 445395.45 | ... AB57: =SUM(AB5:AB54) -> 445395.45 | AC57: =SUM(R57:AB57) -> 6320065
Y58: =Y57+X57 -> 924595.45
Z59: Check | AA59: =L57+P57*10+X57 -> 6320065

Sheet infrastructure
B1: Item | D1: Description | G1: Vendor | H1: Cost Split | N1: One-Time | R1: Recurring (Annual)
A2: Pickup | B2: RFP BUDGET IT Infrastructure Cost Model | T2: Add yearly support inflation 2% | U2: Assumptions/Notes: Prices is US Dollars Taxes not included Recurring costs start from first year, unless specified Assume hardware refresh at year 5, 50% of initial cost | V2: Provide cost that PA covers to estimate what needs to be included in the budget | W2: 0
L3: NJ | W3: 2020 Feb
A4: x | B4: Item | D4: Description | E4: Environment | F4: Classification | G4: Vendor | H4: PA | I4: NJ | J4: VT | K4: MASS | N4: One-Time | R4: Recurring (Annual) | V4: Year 0 | W4: Year 1 | X4: Year 2 | Y4: Year 3 | Z4: Year 4 | AA4: Year 5 | AB4: Refresh Year 5 | AC4: Year 6 | AD4: Year 7 | AE4: Year 8 | AF4: Year 9 | AG4: Year 10 | AH4: Total
A5: =IF(AA5>0,"x","") -> x | B5: Hosting | D5: Additional cabinet | E5: PRIMARY | F5: Datacenter Hosting | G5: Equinix | I5: 1 | L5: NJ | M5: =SUM(H5:K5) -> 1 | N5: 1 | O5: 5000 | P5: =N5*O5 -> 5000 | R5: =N5 -> 1 | S5: =2656*12*R5 -> 31872 | T5: =S5*R5 -> 31872 | U5: Needed for the equipment refresh | V5: =P5+T5 -> 36872 | W5: =T5 -> 31872 | X5: =W5 -> 31872 | Y5: =X5 -> 31872 | Z5: =Y5 -> 31872 | AA5: =Z5 -> 31872 | AB5: =IF(C5="R",P5,) -> 0 | AC5: =Z5 -> 31872 | AD5: =AA5 -> 31872 | AE5: =AD5 -> 31872 | AF5: =AE5 -> 31872 | AG5: =AF5 -> 31872 | AH5: =SUM(V5:AF5) -> 323720
A6: =IF(AA6>0,"x","") -> x | B6: Hosting | D6: Existing Cost | E6: PRIMARY/DR | F6: Datacenter Hosting | G6: Equinix | I6: 1 | L6: NJ | M6: =SUM(H6:K6) -> 1 | N6: 1 | P6: =N6*O6 -> 0 | R6: =N6 -> 1 | S6: =(2000+2400)*12*R6 -> 52800 | T6: =S6*R6 -> 52800 | V6: =P6+T6 -> 52800 | W6: =T6 -> 52800 | X6: =W6 -> 52800 | Y6: =X6 -> 52800 | Z6: =Y6 -> 52800 | AA6: =Z6 -> 52800 | AB6: =IF(C6="R",P6,) -> 0 | AC6: =Z6 -> 52800 | AD6: =AA6 -> 52800 | AE6: =AD6 -> 52800 | AF6: =AE6 -> 52800 | AG6: =AF6 -> 52800 | AH6: =SUM(V6:AF6) -> 528000
A7: =IF(AA7>0,"x","") -> x | B7: Hosting | D7: Existing Cost | E7: PRIMARY/DR | F7: Datacenter Hosting | G7: Equinix | H7: 1 | L7: PA | M7: =SUM(H7:K7) -> 1 | N7: 1 | P7: =N7*O7 -> 0 | R7: =N7 -> 1 | S7: =(20000-2000-2400)*12*R7 -> 187200 | T7: =S7*R7 -> 187200 | V7: =P7+T7 -> 187200 | W7: =T7 -> 187200 | X7: =W7 -> 187200 | Y7: =X7 -> 187200 | Z7: =Y7 -> 187200 | AA7: =Z7 -> 187200 | AB7: =IF(C7="R",P7,) -> 0 | AC7: =Z7 -> 187200 | AD7: =AA7 -> 187200 | AE7: =AD7 -> 187200 | AF7: =AE7 -> 187200 | AG7: =AF7 -> 187200 | AH7: =SUM(V7:AF7) -> 1872000
A8: =IF(AA8>0,"x","") | B8: Cables / Wiring / Cable Management | E8: PRIMARY/DR | F8: Hardware | G8: TBD | I8: 1 | L8: NJ | M8: =SUM(H8:K8) -> 1 | N8: 1 | O8: 2000 | P8: =N8*O8 -> 2000 | R8: 1 | T8: =S8*R8 -> 0 | V8: =P8+T8 -> 2000 | W8: =T8 -> 0 | X8: =W8 -> 0 | Y8: =X8 -> 0 | Z8: =Y8 -> 0 | AA8: =Z8 -> 0 | AB8: =IF(C8="R",P8,) -> 0 | AC8: =Z8 -> 0 | AD8: =AA8 -> 0 | AE8: =AD8 -> 0 | AF8: =AE8 -> 0 | AG8: =AF8 -> 0 | AH8: =SUM(V8:AF8) -> 2000
A9: =IF(AA9>0,"x","") -> x | B9: VMware vSphere(Virtualization Hardware) | D9: Existing Cost | E9: PRIMARY/DR | F9: Hardware/Software | G9: HP | H9: 1 | L9: PA | M9: =SUM(H9:K9) -> 1 | N9: 1 | P9: =N9*O9 -> 0 | R9: =N9 -> 1 | S9: 55480 | T9: =S9*R9 -> 55480 | U9: Includes HP systems, EVA storage and Vmware licensing. 50% reduction in support cost based on the systems refresh | V9: =P9+T9 -> 55480 | W9: =(T9+T9*$W$2)/2 -> 27740 | X9: =W9+W9*$W$2 -> 27740 | Y9: =X9+X9*$W$2 -> 27740 | Z9: =Y9+Y9*$W$2 -> 27740 | AA9: =Z9+Z9*$W$2 -> 27740 | AB9: =IF(C9="R",P9,) -> 0 | AC9: =AA9+AA9*$W$2 -> 27740 | AD9: =AC9+AC9*$W$2 -> 27740 | AE9: =AD9+AD9*$W$2 -> 27740 | AF9: =AE9+AE9*$W$2 -> 27740 | AG9: =AF9+AF9*$W$2 -> 27740 | AH9: =SUM(V9:AF9) -> 305140
A10: =IF(AA10>0,"x","") -> x | B10: VMware vSphere(Virtualization Hardware) | D10: Existing Cost | E10: PRIMARY/DR | F10: Hardware/Software | G10: HP | I10: 1 | L10: NJ | M10: =SUM(H10:K10) -> 1 | N10: 1 | P10: =N10*O10 -> 0 | R10: =N10 -> 1 | S10: 22785 | T10: =S10*R10 -> 22785 | U10: Includes HP systems, EVA storage and Vmware licensing | V10: =P10+T10 -> 22785 | W10: =(T10+T10*$W$2)/2 -> 11392.5 | X10: =W10+W10*$W$2 -> 11392.5 | Y10: =X10+X10*$W$2 -> 11392.5 | Z10: =Y10+Y10*$W$2 -> 11392.5 | AA10: =Z10+Z10*$W$2 -> 11392.5 | AB10: =IF(C10="R",P10,) -> 0 | AC10: =AA10+AA10*$W$2 -> 11392.5 | AD10: =AC10+AC10*$W$2 -> 11392.5 | AE10: =AD10+AD10*$W$2 -> 11392.5 | AF10: =AE10+AE10*$W$2 -> 11392.5 | AG10: =AF10+AF10*$W$2 -> 11392.5 | AH10: =AG10+AG10*$W$2 -> 11392.5
A11: =IF(AA11>0,"x","") -> x | B11: RedHat | D11: Existing Cost | E11: PRIMARY/DR | F11: Software | G11: IBM | H11: 1 | L11: PA | M11: =SUM(H11:K11) -> 1 | N11: 1 | P11: =N11*O11 -> 0 | R11: =N11 -> 1 | S11: 20000 | T11: =S11*R11 -> 20000 | V11: =P11+T11 -> 20000 | W11: =T11+T11*$W$2 -> 20000 | X11: =W11+W11*$W$2 -> 20000 | Y11: =X11+X11*$W$2 -> 20000 | Z11: =Y11+Y11*$W$2 -> 20000 | AA11: =Z11+Z11*$W$2 -> 20000 | AB11: =IF(C11="R",P11,) -> 0 | AC11: =AA11+AA11*$W$2 -> 20000 | AD11: =AC11+AC11*$W$2 -> 20000 | AE11: =AD11+AD11*$W$2 -> 20000 | AF11: =AE11+AE11*$W$2 -> 20000 | AG11: =AF11+AF11*$W$2 -> 20000 | AH11: =AG11+AG11*$W$2 -> 20000
A12: =IF(AA12>0,"x","") -> x | B12: RedHat | D12: Existing Cost | E12: PRIMARY/DR | F12: Software | G12: IBM | I12: 1 | L12: NJ | M12: =SUM(H12:K12) -> 1 | N12: 1 | P12: =N12*O12 -> 0 | R12: =N12 -> 1 | S12: 20000 | T12: =S12*R12 -> 20000 | V12: =P12+T12 -> 20000 | W12: =T12+T12*$W$2 -> 20000 | X12: =W12+W12*$W$2 -> 20000 | Y12: =X12+X12*$W$2 -> 20000 | Z12: =Y12+Y12*$W$2 -> 20000 | AA12: =Z12+Z12*$W$2 -> 20000 | AB12: =IF(C12="R",P12,) -> 0 | AC12: =AA12+AA12*$W$2 -> 20000 | AD12: =AC12+AC12*$W$2 -> 20000 | AE12: =AD12+AD12*$W$2 -> 20000 | AF12: =AE12+AE12*$W$2 -> 20000 | AG12: =AF12+AF12*$W$2 -> 20000 | AH12: =AG12+AG12*$W$2 -> 20000
A13: =IF(AA13>0,"x","") -> x | B13: Nagios | D13: Existing Cost | E13: PRIMARY/DR | F13: Software | G13: Nagios | I13: 1 | L13: NJ | M13: =SUM(H13:K13) -> 1 | N13: 1 | P13: =N13*O13 -> 0 | R13: =N13 -> 1 | S13: 4000 | T13: =S13*R13 -> 4000 | V13: =P13+T13 -> 4000 | W13: =T13+T13*$W$2 -> 4000 | X13: =W13+W13*$W$2 -> 4000 | Y13: =X13+X13*$W$2 -> 4000 | Z13: =Y13+Y13*$W$2 -> 4000 | AA13: =Z13+Z13*$W$2 -> 4000 | AB13: =IF(C13="R",P13,) -> 0 | AC13: =AA13+AA13*$W$2 -> 4000 | AD13: =AC13+AC13*$W$2 -> 4000 | AE13: =AD13+AD13*$W$2 -> 4000 | AF13: =AE13+AE13*$W$2 -> 4000 | AG13: =AF13+AF13*$W$2 -> 4000 | AH13: =AG13+AG13*$W$2 -> 4000
A14: =IF(AA14>0,"x","") -> x | B14: Netbackup | D14: Existing Cost | E14: PRIMARY/DR | F14: Software | G14: Veritas | H14: 1 | L14: PA | M14: =SUM(H14:K14) -> 1 | N14: 1 | P14: =N14*O14 -> 0 | R14: =N14 -> 1 | S14: 11000 | T14: =S14*R14 -> 11000 | V14: =P14+T14 -> 11000 | W14: =T14+T14*$W$2 -> 11000 | X14: =W14+W14*$W$2 -> 11000 | Y14: =X14+X14*$W$2 -> 11000 | Z14: =Y14+Y14*$W$2 -> 11000 | AA14: =Z14+Z14*$W$2 -> 11000 | AB14: =IF(C14="R",P14,) -> 0 | AC14: =AA14+AA14*$W$2 -> 11000 | AD14: =AC14+AC14*$W$2 -> 11000 | AE14: =AD14+AD14*$W$2 -> 11000 | AF14: =AE14+AE14*$W$2 -> 11000 | AG14: =AF14+AF14*$W$2 -> 11000 | AH14: =AG14+AG14*$W$2 -> 11000
A15: =IF(AA15>0,"x","") -> x | B15: Netbackup | D15: Existing Cost | E15: PRIMARY/DR | F15: Software | G15: Veritas | I15: 1 | L15: NJ | M15: =SUM(H15:K15) -> 1 | N15: 1 | P15: =N15*O15 -> 0 | R15: =N15 -> 1 | S15: 4000 | T15: =S15*R15 -> 4000 | V15: =P15+T15 -> 4000 | W15: =T15+T15*$W$2 -> 4000 | X15: =W15+W15*$W$2 -> 4000 | Y15: =X15+X15*$W$2 -> 4000 | Z15: =Y15+Y15*$W$2 -> 4000 | AA15: =Z15+Z15*$W$2 -> 4000 | AB15: =IF(C15="R",P15,) -> 0 | AC15: =AA15+AA15*$W$2 -> 4000 | AD15: =AC15+AC15*$W$2 -> 4000 | AE15: =AD15+AD15*$W$2 -> 4000 | AF15: =AE15+AE15*$W$2 -> 4000 | AG15: =AF15+AF15*$W$2 -> 4000 | AH15: =AG15+AG15*$W$2 -> 4000
A16: =IF(AA16>0,"x","") -> x | B16: Oracle ZS3 | D16: Existing Cost | E16: PRIMARY/DR | F16: Hardware | G16: Oracle | J16: 1 | L16: VT | M16: =SUM(H16:K16) -> 1 | N16: 1 | P16: =N16*O16 -> 0 | R16: =N16 -> 1 | S16: 33000 | T16: =S16*R16 -> 33000 | V16: =P16+T16 -> 33000 | W16: =T16+T16*$W$2 -> 33000 | X16: =W16+W16*$W$2 -> 33000 | Y16: =X16+X16*$W$2 -> 33000 | Z16: =Y16+Y16*$W$2 -> 33000 | AA16: =Z16+Z16*$W$2 -> 33000 | AB16: =IF(C16="R",P16,) -> 0 | AC16: =AA16+AA16*$W$2 -> 33000 | AD16: =AC16+AC16*$W$2 -> 33000 | AE16: =AD16+AD16*$W$2 -> 33000 | AF16: =AE16+AE16*$W$2 -> 33000 | AG16: =AF16+AF16*$W$2 -> 33000 | AH16: =AG16+AG16*$W$2 -> 33000
A17: =IF(AA17>0,"x","") -> x | B17: Cisco Network Hardware | D17: Existing Cost | E17: PRIMARY/DR | F17: Hardware | G17: Cisco | H17: 1 | L17: PA | M17: =SUM(H17:K17) -> 1 | N17: 1 | P17: =N17*O17 -> 0 | R17: =N17 -> 1 | S17: 9000 | T17: =S17*R17 -> 9000 | V17: =P17+T17 -> 9000 | W17: =T17+T17*$W$2 -> 9000 | X17: =W17+W17*$W$2 -> 9000 | Y17: =X17+X17*$W$2 -> 9000 | Z17: =Y17+Y17*$W$2 -> 9000 | AA17: =Z17+Z17*$W$2 -> 9000 | AB17: =IF(C17="R",P17,) -> 0 | AC17: =AA17+AA17*$W$2 -> 9000 | AD17: =AC17+AC17*$W$2 -> 9000 | AE17: =AD17+AD17*$W$2 -> 9000 | AF17: =AE17+AE17*$W$2 -> 9000 | AG17: =AF17+AF17*$W$2 -> 9000 | AH17: =AG17+AG17*$W$2 -> 9000
A18: =IF(AA18>0,"x","") | B18: Load Balancer/DNS failover | D18: Existing Cost | E18: PRIMARY/DR | F18: Hardware | G18: F5 | I18: 1 | L18: NJ | M18: =SUM(H18:K18) -> 1 | N18: 1 | P18: =N18*O18 -> 0 | R18: =N18 -> 1 | S18: 25000 | T18: =S18*R18 -> 25000 | V18: =P18+T18 -> 25000 | W18: =T18+T18*$W$2 -> 25000
A19: =IF(AA19>0,"x","") -> x | B19: Database | D19: Existing Cost | E19: PRIMARY/DR | F19: Software | G19: Oracle | H19: 1 | L19: PA | M19: =SUM(H19:K19) -> 1 | N19: 1 | P19: =N19*O19 -> 0 | R19: =N19 -> 1 | S19: 83000 | T19: =S19*R19 -> 83000 | V19: =P19+T19 -> 83000 | W19: =T19+T19*$W$2 -> 83000 | X19: =W19+W19*$W$2 -> 83000 | Y19: =X19+X19*$W$2 -> 83000 | Z19: =Y19+Y19*$W$2 -> 83000 | AA19: =Z19+Z19*$W$2 -> 83000 | AB19: =IF(C19="R",P19,) -> 0 | AC19: =AA19+AA19*$W$2 -> 83000 | AD19: =AC19+AC19*$W$2 -> 83000 | AE19: =AD19+AD19*$W$2 -> 83000 | AF19: =AE19+AE19*$W$2 -> 83000 | AG19: =AF19+AF19*$W$2 -> 83000 | AH19: =AG19+AG19*$W$2 -> 83000
A20: =IF(AA20>0,"x","") -> x | B20: Database | D20: Existing Cost | E20: PRIMARY/DR | F20: Software | G20: Oracle | I20: 1 | L20: NJ | M20: =SUM(H20:K20) -> 1 | N20: 1 | P20: =N20*O20 -> 0 | R20: =N20 -> 1 | S20: 36000 | T20: =S20*R20 -> 36000 | V20: =P20+T20 -> 36000 | W20: =T20+T20*$W$2 -> 36000 | X20: =W20+W20*$W$2 -> 36000 | Y20: =X20+X20*$W$2 -> 36000 | Z20: =Y20+Y20*$W$2 -> 36000 | AA20: =Z20+Z20*$W$2 -> 36000 | AB20: =IF(C20="R",P20,) -> 0 | AC20: =AA20+AA20*$W$2 -> 36000 | AD20: =AC20+AC20*$W$2 -> 36000 | AE20: =AD20+AD20*$W$2 -> 36000 | AF20: =AE20+AE20*$W$2 -> 36000 | AG20: =AF20+AF20*$W$2 -> 36000 | AH20: =AG20+AG20*$W$2 -> 36000
A21: =IF(AA21>0,"x","") -> x | B21: Portal/WAS | D21: Existing Cost | E21: PRIMARY/DR | F21: Software | G21: IBM | H21: 1 | L21: PA | M21: =SUM(H21:K21) -> 1 | N21: 1 | P21: =N21*O21 -> 0 | R21: =N21 -> 1 | S21: 85000 | T21: =S21*R21 -> 85000 | V21: =P21+T21 -> 85000 | W21: =T21+T21*$W$2 -> 85000 | X21: =W21+W21*$W$2 -> 85000 | Y21: =X21+X21*$W$2 -> 85000 | Z21: =Y21+Y21*$W$2 -> 85000 | AA21: =Z21+Z21*$W$2 -> 85000 | AB21: =IF(C21="R",P21,) -> 0 | AC21: =AA21+AA21*$W$2 -> 85000 | AD21: =AC21+AC21*$W$2 -> 85000 | AE21: =AD21+AD21*$W$2 -> 85000 | AF21: =AE21+AE21*$W$2 -> 85000 | AG21: =AF21+AF21*$W$2 -> 85000 | AH21: =AG21+AG21*$W$2 -> 85000
A22: =IF(AA22>0,"x","") -> x | B22: Portal/WAS | D22: Existing Cost | E22: PRIMARY/DR | F22: Software | G22: IBM | I22: 1 | L22: NJ | M22: =SUM(H22:K22) -> 1 | N22: 1 | P22: =N22*O22 -> 0 | R22: =N22 -> 1 | S22: 33000 | T22: =S22*R22 -> 33000 | V22: =P22+T22 -> 33000 | W22: =T22+T22*$W$2 -> 33000 | X22: =W22+W22*$W$2 -> 33000 | Y22: =X22+X22*$W$2 -> 33000 | Z22: =Y22+Y22*$W$2 -> 33000 | AA22: =Z22+Z22*$W$2 -> 33000 | AB22: =IF(C22="R",P22,) -> 0 | AC22: =AA22+AA22*$W$2 -> 33000 | AD22: =AC22+AC22*$W$2 -> 33000 | AE22: =AD22+AD22*$W$2 -> 33000 | AF22: =AE22+AE22*$W$2 -> 33000 | AG22: =AF22+AF22*$W$2 -> 33000 | AH22: =AG22+AG22*$W$2 -> 33000
A23: =IF(AA23>0,"x","") -> x | B23: Business Intelligence | D23: Existing Cost | E23: PRIMARY/DR | F23: Software | G23: Pentaho | L23: PA | M23: =SUM(H23:K23) -> 0 | N23: 1 | P23: =N23*O23 -> 0 | R23: =N23 -> 1 | S23: 22000 | T23: =S23*R23 -> 22000 | V23: =P23+T23 -> 22000 | W23: =T23+T23*$W$2 -> 22000 | X23: =W23+W23*$W$2 -> 22000 | Y23: =X23+X23*$W$2 -> 22000 | Z23: =Y23+Y23*$W$2 -> 22000 | AA23: =Z23+Z23*$W$2 -> 22000 | AB23: =IF(C23="R",P23,) -> 0 | AC23: =AA23+AA23*$W$2 -> 22000 | AD23: =AC23+AC23*$W$2 -> 22000 | AE23: =AD23+AD23*$W$2 -> 22000 | AF23: =AE23+AE23*$W$2 -> 22000 | AG23: =AF23+AF23*$W$2 -> 22000 | AH23: =AG23+AG23*$W$2 -> 22000
A24: =IF(AA24>0,"x","") -> x | B24: VMware vSphere(Virtualization Hardware) | C24: R | D24: Hardware refresh | E24: Primary PROD | F24: Hardware | G24: Oracle | I24: 1 | L24: NJ | M24: =SUM(H24:K24) -> 1 | N24: 3 | O24: 16000 | P24: =N24*O24 -> 48000 | Q24: Default discount applied | R24: =N24 -> 3 | S24: =21%*O24 -> 3360 | T24: =S24*R24 -> 10080 | U24: First year support paid at the time of purchase. Assume 50% increase for the last 2 yrs | V24: =P24 -> 48000 | W24: =T24+T24*$W$2 -> 10080 | X24: =W24+W24*$W$2 -> 10080 | Y24: =X24+X24*$W$2 -> 10080 | Z24: =Y24+Y24*$W$2 -> 10080 | AA24: =Z24+Z24*$W$2 -> 10080 | AB24: =IF(C24="R",P24,) -> 48000 | AC24: =AA24+AA24*$W$2 -> 10080 | AD24: =AC24+AC24*$W$2 -> 10080 | AE24: =AD24+AD24*$W$2 -> 10080 | AF24: =AE24+AE24*$W$2 -> 10080 | AG24: =AF24+AF24*$W$2 -> 10080 | AH24: =AG24+AG24*$W$2 -> 10080
A25: =IF(AA25>0,"x","") -> x | B25: VMware vSphere(Virtualization Hardware) | C25: R | D25: Hardware refresh | E25: NON-PROD | F25: Hardware | G25: Oracle | I25: 1 | L25: NJ | M25: =SUM(H25:K25) -> 1 | N25: 4 | O25: 16000 | P25: =N25*O25 -> 64000 | Q25: Default discount applied | R25: =N25 -> 4 | S25: =21%*O25 -> 3360 | T25: =S25*R25 -> 13440 | U25: First year support paid at the time of purchase. Assume 50% increase for the last 2 yrs | V25: =P25 -> 64000 | W25: =T25+T25*$W$2 -> 13440 | X25: =W25+W25*$W$2 -> 13440 | Y25: =X25+X25*$W$2 -> 13440 | Z25: =Y25+Y25*$W$2 -> 13440 | AA25: =Z25+Z25*$W$2 -> 13440 | AB25: =IF(C25="R",P25,) -> 64000 | AC25: =AA25+AA25*$W$2 -> 13440 | AD25: =AC25+AC25*$W$2 -> 13440 | AE25: =AD25+AD25*$W$2 -> 13440 | AF25: =AE25+AE25*$W$2 -> 13440 | AG25: =AF25+AF25*$W$2 -> 13440 | AH25: =AG25+AG25*$W$2 -> 13440
A26: =IF(AA26>0,"x","") -> x | B26: DB Server Refresh | C26: R | D26: Oracle x86, OVM PROD, two node clusters | E26: PROD | F26: Hardware | G26: Oracle | I26: 1 | L26: NJ | M26: =SUM(H26:K26) -> 1 | N26: 2 | O26: 16000 | P26: =N26*O26 -> 32000 | Q26: Default discount applied | R26: =N26 -> 2 | S26: =15%*O26 -> 2400 | T26: =S26*R26 -> 4800 | U26: First year support paid at the time of purchase. Assume 50% increase for the last 2 yrs | V26: =P26+T26 -> 36800 | W26: =T26+T26*$W$2 -> 4800 | X26: =W26+W26*$W$2 -> 4800 | Y26: =X26+X26*$W$2 -> 4800 | Z26: =Y26+Y26*$W$2 -> 4800 | AA26: =Z26+Z26*$W$2 -> 4800 | AB26: =IF(C26="R",P26,) -> 32000 | AC26: =AA26+AA26*$W$2 -> 4800 | AD26: =AC26+AC26*$W$2 -> 4800 | AE26: =AD26+AD26*$W$2 -> 4800 | AF26: =AE26+AE26*$W$2 -> 4800 | AG26: =AF26+AF26*$W$2 -> 4800 | AH26: =AG26+AG26*$W$2 -> 4800
A27: =IF(AA27>0,"x","") -> x | B27: vCentre | C27: R | D27: Hardware refresh | E27: Primary | F27: Hardware | G27: Oracle | I27: 1 | L27: NJ | M27: =SUM(H27:K27) -> 1 | N27: 1 | O27: 8000 | P27: =N27*O27 -> 8000 | Q27: Default discount applied | R27: =N27 -> 1 | S27: =21%*O27 -> 1680 | T27: =S27*R27 -> 1680 | U27: First year support paid at the time of purchase. Assume 50% increase for the last 2 yrs | V27: =P27 -> 8000 | W27: =T27+T27*$W$2 -> 1680 | X27: =W27+W27*$W$2 -> 1680 | Y27: =X27+X27*$W$2 -> 1680 | Z27: =Y27+Y27*$W$2 -> 1680 | AA27: =Z27+Z27*$W$2 -> 1680 | AB27: =IF(C27="R",P27,) -> 8000 | AC27: =AA27+AA27*$W$2 -> 1680 | AD27: =AC27+AC27*$W$2 -> 1680 | AE27: =AD27+AD27*$W$2 -> 1680 | AF27: =AE27+AE27*$W$2 -> 1680 | AG27: =AF27+AF27*$W$2 -> 1680 | AH27: =AG27+AG27*$W$2 -> 1680
A28: =IF(AA28>0,"x","") | B28: Centralized Logging/Network monitor/HIDS (virtualized) | D28: Hardware refresh | E28: Primary | F28: Hardware | G28: HP | I28: 1 | L28: NJ | M28: =SUM(H28:K28) -> 1 | N28: 0 | O28: 8000 | P28: =N28*O28 -> 0 | Q28: Default discount applied | R28: =N28 -> 0 | S28: =21%*O28 -> 1680 | T28: =S28*R28 -> 0 | U28: First year support paid at the time of purchase. Assume 50% increase for the last 2 yrs | V28: =P28 -> 0 | W28: =T28+T28*$W$2 -> 0 | X28: =W28+W28*$W$2 -> 0 | Y28: =X28+X28*$W$2 -> 0 | Z28: =Y28+Y28*$W$2 -> 0 | AA28: =Z28+Z28*$W$2 -> 0 | AB28: =IF(C28="R",P28,) -> 0 | AC28: =AA28+AA28*$W$2 -> 0 | AD28: =AC28+AC28*$W$2 -> 0 | AE28: =AD28+AD28*$W$2 -> 0 | AF28: =AE28+AE28*$W$2 -> 0 | AG28: =AF28+AF28*$W$2 -> 0 | AH28: =AG28+AG28*$W$2 -> 0
A29: =IF(AA29>0,"x","") | B29: VMware storage - Oracle ZFS 3-2 | C29: R | D29: Storage Equipment for Vsphere environment | F29: Hardware | G29: Oracle | I29: 1 | L29: NJ | M29: =SUM(H29:K29) -> 1 | O29: 65000 | P29: =N29*O29 -> 0 | Q29: Default discount applied | R29: =N29 -> 0 | S29: =21%*O29 -> 13650 | T29: =S29*R29 -> 0 | U29: First year support paid at the time of purchase. Assume 50% increase for the last 2 yrs | V29: =P29+T29 -> 0 | W29: =T29+T29*$W$2 -> 0 | X29: =W29+W29*$W$2 -> 0 | Y29: =X29+X29*$W$2 -> 0 | Z29: =Y29+Y29*$W$2 -> 0 | AA29: =Z29+Z29*$W$2 -> 0 | AB29: =IF(C29="R",P29,) -> 0 | AC29: =AA29+AA29*$W$2 -> 0 | AD29: =AC29+AC29*$W$2 -> 0 | AE29: =AD29+AD29*$W$2 -> 0 | AF29: =AE29+AE29*$W$2 -> 0 | AG29: =AF29+AF29*$W$2 -> 0 | AH29: =AG29+AG29*$W$2 -> 0
A30: =IF(AA30>0,"x","") -> x | B30: Backup server | C30: R | D30: Hardware refresh | E30: Primary | F30: Hardware | G30: Oracle | I30: 1 | L30: NJ | M30: =SUM(H30:K30) -> 1 | N30: 1 | O30: 8000 | P30: =N30*O30 -> 8000 | Q30: Default discount applied | R30: =N30 -> 1 | S30: =21%*O30 -> 1680 | T30: =S30*R30 -> 1680 | U30: First year support paid at the time of purchase. Assume 50% increase for the last 2 yrs | V30: =P30 -> 8000 | W30: =T30+T30*$W$2 -> 1680 | X30: =W30+W30*$W$2 -> 1680 | Y30: =X30+X30*$W$2 -> 1680 | Z30: =Y30+Y30*$W$2 -> 1680 | AA30: =Z30+Z30*$W$2 -> 1680 | AB30: =IF(C30="R",P30,) -> 8000 | AC30: =AA30+AA30*$W$2 -> 1680 | AD30: =AC30+AC30*$W$2 -> 1680 | AE30: =AD30+AD30*$W$2 -> 1680 | AF30: =AE30+AE30*$W$2 -> 1680 | AG30: =AF30+AF30*$W$2 -> 1680 | AH30: =AG30+AG30*$W$2 -> 1680
A31: =IF(AA31>0,"x","") -> x | B31: DB Server Refresh | C31: R | D31: Hardware refresh, two node clusters | E31: NON-PROD | F31: Hardware | G31: Oracle | I31: 1 | L31: NJ | M31: =SUM(H31:K31) -> 1 | N31: 2 | O31: 16000 | P31: =N31*O31 -> 32000 | Q31: Default discount applied | R31: =N31 -> 2 | S31: =16%*O31 -> 2560 | T31: =S31*R31 -> 5120 | U31: First year support paid at the time of purchase. Assume 50% increase for the last 2 yrs | V31: =P31 -> 32000 | W31: =T31+T31*$W$2 -> 5120 | X31: =W31+W31*$W$2 -> 5120 | Y31: =X31+X31*$W$2 -> 5120 | Z31: =Y31+Y31*$W$2 -> 5120 | AA31: =Z31+Z31*$W$2 -> 5120 | AB31: =IF(C31="R",P31,) -> 32000 | AC31: =AA31+AA31*$W$2 -> 5120 | AD31: =AC31+AC31*$W$2 -> 5120 | AE31: =AD31+AD31*$W$2 -> 5120 | AF31: =AE31+AE31*$W$2 -> 5120 | AG31: =AF31+AF31*$W$2 -> 5120 | AH31: =AG31+AG31*$W$2 -> 5120
A32: =IF(AA32>0,"x","") -> x | B32: Switch - 10GB | C32: R | D32: Cisco 10GB Switch - assumed 40% discount | E32: PRIMARY | F32: Hardware | G32: Cisco | I32: 1 | L32: NJ | M32: =SUM(H32:K32) -> 1 | N32: 4 | O32: 20400 | P32: =N32*O32 -> 81600 | Q32: 40% discount | R32: =N32 -> 4 | S32: =21%*O32 -> 4284 | T32: =S32*R32 -> 17136 | U32: First year support paid at the time of purchase. Assume 50% increase for the last 2 yrs | V32: =P32+T32 -> 98736 | W32: =T32+T32*$W$2 -> 17136 | X32: =W32+W32*$W$2 -> 17136 | Y32: =X32+X32*$W$2 -> 17136 | Z32: =Y32+Y32*$W$2 -> 17136 | AA32: =Z32+Z32*$W$2 -> 17136 | AB32: =IF(C32="R",P32,) -> 81600 | AC32: =AA32+AA32*$W$2 -> 17136 | AD32: =AC32+AC32*$W$2 -> 17136 | AE32: =AD32+AD32*$W$2 -> 17136 | AF32: =AE32+AE32*$W$2 -> 17136 | AG32: =AF32+AF32*$W$2 -> 17136 | AH32: =AG32+AG32*$W$2 -> 17136
A33: =IF(AA33>0,"x","") -> x | B33: Centralized Stations VPN hardware | D33: Cisco 5506W-X | F33: Hardware | G33: Cisco | I33: 1 | L33: NJ | M33: =SUM(H33:K33) -> 1 | N33: 36 | O33: 1000 | P33: =N33*O33 -> 36000 | R33: =N33 -> 36 | S33: =21%*O33 -> 210 | T33: =S33*R33 -> 7560 | U33: First year support paid at the time of purchase. Assume 50% increase for the last 2 yrs | V33: =P33+T33 -> 43560 | W33: =T33+T33*$W$2 -> 7560 | X33: =W33+W33*$W$2 -> 7560 | Y33: =X33+X33*$W$2 -> 7560 | Z33: =Y33+Y33*$W$2 -> 7560 | AA33: =Z33+Z33*$W$2 -> 7560 | AB33: =IF(C33="R",P33,) -> 0 | AC33: =AA33+AA33*$W$2 -> 7560 | AD33: =AC33+AC33*$W$2 -> 7560 | AE33: =AD33+AD33*$W$2 -> 7560 | AF33: =AE33+AE33*$W$2 -> 7560 | AG33: =AF33+AF33*$W$2 -> 7560 | AH33: =AG33+AG33*$W$2 -> 7560
A34: =IF(AA34>0,"x","") | B34: Firewall / IPS | C34: R | D34: assumed 40% discount | F34: Hardware | G34: Cisco | I34: 1 | L34: NJ | M34: =SUM(H34:K34) -> 1 | O34: 17000 | P34: =N34*O34 -> 0 | Q34: 40% discount | R34: =N34 -> 0 | S34: =21%*O34 -> 3570 | T34: =S34*R34 -> 0 | U34: First year support paid at the time of purchase. Assume 50% increase for the last 2 yrs | V34: =P34+T34 -> 0 | W34: =T34+T34*$W$2 -> 0 | X34: =W34+W34*$W$2 -> 0 | Y34: =X34+X34*$W$2 -> 0 | Z34: =Y34+Y34*$W$2 -> 0 | AA34: =Z34+Z34*$W$2 -> 0 | AB34: =IF(C34="R",P34,) -> 0 | AC34: =AA34+AA34*$W$2 -> 0 | AD34: =AC34+AC34*$W$2 -> 0 | AE34: =AD34+AD34*$W$2 -> 0 | AF34: =AE34+AE34*$W$2 -> 0 | AG34: =AF34+AF34*$W$2 -> 0 | AH34: =AG34+AG34*$W$2 -> 0
A35: =IF(AA35>0,"x","") -> x | B35: CORTICON | D35: MPLS | F35: Telecom | I35: 1 | L35: NJ | M35: =SUM(H35:K35) -> 1 | N35: 1 | O35: 138750 | P35: =N35*O35 -> 138750 | R35: =N35 -> 1 | S35: 30525 | T35: =R35*S35 -> 30525 | U35: Yearly recurring cost startgin year 2 | V35: =P35 -> 138750 | X35: =T35+T35*$W$2 -> 30525 | Y35: =X35+X35*$W$2 -> 30525 | Z35: =Y35+Y35*$W$2 -> 30525 | AA35: =Z35+Z35*$W$2 -> 30525 | AB35: =IF(C35="R",P35,) -> 0 | AC35: =AA35+AA35*$W$2 -> 30525 | AD35: =AC35+AC35*$W$2 -> 30525 | AE35: =AD35+AD35*$W$2 -> 30525 | AF35: =AE35+AE35*$W$2 -> 30525 | AG35: =AF35+AF35*$W$2 -> 30525 | AH35: =AG35+AG35*$W$2 -> 30525
A36: =IF(AA36>0,"x","") | B36: Link to Lawrenceville office | D36: MPLS | F36: Telecom | I36: 1 | L36: NJ | M36: =SUM(H36:K36) -> 1 | N36: 0 | O36: 1000 | P36: =N36*O36 -> 0 | R36: =N36 -> 0 | S36: =12*1500 -> 18000 | T36: =R36*S36 -> 0 | V36: =P36+T36 -> 0 | W36: =T36+T36*$W$2 -> 0 | X36: =W36+W36*$W$2 -> 0 | Y36: =X36+X36*$W$2 -> 0 | Z36: =Y36+Y36*$W$2 -> 0 | AA36: =Z36+Z36*$W$2 -> 0 | AB36: =IF(C36="R",P36,) -> 0 | AC36: =AA36+AA36*$W$2 -> 0 | AD36: =AC36+AC36*$W$2 -> 0 | AE36: =AD36+AD36*$W$2 -> 0 | AF36: =AE36+AE36*$W$2 -> 0 | AG36: =AF36+AF36*$W$2 -> 0 | AH36: =AG36+AG36*$W$2 -> 0
A37: =IF(AA37>0,"x","") | B37: Link to NJ State | D37: MPLS (VPN is used) | F37: Telecom | I37: 1 | L37: NJ | M37: =SUM(H37:K37) -> 1 | N37: 0 | O37: 1000 | P37: =N37*O37 -> 0 | R37: =N37 -> 0 | S37: =12*1500 -> 18000 | T37: =R37*S37 -> 0 | V37: =P37+T37 -> 0 | W37: =T37+T37*$W$2 -> 0 | X37: =W37+W37*$W$2 -> 0 | Y37: =X37+X37*$W$2 -> 0 | Z37: =Y37+Y37*$W$2 -> 0 | AA37: =Z37+Z37*$W$2 -> 0 | AB37: =IF(C37="R",P37,) -> 0 | AC37: =AA37+AA37*$W$2 -> 0 | AD37: =AC37+AC37*$W$2 -> 0 | AE37: =AD37+AD37*$W$2 -> 0 | AF37: =AE37+AE37*$W$2 -> 0 | AG37: =AF37+AF37*$W$2 -> 0 | AH37: =AG37+AG37*$W$2 -> 0
A38: =IF(AA38>0,"x","") -> x | B38: RDBMS Mgmt Option Packs | D38: GoldenGate (for Oracle Database) | E38: PROD | F38: Software | G38: Oracle | I38: 1 | L38: NJ | M38: =SUM(H38:K38) -> 1 | N38: 6 | O38: 17500 | P38: =N38*O38*60% -> 63000 | Q38: 40% Discount | R38: =N38 -> 6 | S38: =O38*22%*60% -> 2310 | T38: =S38*R38 -> 13860 | V38: =P38+T38 -> 76860 | W38: =T38+T38*$W$2 -> 13860 | X38: =W38+W38*$W$2 -> 13860 | Y38: =X38+X38*$W$2 -> 13860 | Z38: =Y38+Y38*$W$2 -> 13860 | AA38: =Z38+Z38*$W$2 -> 13860 | AB38: =IF(C38="R",P38,) -> 0 | AC38: =AA38+AA38*$W$2 -> 13860 | AD38: =AC38+AC38*$W$2 -> 13860 | AE38: =AD38+AD38*$W$2 -> 13860 | AF38: =AE38+AE38*$W$2 -> 13860 | AG38: =AF38+AF38*$W$2 -> 13860 | AH38: =AG38+AG38*$W$2 -> 13860
A39: =IF(AA39>0,"x","") -> x | B39: RDBMS Mgmt Option Packs | D39: GoldenGate Foundation Pack (Includes Veridata, Managament Pack & GG studio) | E39: PROD | F39: Software | G39: Oracle | I39: 1 | L39: NJ | M39: =SUM(H39:K39) -> 1 | N39: 6 | O39: 7500 | P39: =N39*O39*60% -> 27000 | Q39: 50% Discount | R39: =N39 -> 6 | S39: =O39*22%*60% -> 990 | T39: =S39*R39 -> 5940 | V39: =P39+T39 -> 32940 | W39: =T39+T39*$W$2 -> 5940 | X39: =W39+W39*$W$2 -> 5940 | Y39: =X39+X39*$W$2 -> 5940 | Z39: =Y39+Y39*$W$2 -> 5940 | AA39: =Z39+Z39*$W$2 -> 5940 | AB39: =IF(C39="R",P39,) -> 0 | AC39: =AA39+AA39*$W$2 -> 5940 | AD39: =AC39+AC39*$W$2 -> 5940 | AE39: =AD39+AD39*$W$2 -> 5940 | AF39: =AE39+AE39*$W$2 -> 5940 | AG39: =AF39+AF39*$W$2 -> 5940 | AH39: =AG39+AG39*$W$2 -> 5940
A40: =IF(AA40>0,"x","") -> x | B40: RDBMS Mgmt Option Packs | D40: Multitenant Option | E40: PROD | F40: Software | G40: Oracle | I40: 1 | L40: NJ | M40: =SUM(H40:K40) -> 1 | N40: 6 | O40: 17500 | P40: =N40*O40*60% -> 63000 | Q40: 50% Discount | R40: =N40 -> 6 | S40: =O40*22%*60% -> 2310 | T40: =S40*R40 -> 13860 | V40: =P40+T40 -> 76860 | W40: =T40+T40*$W$2 -> 13860 | X40: =W40+W40*$W$2 -> 13860 | Y40: =X40+X40*$W$2 -> 13860 | Z40: =Y40+Y40*$W$2 -> 13860 | AA40: =Z40+Z40*$W$2 -> 13860 | AB40: =IF(C40="R",P40,) -> 0 | AC40: =AA40+AA40*$W$2 -> 13860 | AD40: =AC40+AC40*$W$2 -> 13860 | AE40: =AD40+AD40*$W$2 -> 13860 | AF40: =AE40+AE40*$W$2 -> 13860 | AG40: =AF40+AF40*$W$2 -> 13860 | AH40: =AG40+AG40*$W$2 -> 13860
A41: =IF(AA41>0,"x","") -> x | B41: VIN Decoder | D41: Vin Power | F41: Software | G41: VINPower | I41: 1 | L41: NJ | M41: =SUM(H41:K41) -> 1 | P41: =N41*O41 -> 0 | R41: 1 | S41: 13000 | T41: =S41*R41 -> 13000 | V41: =P41+T41 -> 13000 | W41: =T41+T41*$W$2 -> 13000 | X41: =W41+W41*$W$2 -> 13000 | Y41: =X41+X41*$W$2 -> 13000 | Z41: =Y41+Y41*$W$2 -> 13000 | AA41: =Z41+Z41*$W$2 -> 13000 | AB41: =IF(C41="R",P41,) -> 0 | AC41: =AA41+AA41*$W$2 -> 13000 | AD41: =AC41+AC41*$W$2 -> 13000 | AE41: =AD41+AD41*$W$2 -> 13000 | AF41: =AE41+AE41*$W$2 -> 13000 | AG41: =AF41+AF41*$W$2 -> 13000 | AH41: =AG41+AG41*$W$2 -> 13000
A42: =IF(AA42>0,"x","") -> x | B42: Business Intelligence | D42: Actuate, PROD, UAT, QAT, DEV | F42: Software | G42: Actuate | I42: 1 | L42: NJ | M42: =SUM(H42:K42) -> 1 | N42: 1 | O42: 76032 | P42: =N42*O42 -> 76032 | R42: 1 | S42: =O42*20% -> 15206.4 | T42: =S42*R42 -> 15206.4 | U42: Migrate to Vmware, waiting to confirm this cost | V42: =P42+T42 -> 91238.4 | W42: =T42+T42*$W$2 -> 15206.4 | X42: =W42+W42*$W$2 -> 15206.4 | Y42: =X42+X42*$W$2 -> 15206.4 | Z42: =Y42+Y42*$W$2 -> 15206.4 | AA42: =Z42+Z42*$W$2 -> 15206.4 | AB42: =IF(C42="R",P42,) -> 0 | AC42: =AA42+AA42*$W$2 -> 15206.4 | AD42: =AC42+AC42*$W$2 -> 15206.4 | AE42: =AD42+AD42*$W$2 -> 15206.4 | AF42: =AE42+AE42*$W$2 -> 15206.4 | AG42: =AF42+AF42*$W$2 -> 15206.4 | AH42: =AG42+AG42*$W$2 -> 15206.4
A43: =IF(AA43>0,"x","") -> x | B43: Business Intelligence | D43: Developer tools | F43: Software | G43: Actuate | I43: 1 | L43: NJ | M43: =SUM(H43:K43) -> 1 | N43: 1 | O43: 4000 | P43: =N43*O43 -> 4000 | R43: 1 | S43: =O43*20% -> 800 | T43: =S43*R43 -> 800 | V43: =P43+T43 -> 4800 | W43: =T43+T43*$W$2 -> 800 | X43: =W43+W43*$W$2 -> 800 | Y43: =X43+X43*$W$2 -> 800 | Z43: =Y43+Y43*$W$2 -> 800 | AA43: =Z43+Z43*$W$2 -> 800 | AB43: =IF(C43="R",P43,) -> 0 | AC43: =AA43+AA43*$W$2 -> 800 | AD43: =AC43+AC43*$W$2 -> 800 | AE43: =AD43+AD43*$W$2 -> 800 | AF43: =AE43+AE43*$W$2 -> 800 | AG43: =AF43+AF43*$W$2 -> 800 | AH43: =AG43+AG43*$W$2 -> 800
A44: =IF(AA44>0,"x","") -> x | B44: Business Intelligence | D44: Existing Cost | F44: Software | G44: Pentaho | H44: 1 | L44: PA | M44: =SUM(H44:K44) -> 1 | N44: 1 | P44: =N44*O44 -> 0 | R44: 1 | S44: 80000 | T44: =S44*R44 -> 80000 | U44: Pentaho, PROD, UAT, QAT, DEV | V44: =P44+T44 -> 80000 | W44: =T44+T44*$W$2 -> 80000 | X44: =W44+W44*$W$2 -> 80000 | Y44: =X44+X44*$W$2 -> 80000 | Z44: =Y44+Y44*$W$2 -> 80000 | AA44: =Z44+Z44*$W$2 -> 80000 | AB44: =IF(C44="R",P44,) -> 0 | AC44: =AA44+AA44*$W$2 -> 80000 | AD44: =AC44+AC44*$W$2 -> 80000 | AE44: =AD44+AD44*$W$2 -> 80000 | AF44: =AE44+AE44*$W$2 -> 80000 | AG44: =AF44+AF44*$W$2 -> 80000 | AH44: =AG44+AG44*$W$2 -> 80000
A45: =IF(AA45>0,"x","") -> x | B45: Linux subscription | D45: Satellite server | F45: Software | G45: RedHat | I45: 1 | L45: NJ | M45: =SUM(H45:K45) -> 1 | P45: =N45*O45 -> 0 | R45: 1 | S45: 10000 | T45: =S45*R45 -> 10000 | V45: =P45+T45 -> 10000 | W45: =T45+T45*$W$2 -> 10000 | X45: =W45+W45*$W$2 -> 10000 | Y45: =X45+X45*$W$2 -> 10000 | Z45: =Y45+Y45*$W$2 -> 10000 | AA45: =Z45+Z45*$W$2 -> 10000 | AB45: =IF(C45="R",P45,) -> 0 | AC45: =AA45+AA45*$W$2 -> 10000 | AD45: =AC45+AC45*$W$2 -> 10000 | AE45: =AD45+AD45*$W$2 -> 10000 | AF45: =AE45+AE45*$W$2 -> 10000 | AG45: =AF45+AF45*$W$2 -> 10000 | AH45: =AG45+AG45*$W$2 -> 10000
A46: =IF(AA46>0,"x","") -> x | B46: Linux subscription | D46: Satellite server client license | F46: Software | G46: RedHat | I46: 1 | L46: NJ | M46: =SUM(H46:K46) -> 1 | P46: =N46*O46 -> 0 | R46: 200 | S46: 192 | T46: =S46*R46 -> 38400 | V46: =P46+T46 -> 38400 | W46: =T46+T46*$W$2 -> 38400 | X46: =W46+W46*$W$2 -> 38400 | Y46: =X46+X46*$W$2 -> 38400 | Z46: =Y46+Y46*$W$2 -> 38400 | AA46: =Z46+Z46*$W$2 -> 38400 | AB46: =IF(C46="R",P46,) -> 0 | AC46: =AA46+AA46*$W$2 -> 38400 | AD46: =AC46+AC46*$W$2 -> 38400 | AE46: =AD46+AD46*$W$2 -> 38400 | AF46: =AE46+AE46*$W$2 -> 38400 | AG46: =AF46+AF46*$W$2 -> 38400 | AH46: =AG46+AG46*$W$2 -> 38400
A47: =IF(AA47>0,"x","") | B47: Windows Server | D47: Datacenter edition | E47: PRIMARY | F47: Software | G47: Microsoft | I47: 1 | L47: NJ | M47: =SUM(H47:K47) -> 1 | N47: 2 | O47: 5000 | P47: =N47*O47 -> 10000 | R47: =N47 -> 2 | T47: =S47*R47 -> 0 | V47: =P47+T47 -> 10000 | W47: =T47+T47*$W$2 -> 0 | X47: =W47+W47*$W$2 -> 0 | Y47: =X47+X47*$W$2 -> 0 | Z47: =Y47+Y47*$W$2 -> 0 | AA47: =Z47+Z47*$W$2 -> 0 | AB47: =IF(C47="R",P47,) -> 0 | AC47: =AA47+AA47*$W$2 -> 0 | AD47: =AC47+AC47*$W$2 -> 0 | AE47: =AD47+AD47*$W$2 -> 0 | AF47: =AE47+AE47*$W$2 -> 0 | AG47: =AF47+AF47*$W$2 -> 0 | AH47: =AG47+AG47*$W$2 -> 0
A48: =IF(AA48>0,"x","") | B48: Virus Scanner (Windows Defender) | D48: Virus/Malware scanner for test units | F48: Software | G48: Microsoft | I48: 1 | L48: NJ | M48: =SUM(H48:K48) -> 1 | P48: =N48*O48 -> 0 | R48: 0 | S48: 32 | T48: =S48*R48 -> 0 | V48: =P48+T48 -> 0 | W48: =T48+T48*$W$2 -> 0 | X48: =W48+W48*$W$2 -> 0 | Y48: =X48+X48*$W$2 -> 0 | Z48: =Y48+Y48*$W$2 -> 0 | AA48: =Z48+Z48*$W$2 -> 0 | AB48: =IF(C48="R",P48,) -> 0 | AC48: =AA48+AA48*$W$2 -> 0 | AD48: =AC48+AC48*$W$2 -> 0 | AE48: =AD48+AD48*$W$2 -> 0 | AF48: =AE48+AE48*$W$2 -> 0 | AG48: =AF48+AF48*$W$2 -> 0 | AH48: =AG48+AG48*$W$2 -> 0
A49: =IF(AA49>0,"x","") -> x | B49: Mobile Device Management | D49: Device management for Windows 10 devices | F49: Software | G49: Soti | I49: 1 | L49: NJ | M49: =SUM(H49:K49) -> 1 | P49: =N49*O49 -> 0 | R49: 1000 | S49: =12*4 -> 48 | T49: =S49*R49 -> 48000 | U49: Pricing provided by Gus, this is the highest cost option. | V49: =P49+T49 -> 48000 | W49: =T49+T49*$W$2 -> 48000 | X49: =W49+W49*$W$2 -> 48000 | Y49: =X49+X49*$W$2 -> 48000 | Z49: =Y49+Y49*$W$2 -> 48000 | AA49: =Z49+Z49*$W$2 -> 48000 | AB49: =IF(C49="R",P49,) -> 0 | AC49: =AA49+AA49*$W$2 -> 48000 | AD49: =AC49+AC49*$W$2 -> 48000 | AE49: =AD49+AD49*$W$2 -> 48000 | AF49: =AE49+AE49*$W$2 -> 48000 | AG49: =AF49+AF49*$W$2 -> 48000 | AH49: =AG49+AG49*$W$2 -> 48000
A50: =IF(AA50>0,"x","") | B50: Backup Software | D50: NetBackup - migration to SPARC platform | F50: Software | G50: Symantec | I50: 1 | L50: NJ | M50: =SUM(H50:K50) -> 1 | O50: 8000 | P50: =N50*O50 -> 0 | R50: =N50 -> 0 | S50: 2000 | T50: =S50*R50 -> 0 | V50: =P50+T50 -> 0 | W50: =T50+T50*$W$2 -> 0 | X50: =W50+W50*$W$2 -> 0 | Y50: =X50+X50*$W$2 -> 0 | Z50: =Y50+Y50*$W$2 -> 0 | AA50: =Z50+Z50*$W$2 -> 0 | AB50: =IF(C50="R",P50,) -> 0 | AC50: =AA50+AA50*$W$2 -> 0 | AD50: =AC50+AC50*$W$2 -> 0 | AE50: =AD50+AD50*$W$2 -> 0 | AF50: =AE50+AE50*$W$2 -> 0 | AG50: =AF50+AF50*$W$2 -> 0 | AH50: =AG50+AG50*$W$2 -> 0
A51: =IF(AA51>0,"x","") | B51: Backup client licenses | D51: Netbackup Enterprise Client (LDOMs) | F51: Software | G51: Symantec | I51: 1 | L51: NJ | M51: =SUM(H51:K51) -> 1 | O51: 2000 | P51: =N51*O51 -> 0 | R51: =N51 -> 0 | S51: =20%*O51 -> 400 | T51: =S51*R51 -> 0 | V51: =P51+T51 -> 0 | W51: =T51+T51*$W$2 -> 0 | X51: =W51+W51*$W$2 -> 0 | Y51: =X51+X51*$W$2 -> 0 | Z51: =Y51+Y51*$W$2 -> 0 | AA51: =Z51+Z51*$W$2 -> 0 | AB51: =IF(C51="R",P51,) -> 0 | AC51: =AA51+AA51*$W$2 -> 0 | AD51: =AC51+AC51*$W$2 -> 0 | AE51: =AD51+AD51*$W$2 -> 0 | AF51: =AE51+AE51*$W$2 -> 0 | AG51: =AF51+AF51*$W$2 -> 0 | AH51: =AG51+AG51*$W$2 -> 0
A52: =IF(AA52>0,"x","") -> x | B52: RDBMS Mgmt Option Packs | D52: GoldenGate (for Oracle Database) | E52: NON-PROD | F52: Software | G52: Oracle | I52: 1 | L52: NJ | M52: =SUM(H52:K52) -> 1 | N52: 150 | O52: 350 | P52: =N52*O52*60% -> 31500 | Q52: 40% Discount | R52: =N52 -> 150 | S52: =O52*22%*60% -> 46.2 | T52: =S52*R52 -> 6930 | V52: =P52+T52 -> 38430 | W52: =T52+T52*$W$2 -> 6930 | X52: =W52+W52*$W$2 -> 6930 | Y52: =X52+X52*$W$2 -> 6930 | Z52: =Y52+Y52*$W$2 -> 6930 | AA52: =Z52+Z52*$W$2 -> 6930 | AB52: =IF(C52="R",P52,) -> 0 | AC52: =AA52+AA52*$W$2 -> 6930 | AD52: =AC52+AC52*$W$2 -> 6930 | AE52: =AD52+AD52*$W$2 -> 6930 | AF52: =AE52+AE52*$W$2 -> 6930 | AG52: =AF52+AF52*$W$2 -> 6930 | AH52: =AG52+AG52*$W$2 -> 6930
A53: =IF(AA53>0,"x","") -> x | B53: RDBMS Mgmt Option Packs | D53: GoldenGate Foundation Pack (Includes Veridata, Managament Pack & GG studio) | E53: NON-PROD | F53: Software | G53: Oracle | I53: 1 | L53: NJ | M53: =SUM(H53:K53) -> 1 | N53: 150 | O53: 150 | P53: =N53*O53*60% -> 13500 | Q53: 50% Discount | R53: =N53 -> 150 | S53: =O53*22%*60% -> 19.8 | T53: =S53*R53 -> 2970 | V53: =P53+T53 -> 16470 | W53: =T53+T53*$W$2 -> 2970 | X53: =W53+W53*$W$2 -> 2970 | Y53: =X53+X53*$W$2 -> 2970 | Z53: =Y53+Y53*$W$2 -> 2970 | AA53: =Z53+Z53*$W$2 -> 2970 | AB53: =IF(C53="R",P53,) -> 0 | AC53: =AA53+AA53*$W$2 -> 2970 | AD53: =AC53+AC53*$W$2 -> 2970 | AE53: =AD53+AD53*$W$2 -> 2970 | AF53: =AE53+AE53*$W$2 -> 2970 | AG53: =AF53+AF53*$W$2 -> 2970 | AH53: =AG53+AG53*$W$2 -> 2970
A54: =IF(AA54>0,"x","") -> x | B54: RDBMS Mgmt Option Packs | D54: Multitenant Option | E54: NON-PROD | F54: Software | G54: Oracle | I54: 1 | L54: NJ | M54: =SUM(H54:K54) -> 1 | N54: 150 | O54: 350 | P54: =N54*O54*60% -> 31500 | Q54: 50% Discount | R54: =N54 -> 150 | S54: =O54*22%*60% -> 46.2 | T54: =S54*R54 -> 6930 | V54: =P54+T54 -> 38430 | W54: =T54+T54*$W$2 -> 6930 | X54: =W54+W54*$W$2 -> 6930 | Y54: =X54+X54*$W$2 -> 6930 | Z54: =Y54+Y54*$W$2 -> 6930 | AA54: =Z54+Z54*$W$2 -> 6930 | AB54: =IF(C54="R",P54,) -> 0 | AC54: =AA54+AA54*$W$2 -> 6930 | AD54: =AC54+AC54*$W$2 -> 6930 | AE54: =AD54+AD54*$W$2 -> 6930 | AF54: =AE54+AE54*$W$2 -> 6930 | AG54: =AF54+AF54*$W$2 -> 6930 | AH54: =AG54+AG54*$W$2 -> 6930
A55: =IF(AA55>0,"x","") | B55: Windows Server | D55: Datacenter edition | E55: DR | F55: Software | G55: Microsoft | I55: 1 | L55: NJ | M55: =SUM(H55:K55) -> 1 | N55: 2 | O55: 5000 | P55: =N55*O55 -> 10000 | R55: =N55 -> 2 | T55: =S55*R55 -> 0 | V55: =P55+T55 -> 10000 | W55: =T55+T55*$W$2 -> 0 | X55: =W55+W55*$W$2 -> 0 | Y55: =X55+X55*$W$2 -> 0 | Z55: =Y55+Y55*$W$2 -> 0 | AA55: =Z55+Z55*$W$2 -> 0 | AB55: =IF(C55="R",P55,) -> 0 | AC55: =AA55+AA55*$W$2 -> 0 | AD55: =AC55+AC55*$W$2 -> 0 | AE55: =AD55+AD55*$W$2 -> 0 | AF55: =AE55+AE55*$W$2 -> 0 | AG55: =AF55+AF55*$W$2 -> 0 | AH55: =AG55+AG55*$W$2 -> 0
A56: =IF(AA56>0,"x","") | B56: Backup client licenses | D56: Netbackup Enterprise Client (Vmware) | F56: Software | G56: Symantec | I56: 1 | L56: NJ | M56: =SUM(H56:K56) -> 1 | N56: 0 | O56: 2000 | P56: =N56*O56 -> 0 | R56: =N56 -> 0 | S56: =20%*O56 -> 400 | T56: =S56*R56 -> 0 | V56: =P56+T56 -> 0 | W56: =T56+T56*$W$2 -> 0 | X56: =W56+W56*$W$2 -> 0 | Y56: =X56+X56*$W$2 -> 0 | Z56: =Y56+Y56*$W$2 -> 0 | AA56: =Z56+Z56*$W$2 -> 0 | AB56: =IF(C56="R",P56,) -> 0 | AC56: =AA56+AA56*$W$2 -> 0 | AD56: =AC56+AC56*$W$2 -> 0 | AE56: =AD56+AD56*$W$2 -> 0 | AF56: =AE56+AE56*$W$2 -> 0 | AG56: =AF56+AF56*$W$2 -> 0 | AH56: =AG56+AG56*$W$2 -> 0
A57: =IF(AA57>0,"x","") | B57: Tape | D57: LTO5 | F57: Hardware | G57: TBD | H57: 0 | I57: 1 | J57: 0 | L57: NJ | M57: =SUM(H57:K57) -> 1 | N57: 300 | O57: 100 | P57: =N57*O57 -> 30000 | R57: 0 | S57: 300 | T57: =S57*R57 -> 0 | V57: =P57+T57 -> 30000 | W57: =T57+T57*$W$2 -> 0 | X57: =W57+W57*$W$2 -> 0 | Y57: =X57+X57*$W$2 -> 0 | Z57: =Y57+Y57*$W$2 -> 0 | AA57: =Z57+Z57*$W$2 -> 0 | AB57: =IF(C57="R",P57,) -> 0 | AC57: =AA57+AA57*$W$2 -> 0 | AD57: =AC57+AC57*$W$2 -> 0 | AE57: =AD57+AD57*$W$2 -> 0 | AF57: =AE57+AE57*$W$2 -> 0 | AG57: =AF57+AF57*$W$2 -> 0 | AH57: =AG57+AG57*$W$2 -> 0
A58: =IF(AA58>0,"x","") -> x | B58: Hosting | D58: Additional cabinet | E58: DR | F58: Datacenter Hosting | G58: Equinix | I58: 1 | L58: NJ | M58: =SUM(H58:K58) -> 1 | N58: 1 | O58: 3891.25 | P58: =N58*O58 -> 3891.25 | R58: 1 | S58: =2984*12*R58 -> 35808 | T58: =S58*R58 -> 35808 | U58: Needed for the equipment refresh | V58: =P58+T58 -> 39699.25 | W58: =T58+T58*$W$2 -> 35808 | X58: =W58+W58*$W$2 -> 35808 | Y58: =X58+X58*$W$2 -> 35808 | Z58: =Y58+Y58*$W$2 -> 35808 | AA58: =Z58+Z58*$W$2 -> 35808 | AB58: =IF(C58="R",P58,) -> 0 | AC58: =AA58+AA58*$W$2 -> 35808 | AD58: =AC58+AC58*$W$2 -> 35808 | AE58: =AD58+AD58*$W$2 -> 35808 | AF58: =AE58+AE58*$W$2 -> 35808 | AG58: =AF58+AF58*$W$2 -> 35808 | AH58: =AG58+AG58*$W$2 -> 35808
A59: =IF(AA59>0,"x","") -> x | B59: DB Server Refresh | D59: Oracle x86, OVM DR-PROD/DR-DTS, two node clusters | E59: DR | F59: Hardware | G59: Oracle | I59: 1 | L59: NJ | M59: =SUM(H59:K59) -> 1 | N59: 2 | O59: 16000 | P59: =N59*O59 -> 32000 | Q59: Default discount applied | R59: =N59 -> 2 | S59: =16%*O59 -> 2560 | T59: =S59*R59 -> 5120 | U59: First year paid at the time of purchase. Assume 50% increase for the last 2 yrs | V59: =P59+T59 -> 37120 | W59: =T59+T59*$W$2 -> 5120 | X59: =W59+W59*$W$2 -> 5120 | Y59: =X59+X59*$W$2 -> 5120 | Z59: =Y59+Y59*$W$2 -> 5120 | AA59: =Z59+Z59*$W$2 -> 5120 | AB59: =IF(C59="R",P59,) -> 0 | AC59: =AA59+AA59*$W$2 -> 5120 | AD59: =AC59+AC59*$W$2 -> 5120 | AE59: =AD59+AD59*$W$2 -> 5120 | AF59: =AE59+AE59*$W$2 -> 5120 | AG59: =AF59+AF59*$W$2 -> 5120 | AH59: =AG59+AG59*$W$2 -> 5120
A60: =IF(AA60>0,"x","") -> x | B60: vCentre | C60: R | D60: Hardware refresh | E60: DR | F60: Hardware | G60: Oracle | I60: 1 | L60: NJ | M60: =SUM(H60:K60) -> 1 | N60: 1 | O60: 8000 | P60: =O60*N60 -> 8000 | R60: =N60 -> 1 | S60: =21%*O60 -> 1680 | T60: =S60*R60 -> 1680 | U60: First year paid at the time of purchase. Assume 50% increase for the last 2 yrs | V60: =P60 -> 8000 | W60: =T60+T60*$W$2 -> 1680 | X60: =W60+W60*$W$2 -> 1680 | Y60: =X60+X60*$W$2 -> 1680 | Z60: =Y60+Y60*$W$2 -> 1680 | AA60: =Z60+Z60*$W$2 -> 1680 | AB60: =IF(C60="R",P60,) -> 8000 | AC60: =AA60+AA60*$W$2 -> 1680 | AD60: =AC60+AC60*$W$2 -> 1680 | AE60: =AD60+AD60*$W$2 -> 1680 | AF60: =AE60+AE60*$W$2 -> 1680 | AG60: =AF60+AF60*$W$2 -> 1680 | AH60: =AG60+AG60*$W$2 -> 1680
A61: =IF(AA61>0,"x","") | B61: Centralized Logging/Network monitor/HIDS (virtualized) | D61: Hardware refresh | E61: DR | F61: Hardware | G61: HP | I61: 1 | L61: NJ | M61: =SUM(H61:K61) -> 1 | N61: 0 | O61: 8000 | P61: =O61*N61 -> 0 | R61: =N61 -> 0 | S61: =21%*O61 -> 1680 | T61: =S61*R61 -> 0 | U61: First year paid at the time of purchase. Assume 50% increase for the last 2 yrs | V61: =P61 -> 0 | W61: =T61+T61*$W$2 -> 0 | X61: =W61+W61*$W$2 -> 0 | Y61: =X61+X61*$W$2 -> 0 | Z61: =Y61+Y61*$W$2 -> 0 | AA61: =Z61+Z61*$W$2 -> 0 | AB61: =IF(C61="R",P61,) -> 0 | AC61: =AA61+AA61*$W$2 -> 0 | AD61: =AC61+AC61*$W$2 -> 0 | AE61: =AD61+AD61*$W$2 -> 0 | AF61: =AE61+AE61*$W$2 -> 0 | AG61: =AF61+AF61*$W$2 -> 0 | AH61: =AG61+AG61*$W$2 -> 0
A62: =IF(AA62>0,"x","") | B62: VMware storage - Oracle ZFS 3-2 | C62: R | D62: Storage Equipment for Vsphere environment | F62: Hardware | G62: Oracle | I62: 1 | L62: NJ | M62: =SUM(H62:K62) -> 1 | O62: 65000 | P62: =N62*O62 -> 0 | R62: =N62 -> 0 | S62: =21%*O62 -> 13650 | T62: =S62*R62 -> 0 | V62: =P62+T62 -> 0 | W62: =T62+T62*$W$2 -> 0 | X62: =W62+W62*$W$2 -> 0 | Y62: =X62+X62*$W$2 -> 0 | Z62: =Y62+Y62*$W$2 -> 0 | AA62: =Z62+Z62*$W$2 -> 0 | AB62: =IF(C62="R",P62,) -> 0 | AC62: =AA62+AA62*$W$2 -> 0 | AD62: =AC62+AC62*$W$2 -> 0 | AE62: =AD62+AD62*$W$2 -> 0 | AF62: =AE62+AE62*$W$2 -> 0 | AG62: =AF62+AF62*$W$2 -> 0 | AH62: =AG62+AG62*$W$2 -> 0
A63: =IF(AA63>0,"x","") -> x | B63: VMware vSphere(Virtualization Hardware) | C63: R | D63: Hardware refresh | E63: DR | F63: Hardware | G63: Oracle | I63: 1 | L63: NJ | M63: =SUM(H63:K63) -> 1 | N63: 3 | O63: 16000 | P63: =N63*O63 -> 48000 | Q63: Default discount applied | R63: =N63 -> 3 | S63: =21%*O63 -> 3360 | T63: =S63*R63 -> 10080 | U63: First year support paid at the time of purchase. Assume 50% increase for the last 2 yrs | V63: =P63 -> 48000 | W63: =T63+T63*$W$2 -> 10080 | X63: =W63+W63*$W$2 -> 10080 | Y63: =X63+X63*$W$2 -> 10080 | Z63: =Y63+Y63*$W$2 -> 10080 | AA63: =Z63+Z63*$W$2 -> 10080 | AB63: =IF(C63="R",P63,) -> 48000 | AC63: =AA63+AA63*$W$2 -> 10080 | AD63: =AC63+AC63*$W$2 -> 10080 | AE63: =AD63+AD63*$W$2 -> 10080 | AF63: =AE63+AE63*$W$2 -> 10080 | AG63: =AF63+AF63*$W$2 -> 10080 | AH63: =AG63+AG63*$W$2 -> 10080
A64: =IF(AA64>0,"x","") -> x | B64: Backup server | C64: R | D64: Hardware refresh | E64: DR | F64: Hardware | G64: Oracle | I64: 1 | L64: NJ | M64: =SUM(H64:K64) -> 1 | N64: 1 | O64: 8000 | P64: =N64*O64 -> 8000 | R64: =N64 -> 1 | S64: =21%*O64 -> 1680 | T64: =S64*R64 -> 1680 | U64: First year paid at the time of purchase. Assume 50% increase for the last 2 yrs | V64: =P64 -> 8000 | W64: =T64+T64*$W$2 -> 1680 | X64: =W64+W64*$W$2 -> 1680 | Y64: =X64+X64*$W$2 -> 1680 | Z64: =Y64+Y64*$W$2 -> 1680 | AA64: =Z64+Z64*$W$2 -> 1680 | AB64: =IF(C64="R",P64,) -> 8000 | AC64: =AA64+AA64*$W$2 -> 1680 | AD64: =AC64+AC64*$W$2 -> 1680 | AE64: =AD64+AD64*$W$2 -> 1680 | AF64: =AE64+AE64*$W$2 -> 1680 | AG64: =AF64+AF64*$W$2 -> 1680 | AH64: =AG64+AG64*$W$2 -> 1680
A65: =IF(AA65>0,"x","") | B65: Tape | C65: R | D65: LTO5 | F65: Hardware | G65: TBD | H65: 0 | I65: 1 | J65: 0 | L65: NJ | M65: =SUM(H65:K65) -> 1 | N65: 150 | O65: 100 | P65: =N65*O65 -> 15000 | R65: 0 | S65: 300 | T65: =S65*R65 -> 0 | V65: =P65+T65 -> 15000 | W65: =T65+T65*$W$2 -> 0 | X65: =W65+W65*$W$2 -> 0 | Y65: =X65+X65*$W$2 -> 0 | Z65: =Y65+Y65*$W$2 -> 0 | AA65: =Z65+Z65*$W$2 -> 0 | AB65: =IF(C65="R",P65,) -> 15000 | AC65: =AA65+AA65*$W$2 -> 0 | AD65: =AC65+AC65*$W$2 -> 0 | AE65: =AD65+AD65*$W$2 -> 0 | AF65: =AE65+AE65*$W$2 -> 0 | AG65: =AF65+AF65*$W$2 -> 0 | AH65: =AG65+AG65*$W$2 -> 0
A66: =IF(AA66>0,"x","") -> x | B66: Switch - 10GB | C66: R | D66: Cisco 10GB Switch - assumed 40% discount | E66: DR | F66: Hardware | G66: Cisco | I66: 1 | L66: NJ | M66: =SUM(H66:K66) -> 1 | N66: 4 | O66: 20400 | P66: =N66*O66 -> 81600 | Q66: 40% discount | R66: =N66 -> 4 | S66: =21%*O66 -> 4284 | T66: =S66*R66 -> 17136 | U66: First year paid at the time of purchase. Assume 50% increase for the last 2 yrs | V66: =P66+T66 -> 98736 | W66: =T66+T66*$W$2 -> 17136 | X66: =W66+W66*$W$2 -> 17136 | Y66: =X66+X66*$W$2 -> 17136 | Z66: =Y66+Y66*$W$2 -> 17136 | AA66: =Z66+Z66*$W$2 -> 17136 | AB66: =IF(C66="R",P66,) -> 81600 | AC66: =AA66+AA66*$W$2 -> 17136 | AD66: =AC66+AC66*$W$2 -> 17136 | AE66: =AD66+AD66*$W$2 -> 17136 | AF66: =AE66+AE66*$W$2 -> 17136 | AG66: =AF66+AF66*$W$2 -> 17136 | AH66: =AG66+AG66*$W$2 -> 17136
A67: =IF(AA67>0,"x","") -> x | B67: Firewall / IPS | C67: R | D67: assumed 40% discount | F67: Hardware | G67: Cisco | H67: 1 | L67: PA | M67: =SUM(H67:K67) -> 1 | O67: 17000 | P67: =N67*O67 -> 0 | R67: 3 | S67: =6500/3 -> 2166.6667 | T67: =S67*R67 -> 6500 | U67: Purchased in 2018, 3 year support included | W67: =T67+T67*$W$2 -> 6500 | X67: =W67+W67*$W$2 -> 6500 | Y67: =X67+X67*$W$2 -> 6500 | Z67: =Y67+Y67*$W$2 -> 6500 | AA67: =Z67+Z67*$W$2 -> 6500 | AB67: =IF(C67="R",P67,) -> 0 | AC67: =AA67+AA67*$W$2 -> 6500 | AD67: =AC67+AC67*$W$2 -> 6500 | AE67: =AD67+AD67*$W$2 -> 6500 | AF67: =AE67+AE67*$W$2 -> 6500 | AG67: =AF67+AF67*$W$2 -> 6500 | AH67: =AG67+AG67*$W$2 -> 6500
A68: =IF(AA68>0,"x","") | B68: Internet Link | D68: Inspection facility internet link | F68: Telecom | I68: 1 | L68: NJ | M68: =SUM(H68:K68) -> 1 | N68: 0 | O68: 1000 | P68: =N68*O68 -> 0 | R68: 0 | S68: =12*300 -> 3600 | T68: =S68*R68 -> 0 | V68: =P68+T68 -> 0 | W68: =T68+T68*$W$2 -> 0 | X68: =W68+W68*$W$2 -> 0 | Y68: =X68+X68*$W$2 -> 0 | Z68: =Y68+Y68*$W$2 -> 0 | AA68: =Z68+Z68*$W$2 -> 0 | AB68: =IF(C68="R",P68,) -> 0 | AC68: =AA68+AA68*$W$2 -> 0 | AD68: =AC68+AC68*$W$2 -> 0 | AE68: =AD68+AD68*$W$2 -> 0 | AF68: =AE68+AE68*$W$2 -> 0 | AG68: =AF68+AF68*$W$2 -> 0 | AH68: =AG68+AG68*$W$2 -> 0
A69: =IF(AA69>0,"x","") | B69: Link to the State | D69: MPLS (VPN is used) | F69: Telecom | I69: 1 | L69: NJ | M69: =SUM(H69:K69) -> 1 | N69: 0 | O69: 1000 | P69: =N69*O69 -> 0 | R69: =N69 -> 0 | S69: =12*1500 -> 18000 | T69: =R69*S69 -> 0 | V69: =P69+T69 -> 0 | W69: =T69+T69*$W$2 -> 0 | X69: =W69+W69*$W$2 -> 0 | Y69: =X69+X69*$W$2 -> 0 | Z69: =Y69+Y69*$W$2 -> 0 | AA69: =Z69+Z69*$W$2 -> 0 | AB69: =IF(C69="R",P69,) -> 0 | AC69: =AA69+AA69*$W$2 -> 0 | AD69: =AC69+AC69*$W$2 -> 0 | AE69: =AD69+AD69*$W$2 -> 0 | AF69: =AE69+AE69*$W$2 -> 0 | AG69: =AF69+AF69*$W$2 -> 0 | AH69: =AG69+AG69*$W$2 -> 0
A70: =IF(AA70>0,"x","") -> x | B70: RDBMS Mgmt Option Packs | D70: GoldenGate (for Oracle Database) | E70: DR | F70: Software | G70: Oracle | I70: 1 | L70: NJ | M70: =SUM(H70:K70) -> 1 | N70: 3 | O70: 17500 | P70: =N70*O70*60% -> 31500 | Q70: 40% Discount | R70: =N70 -> 3 | S70: =O70*22%*60% -> 2310 | T70: =S70*R70 -> 6930 | V70: =P70+T70 -> 38430 | W70: =T70+T70*$W$2 -> 6930 | X70: =W70+W70*$W$2 -> 6930 | Y70: =X70+X70*$W$2 -> 6930 | Z70: =Y70+Y70*$W$2 -> 6930 | AA70: =Z70+Z70*$W$2 -> 6930 | AB70: =IF(C70="R",P70,) -> 0 | AC70: =AA70+AA70*$W$2 -> 6930 | AD70: =AC70+AC70*$W$2 -> 6930 | AE70: =AD70+AD70*$W$2 -> 6930 | AF70: =AE70+AE70*$W$2 -> 6930 | AG70: =AF70+AF70*$W$2 -> 6930 | AH70: =AG70+AG70*$W$2 -> 6930
A71: =IF(AA71>0,"x","") -> x | B71: RDBMS Mgmt Option Packs | D71: GoldenGate Foundation Pack (Includes Veridata, Managament Pack & GG studio) | E71: DR | F71: Software | G71: Oracle | I71: 1 | L71: NJ | M71: =SUM(H71:K71) -> 1 | N71: 3 | O71: 7500 | P71: =N71*O71*60% -> 13500 | Q71: 40% Discount | R71: =N71 -> 3 | S71: =O71*22%*60% -> 990 | T71: =S71*R71 -> 2970 | V71: =P71+T71 -> 16470 | W71: =T71+T71*$W$2 -> 2970 | X71: =W71+W71*$W$2 -> 2970 | Y71: =X71+X71*$W$2 -> 2970 | Z71: =Y71+Y71*$W$2 -> 2970 | AA71: =Z71+Z71*$W$2 -> 2970 | AB71: =IF(C71="R",P71,) -> 0 | AC71: =AA71+AA71*$W$2 -> 2970 | AD71: =AC71+AC71*$W$2 -> 2970 | AE71: =AD71+AD71*$W$2 -> 2970 | AF71: =AE71+AE71*$W$2 -> 2970 | AG71: =AF71+AF71*$W$2 -> 2970 | AH71: =AG71+AG71*$W$2 -> 2970
A72: =IF(AA72>0,"x","") -> x | B72: RDBMS Mgmt Option Packs | D72: Multitenant Option | E72: DR | F72: Software | G72: Oracle | I72: 1 | L72: NJ | M72: =SUM(H72:K72) -> 1 | N72: 3 | O72: 17500 | P72: =N72*O72*60% -> 31500 | Q72: 40% Discount | R72: =N72 -> 3 | S72: =O72*22%*60% -> 2310 | T72: =S72*R72 -> 6930 | V72: =P72+T72 -> 38430 | W72: =T72+T72*$W$2 -> 6930 | X72: =W72+W72*$W$2 -> 6930 | Y72: =X72+X72*$W$2 -> 6930 | Z72: =Y72+Y72*$W$2 -> 6930 | AA72: =Z72+Z72*$W$2 -> 6930 | AB72: =IF(C72="R",P72,) -> 0 | AC72: =AA72+AA72*$W$2 -> 6930 | AD72: =AC72+AC72*$W$2 -> 6930 | AE72: =AD72+AD72*$W$2 -> 6930 | AF72: =AE72+AE72*$W$2 -> 6930 | AG72: =AF72+AF72*$W$2 -> 6930 | AH72: =AG72+AG72*$W$2 -> 6930
A73: =IF(AA73>0,"x","") | B73: Windows Server | D73: Datacenter edition | F73: Software | G73: Microsoft | I73: 1 | L73: NJ | M73: =SUM(H73:K73) -> 1 | N73: 2 | O73: 5000 | P73: =N73*O73 -> 10000 | R73: =N73 -> 2 | T73: =S73*R73 -> 0 | V73: =P73+T73 -> 10000 | W73: =T73+T73*$W$2 -> 0 | X73: =W73+W73*$W$2 -> 0 | Y73: =X73+X73*$W$2 -> 0 | Z73: =Y73+Y73*$W$2 -> 0 | AA73: =Z73+Z73*$W$2 -> 0 | AB73: =IF(C73="R",P73,) -> 0 | AC73: =AA73+AA73*$W$2 -> 0 | AD73: =AC73+AC73*$W$2 -> 0 | AE73: =AD73+AD73*$W$2 -> 0 | AF73: =AE73+AE73*$W$2 -> 0 | AG73: =AF73+AF73*$W$2 -> 0 | AH73: =AG73+AG73*$W$2 -> 0
A74: =IF(AA74>0,"x","") | B74: Backup Software | D74: NetBackup - migration to SPARC platform | F74: Software | G74: Symantec | I74: 1 | L74: NJ | M74: =SUM(H74:K74) -> 1 | O74: 8000 | P74: =N74*O74 -> 0 | R74: =N74 -> 0 | S74: 2000 | T74: =S74*R74 -> 0 | V74: =P74+T74 -> 0 | W74: =T74+T74*$W$2 -> 0 | X74: =W74+W74*$W$2 -> 0 | Y74: =X74+X74*$W$2 -> 0 | Z74: =Y74+Y74*$W$2 -> 0 | AA74: =Z74+Z74*$W$2 -> 0 | AB74: =IF(C74="R",P74,) -> 0 | AC74: =AA74+AA74*$W$2 -> 0 | AD74: =AC74+AC74*$W$2 -> 0 | AE74: =AD74+AD74*$W$2 -> 0 | AF74: =AE74+AE74*$W$2 -> 0 | AG74: =AF74+AF74*$W$2 -> 0 | AH74: =AG74+AG74*$W$2 -> 0
A75: =IF(AA75>0,"x","") -> x | B75: Load Balancer/DNS failover | D75: Virtualized appliance | E75: PRIMARY/DR | F75: Software | G75: F5 | I75: 1 | L75: NJ | M75: =SUM(H75:K75) -> 1 | N75: 1 | R75: =N75 -> 1 | S75: 25000 | T75: =S75*R75 -> 25000 | U75: Replace existing physical appliances with virtualized ones. Pricing based on Ontario quote | W75: =P75+T75 -> 25000 | X75: =T75 -> 25000 | Y75: =X75+X75*$W$2 -> 25000 | Z75: =Y75+Y75*$W$2 -> 25000 | AA75: =Z75+Z75*$W$2 -> 25000 | AB75: =IF(C75="R",P75,) -> 0 | AC75: =AA75+AA75*$W$2 -> 25000 | AD75: =AC75+AC75*$W$2 -> 25000 | AE75: =AD75+AD75*$W$2 -> 25000 | AF75: =AE75+AE75*$W$2 -> 25000 | AG75: =AF75+AF75*$W$2 -> 25000 | AH75: =AG75+AG75*$W$2 -> 25000
A76: =IF(AA76>0,"x","") | B76: Backup client licenses | D76: Netbackup Enterprise Client (LDOM) | F76: Software | G76: Symantec | I76: 1 | L76: NJ | M76: =SUM(H76:K76) -> 1 | O76: 2000 | P76: =N76*O76 -> 0 | R76: =N76 -> 0 | S76: =20%*O76 -> 400 | T76: =S76*R76 -> 0 | V76: =P76+T76 -> 0 | W76: =T76+T76*$W$2 -> 0 | X76: =W76+W76*$W$2 -> 0 | Y76: =X76+X76*$W$2 -> 0 | Z76: =Y76+Y76*$W$2 -> 0 | AA76: =Z76+Z76*$W$2 -> 0 | AB76: =IF(C76="R",P76,) -> 0 | AC76: =AA76+AA76*$W$2 -> 0 | AD76: =AC76+AC76*$W$2 -> 0 | AE76: =AD76+AD76*$W$2 -> 0 | AF76: =AE76+AE76*$W$2 -> 0 | AG76: =AF76+AF76*$W$2 -> 0 | AH76: =AG76+AG76*$W$2 -> 0
B79: Grand Total | P79: =SUM(P5:P76) -> 1097873.2 | T79: =SUM(T5:T76) -> 1202888.4 | V79: =SUM(V5:V76) -> 2193296.6 | W79: =SUM(W5:W76) -> 1133230.9 | X79: =SUM(X5:X76) -> 1138755.9 | Y79: =SUM(Y5:Y76) -> 1138755.9 | Z79: =SUM(Z5:Z76) -> 1138755.9 | AA79: =SUM(AA5:AA76) -> 1138755.9 | AB79: =SUM(AB5:AB76) -> 434200 | AC79: =SUM(AC5:AC76) -> 1138755.9 | ... AG79: =SUM(AG5:AG76) -> 1138755.9 | AH79: =SUM(V79:AF79) -> 12870775
AC80: =AC79+AB79 -> 1572955.9
V81: =P79+T79-V79 -> 107465 | AB81: =SUMIF($L$5:$L$76,O86,AB$5:AB$76) -> 434200 | AD81: Check | AE81: =P79+T79*10+AB79 -> 13560957
O86: NJ | P86: =SUMIF($L$5:$L$76,O86,$P$5:$P$76) -> 1097873.2 | T86: =SUMIF($L$5:$L$76,O86,$T$5:$T$76) -> 610708.4 | V86: =SUMIF($L$5:$L$76,$O86,V$5:V$76) -> 1607616.6 | W86: =SUMIF($L$5:$L$76,$O86,W$5:W$76) -> 568790.9 | X86: =SUMIF($L$5:$L$76,$O86,X$5:X$76) -> 574315.9 | Y86: =SUMIF($L$5:$L$76,$O86,Y$5:Y$76) -> 574315.9 | Z86: =SUMIF($L$5:$L$76,$O86,Z$5:Z$76) -> 574315.9 | AA86: =SUMIF($L$5:$L$76,$O86,AA$5:AA$76) -> 574315.9 | AB86: =SUMIF($L$5:$L$76,$O86,AB$5:AB$76) -> 434200 | AC86: =SUMIF($L$5:$L$76,$O86,AC$5:AC$76) -> 574315.9 | ... AG86: =SUMIF($L$5:$L$76,$O86,AG$5:AG$76) -> 574315.9
O87: PA | P87: =SUMIF($L$5:$L$76,O87,$P$5:$P$76) -> 0 | T87: =SUMIF($L$5:$L$76,O87,$T$5:$T$76) -> 559180 | V87: =SUMIF($L$5:$L$76,$O87,V$5:V$76) -> 552680 | W87: =SUMIF($L$5:$L$76,$O87,W$5:W$76) -> 531440 | X87: =SUMIF($L$5:$L$76,$O87,X$5:X$76) -> 531440 | Y87: =SUMIF($L$5:$L$76,$O87,Y$5:Y$76) -> 531440 | Z87: =SUMIF($L$5:$L$76,$O87,Z$5:Z$76) -> 531440 | AA87: =SUMIF($L$5:$L$76,$O87,AA$5:AA$76) -> 531440 | AB87: =SUMIF($L$5:$L$76,$O87,AB$5:AB$76) -> 0 | AC87: =SUMIF($L$5:$L$76,$O87,AC$5:AC$76) -> 531440 | ... AG87: =SUMIF($L$5:$L$76,$O87,AG$5:AG$76) -> 531440
O88: VT | P88: =SUMIF($L$5:$L$76,O88,$P$5:$P$76) -> 0 | T88: =SUMIF($L$5:$L$76,O88,$T$5:$T$76) -> 33000 | V88: =SUMIF($L$5:$L$76,$O88,V$5:V$76) -> 33000 | W88: =SUMIF($L$5:$L$76,$O88,W$5:W$76) -> 33000 | X88: =SUMIF($L$5:$L$76,$O88,X$5:X$76) -> 33000 | Y88: =SUMIF($L$5:$L$76,$O88,Y$5:Y$76) -> 33000 | Z88: =SUMIF($L$5:$L$76,$O88,Z$5:Z$76) -> 33000 | AA88: =SUMIF($L$5:$L$76,$O88,AA$5:AA$76) -> 33000 | AB88: =SUMIF($L$5:$L$76,$O88,AB$5:AB$76) -> 0 | AC88: =SUMIF($L$5:$L$76,$O88,AC$5:AC$76) -> 33000 | ... AG88: =SUMIF($L$5:$L$76,$O88,AG$5:AG$76) -> 33000
T89: =SUM(T86:T88) -> 1202888.4 | V89: =SUM(V86:V88) -> 2193296.6 | W89: =SUM(W86:W88) -> 1133230.9 | X89: =SUM(X86:X88) -> 1138755.9 | Y89: =SUM(Y86:Y88) -> 1138755.9 | Z89: =SUM(Z86:Z88) -> 1138755.9 | AA89: =SUM(AA86:AA88) -> 1138755.9 | AB89: =SUM(AB86:AB88) -> 434200 | AC89: =SUM(AC86:AC88) -> 1138755.9 | ... AG89: =SUM(AG86:AG88) -> 1138755.9
T91: =SUM(T5:T76) -> 1202888.4 | V91: =V79-V89 -> 0 | W91: =W79-W89 -> 0 | X91: =X79-X89 -> 0 | Y91: =Y79-Y89 -> 0 | Z91: =Z79-Z89 -> 0 | AA91: =AA79-AA89 -> 0 | AB91: =AB79-AB89 -> 0 | AC91: =AC79-AC89 -> 0 | ... AG91: =AG79-AG89 -> 0
V94: =P86+T86-V86 -> 100965

Sheet Tablet (PIF - BUS TEAM)
A1: Existing Item ID | B1: Replacement | C1: Unit Count | D1: Est Price | F1: Totals
A3: 20-1341R | B3: Brother Printer (HL-L2350DW) | C3: 80 | D3: 99 | F3: =C3*D3 -> 7920
A4: 20-4600E | B4: Offbrand Toner | C4: 80 | D4: 25 | F4: =C4*D4 -> 2000
A5: 20-4601E | B5: Offbrand Drum | C5: 80 | D5: 25 | F5: =C5*D5 -> 2000
A6: 40-1266R | B6: DG Equipment | C6: 80 | D6: 550 | F6: =C6*D6 -> 44000
A7: 60-1121R | B7: DT Research Ruggadized 10" | C7: 80 | D7: 950 | E7: Pro Option Only | F7: =C7*D7 -> 76000
A8: 60-1121R | B8: Surface Go 10" | C8: 40 | D8: 550 | E8: Ruggedized UAG Case (This will not hold up to the rigorous shop environment) | F8: =C8*D8 -> 22000
F9: =C9*D9 -> 0
A10: 60-1125E | B10: Dell Mouse and Keyboard | C10: 80 | D10: 25 | F10: =C10*D10 -> 2000
A11: 10-1001R | B11: 2D Scanner (Premium) | C11: 80 | D11: 675 | F11: =C11*D11 -> 54000
F12: =C12*D12 -> 0
D14: Raw Price | E14: Monthly Fees + Maintenance | F14: Markup | G14: Maintence Only
A15: Total - Pro Options - Leasing | D15: =SUM($D$11,$D$10,$D$7,$D$6,$D$4,$D$3,$D$2) -> 2324 | E15: =D15/16 -> 145.25
A16: Total - Regular Option - Leasing | D16: =SUM($D$11,$D$10,$D$8,$D$6,$D$4,$D$3,$D$2) -> 1924 | E16: =D16/16 -> 120.25
A17: Total - Pro Options - Purchase | D17: =SUM($D$11,$D$10,$D$7,$D$6,$D$4,$D$3,$D$2) -> 2324 | E17: =D17 + (D17*F17) -> 3137.4 | F17: 0.35 | G17: =E17/20 -> 156.87
A18: Total - Regular Option - Purchase | D18: =SUM($D$11,$D$10,$D$8,$D$6,$D$4,$D$3,$D$2) -> 1924 | E18: =D18 + (D18*F18) -> 2597.4 | F18: 0.35 | G18: =E18/20 -> 129.87
B19: Spares
C20: cost | D20: =SUM(D3:D7,D11) -> 2324
B21: Margin | C21: 0.25 | D21: =D20*(1+C21) -> 2905
B22: qty | C22: 80 | D22: =D21*C22 -> 232400

Sheet DESKTOP (PIF)
A1: Existing Item ID | B1: Existing Price | C1: Replacement | D1: Unit Count | E1: Est Price | F1: Total
A2: 10NJ-CP600LCD-R | B2: 105.98 | C2: Cyberpower 600 W | D2: 1250 | E2: 50 | F2: =D2*E2 -> 62500
A3: 20-1341R | B3: 299.99 | C3: Brother Printer (HL-L2350DW) | D3: 1250 | E3: 99 | F3: =D3*E3 -> 123750
A4: 20-4600E | B4: 40.84 | C4: Offbrand Toner | D4: 1250 | E4: 25 | F4: =D4*E4 -> 31250
A5: 20-4601E | B5: 153.9 | C5: Offbrand Drum | D5: 1250 | E5: 25 | F5: =D5*E5 -> 31250
A6: 40-1266R | B6: 273.7 | C6: DG Equipment | D6: 1250 | E6: 550 | F6: =D6*E6 -> 687500
A7: 60-1121R | B7: 710.58 | C7: Dell PC | D7: 1250 | E7: 450 | F7: =D7*E7 -> 562500
A8: 60-1124R | B8: 129.13 | C8: Dell Ultrasharp Monitor | D8: 1250 | E8: 100 | F8: =D8*E8 -> 125000 | G8: Estimated; Quote Required.
A9: 60-1125E | B9: 17.59 | C9: Dell Mouse and Keyboard | D9: 1250 | E9: 25 | F9: =D9*E9 -> 31250
A10: 10-1001R | B10: 250 | C10: 2D Scanner (Premium) | D10: 1250 | E10: 675 | F10: =D10*E10 -> 843750
A11: 10-1001R | B11: 250 | C11: 2D Scanner | D11: 100 | E11: 385 | F11: =D11*E11 -> 38500 | G11: estimated quanity
A12: 40NJ-C748-R | B12: 16.99 | C12: Remote | D12: 500 | E12: 16.99 | F12: =D12*E12 -> 8495
C13: Windows CAL | D13: 1250 | E13: 50 | F13: =D13*E13 -> 62500 | G13: If we decide to log into a Domain Server
C14: Liceses for VPN if present | D14: 1250 | E14: 50 | F14: =D14*E14 -> 62500 | G14: Need to talk to Jakub about this
F16: Raw Price | H16: Markup | I16: Maintence Only
A17: Total - Wireless Options - Leasing | E17: =SUM($E$10,$E$9,$E$8,$E$7,$E$6,$E$4,$E$3,$E$2) -> 1974 | G17: =E17/16 -> 123.375
A18: Total - Wired Option - Leasing | E18: =SUM($E$11,$E$9,$E$8,$E$7,$E$4,$E$3,$E$6) -> 1634 | G18: =E18/16 -> 102.125
A19: Total - Wireless Options - Purchase | E19: =SUM($E$10,$E$9,$E$8,$E$7,$E$6,$E$4,$E$3,$E$2) -> 1974 | G19: =E19 + (E19*H19) -> 2664.9 | H19: 0.35 | I19: 90
A20: Total - Wired Option - Purchase | E20: =SUM($E$11,$E$9,$E$8,$E$7,$E$4,$E$3,$E$6) -> 1634 | G20: =E20 + (E20*H20) -> 2205.9 | H20: 0.35 | I20: 70
A21: Total (Raw Cost No Markup) | F21: =SUM(F2:F13) -> 2608245
C22: Spares?? | D22: QTY | E22: 1250 | F22: =F21/E22 -> 2086.596
D23: Margin | E23: 0.25 | F23: =F22*(1+E23) -> 2608.245

Sheet DESKTOP (CIF)
A1: Existing Item ID | B1: Description | C1: Existing Price | D1: Replacement | E1: unit count | F1: Est Price | G1: Total
A2: 10NJ-CP600LCD-R | B2: UPS, LANE PC & STATION CONTROLLER, CYBER POWER #CP600 | C2: 105.98 | D2: Cyberpower 600 W | F2: 50
A3: 20-1341R | B3: PRINTER, B4350 OKIDATA (LED), REPLACEMENT B4600 62427201 | C3: 299.99 | D3: Brother Printer (HL-L2350DW) | E3: 168 | F3: 99 | G3: =E3*F3 -> 16632
A4: 20-4600E | B4: TONER, OKI 4600 PRINTER. 43502301 | C4: 40.84 | D4: Offbrand Toner | E4: 168 | F4: 25 | G4: =E4*F4 -> 4200
A5: 20-4601E | B5: IMAGE DRUM, 4600 OKI PRINTER. 43501901 | C5: 153.9 | D5: Offbrand Drum | E5: 168 | F5: 25 | G5: =E5*F5 -> 4200
A6: 40-1266R | B6: MODULE, OBD II (CAN) VENTRONIX PN: 02003163 PER JP3 MODULE {ONLY | C6: 273.7 | D6: DG Equipment | E6: 93 | F6: 550 | G6: =E6*F6 -> 51150
A7: 60-1121R | B7: LANE PC DELL OPTIPLEX 360 | C7: 710.58 | D7: Dell PC | E7: 168 | F7: 450 | G7: =E7*F7 -> 75600
A8: 60-1124R | B8: DELL ULTRASHARP 1708FP FLAT PANEL MONITOR | C8: 129.13 | D8: Dell Ultrasharp Monitor | E8: 218 | F8: 100 | G8: =E8*F8 -> 21800 | H8: Estimated; Quote Required.
A9: 60-1125E | B9: DELL USB 2 BUTTON OPTICAL MOUSE | C9: 17.59 | D9: Dell Mouse and Keyboard | E9: 142 | F9: 75 | G9: =E9*F9 -> 10650
A10: 10-1001R | B10: 2D SCANNER - 4600 SERIES HH-IT4600SR051C | C10: 250 | D10: 2D Scanner | E10: 118 | F10: 675 | G10: =E10*F10 -> 79650
D11: 2D wired scanner | E11: 25 | F11: 385 | G11: =E11*F11 -> 9625
D12: Tablets | E12: 36 | F12: 950 | G12: =E12*F12 -> 34200
D13: Wireless System in the Lane | E13: 18 | F13: 100 | G13: =E13*F13 -> 1800
D14: Wireless Router | E14: 18 | F14: 100 | G14: =E14*F14 -> 1800
D15: Totals | G15: =SUM(G3:G14) -> 311307
E16: Margin | F16: 0.25 | G16: =G15*+(1+F16) -> 389133.75
